Workbook

Sheet 目次
A1: 2027年度 売上・顧客情報管理
A2: 正式目標は「中立」：年 26,000,000円・649件。いちばん大事な先行指標は ④自社ネット新規（年143件）です。
A4: タブ | B4: 何のためのタブか | C4: いつ使うか
A5: 【まず見る】
A6: =HYPERLINK("#'目次'!A1","目次") | B6: このタブ。どこに何があるか | C6: 迷ったとき
A7: =HYPERLINK("#'ダッシュボード'!A1","ダッシュボード") | B7: 今月と累計の対計画、④自社ネット新規、提携先社数、赤字月の警告 | C7: 毎朝／毎週月曜
A8: 【毎日・毎月の入力】
A9: =HYPERLINK("#'1月_売上顧客'!A1","1月_売上顧客 〜 12月_売上顧客") | B9: 1件1行で施工を記録。2行目に今月の目標、4行目に自動集計 | C9: 施工したその日
A10: =HYPERLINK("#'1月_支出成績'!A1","1月_支出成績 〜 12月_支出成績") | B10: 左が経費入力、右（M列）が月次P/L。P/Lは行が動きません | C10: 経費が出たとき／月末
A11: 【計画と実績】
A12: =HYPERLINK("#'2027年計画'!A1","2027年計画") | B12: 中立（正式目標）の月次と、保守・攻めの年計。実績で書き換えない | C12: 年初・四半期の判定ゲート
A13: =HYPERLINK("#'年間成績'!A1","年間成績") | B13: 予算対実績・月別P/L・対計画の差額。2026年売上の行だけ手入力 | C13: 毎月1日
A14: 【2027年の新しい取り組み】
A15: =HYPERLINK("#'ネット流入_週次'!A1","ネット流入_週次") | B15: SNS・ブログ・GBP・予約フォーム・受注・広告費・CPA。CPA9,500円超は赤 | C15: 毎週金曜
A16: =HYPERLINK("#'広告_段管理'!A1","広告_段管理") | B16: 段0→段3。月ごとに予算・実績・CPA・次の段へ上がるかの判定 | C16: 月末
A17: =HYPERLINK("#'提携先_パイプライン'!A1","提携先_パイプライン") | B17: アクティブ10社→15社。最終接触日・接触回数・ステージ・次アクション | C17: 接触のたび
A18: =HYPERLINK("#'協力業者_管理'!A1","協力業者_管理") | B18: 3社。契約条件・回した件数・支払額・品質（クレーム・写真提出） | C18: 月末
A19: =HYPERLINK("#'Web予約受信'!A1","Web予約受信") | B19: 予約フォーム／LPからの受信ログ。流入元(?src=)と台帳への転記チェック | C19: 受信したその日
A20: 【顧客と再販】
A21: =HYPERLINK("#'顧客管理台帳'!A1","顧客管理台帳") | B21: ヘッダー15行目・データ16行目から。2027年版は空の器（移行は年末） | C21: 施工の記録後
A22: =HYPERLINK("#'再販リスト'!A1","再販リスト") | B22: メニュー別サイクルで案内時期が来た方を抽出する器 | C22: 再販の波を出す前
A23: =HYPERLINK("#'分析_件数単価流入'!A1","分析_件数単価流入") | B23: 月別の件数・単価と流入経路別の内訳。すべて自動 | C23: 見たいとき
A24: =HYPERLINK("#'分析_流入経路とLTV'!A1","分析_流入経路とLTV") | B24: 入口ごとのLTVとリピート率。広告CPA上限9,500円の根拠 | C24: 広告の判断のとき
A25: 【運用】
A26: =HYPERLINK("#'見積ルール'!A1","見積ルール") | B26: 料金表（税込）と割引・紹介のルール。正データは data/prices.json | C26: 見積のとき
A27: =HYPERLINK("#'TODO'!A1","TODO") | B27: 状態・期限・優先度。完了しても行を消さない | C27: 随時
A28: =HYPERLINK("#'勤怠管理'!A1","勤怠管理") | B28: 日付・氏名・時間・現場数。現場人件費（原価）の根拠 | C28: 毎日
A29: =HYPERLINK("#'メモ・変更履歴'!A1","メモ・変更履歴") | B29: このスプレッドシートに手を入れた記録 | C29: 手を入れたとき
A30: =HYPERLINK("#'選択肢マスター'!A1","選択肢マスター") | B30: 全タブのプルダウンの元データ。並べ替え・行削除をしないこと | C30: 選択肢を足すとき
A32: 【この表は必ず最新にすること】
A33: タブを足したり名前を変えたら、この目次も直してください（2026年版は目次が古くて実在タブが載っていませんでした）。
A35: 【2027年の決まり】
A36: ・料金は data/prices.json が正（税込）。繁忙期加算 3,300円は5・6・7・12月
A37: ・満足度は 98.6%（209名中206名）。「98.8%」は使わない
A38: ・対応エリアは東京都・千葉県・神奈川県
A39: ・お客様に届くもの（SMS・LINE・メール・電話台本）は、台帳の最新の施工の名義と機械照合してから作る
A40: ・お客様が開くページは tools/check-public-page.py を通してから配信する
A42: シート数：42タブ ／ 生成：tools/build-sheet-2027.py

Sheet ダッシュボード
A1: ダッシュボード — 計画に乗っているか、1画面で
A2: B3 に「今月の数字（1〜12）」を入れると、その月の数字に切り替わります。
A3: 今月（1〜12を入れる） | B3: 1 | C3: ← ここだけ手で変えます
A5: ▼ 今月 | B5: 計画 | C5: 実績 | D5: 差額
A6: 売上 | B6: =INDEX('年間成績'!$B$18:$M$18,1,$B$3) | C6: =INDEX('年間成績'!$B$20:$M$20,1,$B$3) | D6: =C6-B6
A7: 件数 | B7: =INDEX('年間成績'!$B$27:$M$27,1,$B$3) | C7: =INDEX('年間成績'!$B$28:$M$28,1,$B$3) | D7: =C7-B7
A8: ★④自社ネット新規 | B8: =INDEX('年間成績'!$B$29:$M$29,1,$B$3) | C8: =INDEX('年間成績'!$B$30:$M$30,1,$B$3) | D8: =C8-B8
A9: 達成率（当月） | C9: =IFERROR(C6/B6,0)
A10: 経常利益（当月） | B10: =INDEX('年間成績'!$B$51:$M$51,1,$B$3) | C10: =INDEX('年間成績'!$B$43:$M$43,1,$B$3) | D10: =C10-B10
A12: ▼ 年間累計 | B12: 計画 | C12: 実績 | D12: 差額
A13: 売上 累計 | B13: =INDEX('年間成績'!$B$22:$M$22,1,$B$3) | C13: =INDEX('年間成績'!$B$21:$M$21,1,$B$3) | D13: =C13-B13 | E13: ※ 「今月」までの累計どうしで比べています。年計画は 売上26,000,000円・④143件・経常利益5,851,371円（中立）
A14: ★④自社ネット新規 累計 | B14: =INDEX('年間成績'!$B$49:$M$49,1,$B$3) | C14: =INDEX('年間成績'!$B$50:$M$50,1,$B$3) | D14: =C14-B14
A15: 経常利益 累計 | B15: =INDEX('年間成績'!$B$52:$M$52,1,$B$3) | C15: =INDEX('年間成績'!$B$44:$M$44,1,$B$3) | D15: =C15-B15
A17: ▼ ★④自社ネット新規（2027年の最重要KPI）
A18: 月 | B18: 1月 | C18: 2月 | D18: 3月 | E18: 4月 | F18: 5月 | G18: 6月 | H18: 7月 | I18: 8月 | J18: 9月 | K18: 10月 | L18: 11月 | M18: 12月 | N18: 年計
A19: 目標 | B19: ='年間成績'!B29 | C19: ='年間成績'!C29 | D19: ='年間成績'!D29 | E19: ='年間成績'!E29 | F19: ='年間成績'!F29 | G19: ='年間成績'!G29 | H19: ='年間成績'!H29 | I19: ='年間成績'!I29 | ... M19: ='年間成績'!M29 | N19: =SUM(B19:M19)
A20: 実績 | B20: ='年間成績'!B30 | C20: ='年間成績'!C30 | D20: ='年間成績'!D30 | E20: ='年間成績'!E30 | F20: ='年間成績'!F30 | G20: ='年間成績'!G30 | H20: ='年間成績'!H30 | I20: ='年間成績'!I30 | ... M20: ='年間成績'!M30 | N20: =SUM(B20:M20)
A21: 差 | B21: =B20-B19 | C21: =C20-C19 | D21: =D20-D19 | E21: =E20-E19 | F21: =F20-F19 | G21: =G20-G19 | H21: =H20-H19 | I21: =I20-I19 | ... N21: =N20-N19
A23: ▼ 先行指標と警告 | B23: 現在 | C23: 目標/上限 | D23: 意味
A24: 提携先 新規の成約 社数 | B24: =COUNTIF('提携先_パイプライン'!$G$5:$G$104,"成約") | C24: 5 | D24: アクティブ10社→15社。1社増えると年50万円規模で効く
A25: 協力業者 契約社数 | B25: =COUNTA('協力業者_管理'!$A$5:$A$24)-COUNTIF('協力業者_管理'!$B$5:$B$24,"未契約") | C25: 3 | D25: 1〜2月に契約、3月から稼働
A26: 経常利益がマイナスの月数 | B26: ='年間成績'!$B$14 | C26: 0 | D26: ★赤字月。0であること
A27: CPAが9,500円を超えた月数 | B27: =COUNTIF('広告_段管理'!$F$5:$F$16,">9500") | C27: 0 | D27: ★超えた月はその月で広告を止める
A28: Web予約 未対応の件数 | B28: =COUNTIF('Web予約受信'!$B$5:$B$504,"未対応") | C28: 0 | D28: ★放置ゼロ。当日中に連絡
A29: 自社（One Hitter）売上 累計 | B29: ='年間成績'!$N$56 | D29: 本舗の1円はロイヤリティで39銭出ていく。自社の1円のほうが残る
A30: 【毎月これだけ見れば足ります】① ④自社ネット新規の件数 ② 提携先の社数 ③ 累計の対計画の差額
A31: ④が動かなければ、他は全部後追いにしかなりません（docs/2027-数値目標.md §8）。

Sheet 1月_売上顧客
A1: ◆ 1月の売上・顧客。入力は 5 行目から。2行目＝今月の目標、4行目＝自動集計（数式・触らない）
A2: 今月目標(売上) | B2: 1440000 | C2: 売上 現在 | D2: =$L$4 | E2: 過不足 | F2: =D2-B2 | G2: 達成率 | H2: =IFERROR(D2/B2,0) | I2: 必要件数 | J2: 37 | K2: 件数 現在 | L2: =$E$4 | M2: 残り件数 | N2: =J2-L2 | O2: ④ネット新規 目標 | P2: 5 | Q2: ④ 現在 | R2: =$R$4
A3: 通し番号 | B3: 売上種類 | C3: 受注日 | D3: 施工日付 | E3: 流入経路 | F3: 流入元の識別子(?src=) | G3: 紹介者（顧客ID） | H3: 氏名 | I3: TEL(-無し) | J3: 郵便番号(-無し) | K3: 住所 | L3: 売上（税込） | M3: 実施メニュー | N3: 施工担当 | O3: フォローコール日 | P3: 早期予約提案 | Q3: フォローコール | R3: 備考(お客様の声) | S3: 入金経路 | T3: 入金額照合 | U3: ＯＨ打診 | V3: 本舗ロイ区分 | W3: お客様周辺/環境情報 | X3: カウント用
A4: ="▼自動集計" | B4: =COUNTIFS($B$5:$B$504,"One Hitter") | C4: =IFERROR(SUMPRODUCT(($C$5:$C$504<>"")*($D$5:$D$504<>"")*($D$5:$D$504-$C$5:$C$504))/SUMPRODUCT(($C$5:$C$504<>"")*($D$5:$D$504<>"")),0) | D4: =COUNTIFS($B$5:$B$504,"本舗") | E4: =COUNTA($D$5:$D$504) | F4: =IFERROR(SUM($L$5:$L$504)/COUNTA($D$5:$D$504),0) | G4: =COUNTA($G$5:$G$504) | H4: =IFERROR(SUMIFS($L$5:$L$504,$B$5:$B$504,"One Hitter")/COUNTIFS($B$5:$B$504,"One Hitter"),0) | I4: =IFERROR(SUMIFS($L$5:$L$504,$B$5:$B$504,"本舗")/COUNTIFS($B$5:$B$504,"本舗"),0) | J4: =SUMIFS($L$5:$L$504,$B$5:$B$504,"One Hitter") | K4: =SUMIFS($L$5:$L$504,$B$5:$B$504,"本舗") | L4: =SUM($L$5:$L$504) | R4: =COUNTIFS($E$5:$E$504,"HP")+COUNTIFS($E$5:$E$504,"LP")+COUNTIFS($E$5:$E$504,"SNS")+COUNTIFS($E$5:$E$504,"GBP(地図検索)")+COUNTIFS($E$5:$E$504,"公式LINE")+COUNTIFS($E$5:$E$504,"アフィリエイト")+COUNTIFS($E$5:$E$504,"LINE/SMS再販")+COUNTIFS($E$5:$E$504,"SMS")+COUNTIFS($E$5:$E$504,"広告") | S4: =SUMIFS($L$5:$L$504,$E$5:$E$504,"HP")+SUMIFS($L$5:$L$504,$E$5:$E$504,"LP")+SUMIFS($L$5:$L$504,$E$5:$E$504,"SNS")+SUMIFS($L$5:$L$504,$E$5:$E$504,"GBP(地図検索)")+SUMIFS($L$5:$L$504,$E$5:$E$504,"公式LINE")+SUMIFS($L$5:$L$504,$E$5:$E$504,"アフィリエイト")+SUMIFS($L$5:$L$504,$E$5:$E$504,"LINE/SMS再販")+SUMIFS($L$5:$L$504,$E$5:$E$504,"SMS")+SUMIFS($L$5:$L$504,$E$5:$E$504,"広告")

Sheet 2月_売上顧客
A1: ◆ 2月の売上・顧客。入力は 5 行目から。2行目＝今月の目標、4行目＝自動集計（数式・触らない）
A2: 今月目標(売上) | B2: 1280000 | C2: 売上 現在 | D2: =$L$4 | E2: 過不足 | F2: =D2-B2 | G2: 達成率 | H2: =IFERROR(D2/B2,0) | I2: 必要件数 | J2: 32 | K2: 件数 現在 | L2: =$E$4 | M2: 残り件数 | N2: =J2-L2 | O2: ④ネット新規 目標 | P2: 5 | Q2: ④ 現在 | R2: =$R$4
A3: 通し番号 | B3: 売上種類 | C3: 受注日 | D3: 施工日付 | E3: 流入経路 | F3: 流入元の識別子(?src=) | G3: 紹介者（顧客ID） | H3: 氏名 | I3: TEL(-無し) | J3: 郵便番号(-無し) | K3: 住所 | L3: 売上（税込） | M3: 実施メニュー | N3: 施工担当 | O3: フォローコール日 | P3: 早期予約提案 | Q3: フォローコール | R3: 備考(お客様の声) | S3: 入金経路 | T3: 入金額照合 | U3: ＯＨ打診 | V3: 本舗ロイ区分 | W3: お客様周辺/環境情報 | X3: カウント用
A4: ="▼自動集計" | B4: =COUNTIFS($B$5:$B$504,"One Hitter") | C4: =IFERROR(SUMPRODUCT(($C$5:$C$504<>"")*($D$5:$D$504<>"")*($D$5:$D$504-$C$5:$C$504))/SUMPRODUCT(($C$5:$C$504<>"")*($D$5:$D$504<>"")),0) | D4: =COUNTIFS($B$5:$B$504,"本舗") | E4: =COUNTA($D$5:$D$504) | F4: =IFERROR(SUM($L$5:$L$504)/COUNTA($D$5:$D$504),0) | G4: =COUNTA($G$5:$G$504) | H4: =IFERROR(SUMIFS($L$5:$L$504,$B$5:$B$504,"One Hitter")/COUNTIFS($B$5:$B$504,"One Hitter"),0) | I4: =IFERROR(SUMIFS($L$5:$L$504,$B$5:$B$504,"本舗")/COUNTIFS($B$5:$B$504,"本舗"),0) | J4: =SUMIFS($L$5:$L$504,$B$5:$B$504,"One Hitter") | K4: =SUMIFS($L$5:$L$504,$B$5:$B$504,"本舗") | L4: =SUM($L$5:$L$504) | R4: =COUNTIFS($E$5:$E$504,"HP")+COUNTIFS($E$5:$E$504,"LP")+COUNTIFS($E$5:$E$504,"SNS")+COUNTIFS($E$5:$E$504,"GBP(地図検索)")+COUNTIFS($E$5:$E$504,"公式LINE")+COUNTIFS($E$5:$E$504,"アフィリエイト")+COUNTIFS($E$5:$E$504,"LINE/SMS再販")+COUNTIFS($E$5:$E$504,"SMS")+COUNTIFS($E$5:$E$504,"広告") | S4: =SUMIFS($L$5:$L$504,$E$5:$E$504,"HP")+SUMIFS($L$5:$L$504,$E$5:$E$504,"LP")+SUMIFS($L$5:$L$504,$E$5:$E$504,"SNS")+SUMIFS($L$5:$L$504,$E$5:$E$504,"GBP(地図検索)")+SUMIFS($L$5:$L$504,$E$5:$E$504,"公式LINE")+SUMIFS($L$5:$L$504,$E$5:$E$504,"アフィリエイト")+SUMIFS($L$5:$L$504,$E$5:$E$504,"LINE/SMS再販")+SUMIFS($L$5:$L$504,$E$5:$E$504,"SMS")+SUMIFS($L$5:$L$504,$E$5:$E$504,"広告")

Sheet 3月_売上顧客
A1: ◆ 3月の売上・顧客。入力は 5 行目から。2行目＝今月の目標、4行目＝自動集計（数式・触らない）
A2: 今月目標(売上) | B2: 1850000 | C2: 売上 現在 | D2: =$L$4 | E2: 過不足 | F2: =D2-B2 | G2: 達成率 | H2: =IFERROR(D2/B2,0) | I2: 必要件数 | J2: 46 | K2: 件数 現在 | L2: =$E$4 | M2: 残り件数 | N2: =J2-L2 | O2: ④ネット新規 目標 | P2: 8 | Q2: ④ 現在 | R2: =$R$4
A3: 通し番号 | B3: 売上種類 | C3: 受注日 | D3: 施工日付 | E3: 流入経路 | F3: 流入元の識別子(?src=) | G3: 紹介者（顧客ID） | H3: 氏名 | I3: TEL(-無し) | J3: 郵便番号(-無し) | K3: 住所 | L3: 売上（税込） | M3: 実施メニュー | N3: 施工担当 | O3: フォローコール日 | P3: 早期予約提案 | Q3: フォローコール | R3: 備考(お客様の声) | S3: 入金経路 | T3: 入金額照合 | U3: ＯＨ打診 | V3: 本舗ロイ区分 | W3: お客様周辺/環境情報 | X3: カウント用
A4: ="▼自動集計" | B4: =COUNTIFS($B$5:$B$504,"One Hitter") | C4: =IFERROR(SUMPRODUCT(($C$5:$C$504<>"")*($D$5:$D$504<>"")*($D$5:$D$504-$C$5:$C$504))/SUMPRODUCT(($C$5:$C$504<>"")*($D$5:$D$504<>"")),0) | D4: =COUNTIFS($B$5:$B$504,"本舗") | E4: =COUNTA($D$5:$D$504) | F4: =IFERROR(SUM($L$5:$L$504)/COUNTA($D$5:$D$504),0) | G4: =COUNTA($G$5:$G$504) | H4: =IFERROR(SUMIFS($L$5:$L$504,$B$5:$B$504,"One Hitter")/COUNTIFS($B$5:$B$504,"One Hitter"),0) | I4: =IFERROR(SUMIFS($L$5:$L$504,$B$5:$B$504,"本舗")/COUNTIFS($B$5:$B$504,"本舗"),0) | J4: =SUMIFS($L$5:$L$504,$B$5:$B$504,"One Hitter") | K4: =SUMIFS($L$5:$L$504,$B$5:$B$504,"本舗") | L4: =SUM($L$5:$L$504) | R4: =COUNTIFS($E$5:$E$504,"HP")+COUNTIFS($E$5:$E$504,"LP")+COUNTIFS($E$5:$E$504,"SNS")+COUNTIFS($E$5:$E$504,"GBP(地図検索)")+COUNTIFS($E$5:$E$504,"公式LINE")+COUNTIFS($E$5:$E$504,"アフィリエイト")+COUNTIFS($E$5:$E$504,"LINE/SMS再販")+COUNTIFS($E$5:$E$504,"SMS")+COUNTIFS($E$5:$E$504,"広告") | S4: =SUMIFS($L$5:$L$504,$E$5:$E$504,"HP")+SUMIFS($L$5:$L$504,$E$5:$E$504,"LP")+SUMIFS($L$5:$L$504,$E$5:$E$504,"SNS")+SUMIFS($L$5:$L$504,$E$5:$E$504,"GBP(地図検索)")+SUMIFS($L$5:$L$504,$E$5:$E$504,"公式LINE")+SUMIFS($L$5:$L$504,$E$5:$E$504,"アフィリエイト")+SUMIFS($L$5:$L$504,$E$5:$E$504,"LINE/SMS再販")+SUMIFS($L$5:$L$504,$E$5:$E$504,"SMS")+SUMIFS($L$5:$L$504,$E$5:$E$504,"広告")

Sheet 4月_売上顧客
A1: ◆ 4月の売上・顧客。入力は 5 行目から。2行目＝今月の目標、4行目＝自動集計（数式・触らない）
A2: 今月目標(売上) | B2: 2260000 | C2: 売上 現在 | D2: =$L$4 | E2: 過不足 | F2: =D2-B2 | G2: 達成率 | H2: =IFERROR(D2/B2,0) | I2: 必要件数 | J2: 57 | K2: 件数 現在 | L2: =$E$4 | M2: 残り件数 | N2: =J2-L2 | O2: ④ネット新規 目標 | P2: 10 | Q2: ④ 現在 | R2: =$R$4
A3: 通し番号 | B3: 売上種類 | C3: 受注日 | D3: 施工日付 | E3: 流入経路 | F3: 流入元の識別子(?src=) | G3: 紹介者（顧客ID） | H3: 氏名 | I3: TEL(-無し) | J3: 郵便番号(-無し) | K3: 住所 | L3: 売上（税込） | M3: 実施メニュー | N3: 施工担当 | O3: フォローコール日 | P3: 早期予約提案 | Q3: フォローコール | R3: 備考(お客様の声) | S3: 入金経路 | T3: 入金額照合 | U3: ＯＨ打診 | V3: 本舗ロイ区分 | W3: お客様周辺/環境情報 | X3: カウント用
A4: ="▼自動集計" | B4: =COUNTIFS($B$5:$B$504,"One Hitter") | C4: =IFERROR(SUMPRODUCT(($C$5:$C$504<>"")*($D$5:$D$504<>"")*($D$5:$D$504-$C$5:$C$504))/SUMPRODUCT(($C$5:$C$504<>"")*($D$5:$D$504<>"")),0) | D4: =COUNTIFS($B$5:$B$504,"本舗") | E4: =COUNTA($D$5:$D$504) | F4: =IFERROR(SUM($L$5:$L$504)/COUNTA($D$5:$D$504),0) | G4: =COUNTA($G$5:$G$504) | H4: =IFERROR(SUMIFS($L$5:$L$504,$B$5:$B$504,"One Hitter")/COUNTIFS($B$5:$B$504,"One Hitter"),0) | I4: =IFERROR(SUMIFS($L$5:$L$504,$B$5:$B$504,"本舗")/COUNTIFS($B$5:$B$504,"本舗"),0) | J4: =SUMIFS($L$5:$L$504,$B$5:$B$504,"One Hitter") | K4: =SUMIFS($L$5:$L$504,$B$5:$B$504,"本舗") | L4: =SUM($L$5:$L$504) | R4: =COUNTIFS($E$5:$E$504,"HP")+COUNTIFS($E$5:$E$504,"LP")+COUNTIFS($E$5:$E$504,"SNS")+COUNTIFS($E$5:$E$504,"GBP(地図検索)")+COUNTIFS($E$5:$E$504,"公式LINE")+COUNTIFS($E$5:$E$504,"アフィリエイト")+COUNTIFS($E$5:$E$504,"LINE/SMS再販")+COUNTIFS($E$5:$E$504,"SMS")+COUNTIFS($E$5:$E$504,"広告") | S4: =SUMIFS($L$5:$L$504,$E$5:$E$504,"HP")+SUMIFS($L$5:$L$504,$E$5:$E$504,"LP")+SUMIFS($L$5:$L$504,$E$5:$E$504,"SNS")+SUMIFS($L$5:$L$504,$E$5:$E$504,"GBP(地図検索)")+SUMIFS($L$5:$L$504,$E$5:$E$504,"公式LINE")+SUMIFS($L$5:$L$504,$E$5:$E$504,"アフィリエイト")+SUMIFS($L$5:$L$504,$E$5:$E$504,"LINE/SMS再販")+SUMIFS($L$5:$L$504,$E$5:$E$504,"SMS")+SUMIFS($L$5:$L$504,$E$5:$E$504,"広告")

Sheet 5月_売上顧客
A1: ◆ 5月の売上・顧客。入力は 5 行目から。2行目＝今月の目標、4行目＝自動集計（数式・触らない）
A2: 今月目標(売上) | B2: 2890000 | C2: 売上 現在 | D2: =$L$4 | E2: 過不足 | F2: =D2-B2 | G2: 達成率 | H2: =IFERROR(D2/B2,0) | I2: 必要件数 | J2: 70 | K2: 件数 現在 | L2: =$E$4 | M2: 残り件数 | N2: =J2-L2 | O2: ④ネット新規 目標 | P2: 14 | Q2: ④ 現在 | R2: =$R$4
A3: 通し番号 | B3: 売上種類 | C3: 受注日 | D3: 施工日付 | E3: 流入経路 | F3: 流入元の識別子(?src=) | G3: 紹介者（顧客ID） | H3: 氏名 | I3: TEL(-無し) | J3: 郵便番号(-無し) | K3: 住所 | L3: 売上（税込） | M3: 実施メニュー | N3: 施工担当 | O3: フォローコール日 | P3: 早期予約提案 | Q3: フォローコール | R3: 備考(お客様の声) | S3: 入金経路 | T3: 入金額照合 | U3: ＯＨ打診 | V3: 本舗ロイ区分 | W3: お客様周辺/環境情報 | X3: カウント用
A4: ="▼自動集計" | B4: =COUNTIFS($B$5:$B$504,"One Hitter") | C4: =IFERROR(SUMPRODUCT(($C$5:$C$504<>"")*($D$5:$D$504<>"")*($D$5:$D$504-$C$5:$C$504))/SUMPRODUCT(($C$5:$C$504<>"")*($D$5:$D$504<>"")),0) | D4: =COUNTIFS($B$5:$B$504,"本舗") | E4: =COUNTA($D$5:$D$504) | F4: =IFERROR(SUM($L$5:$L$504)/COUNTA($D$5:$D$504),0) | G4: =COUNTA($G$5:$G$504) | H4: =IFERROR(SUMIFS($L$5:$L$504,$B$5:$B$504,"One Hitter")/COUNTIFS($B$5:$B$504,"One Hitter"),0) | I4: =IFERROR(SUMIFS($L$5:$L$504,$B$5:$B$504,"本舗")/COUNTIFS($B$5:$B$504,"本舗"),0) | J4: =SUMIFS($L$5:$L$504,$B$5:$B$504,"One Hitter") | K4: =SUMIFS($L$5:$L$504,$B$5:$B$504,"本舗") | L4: =SUM($L$5:$L$504) | R4: =COUNTIFS($E$5:$E$504,"HP")+COUNTIFS($E$5:$E$504,"LP")+COUNTIFS($E$5:$E$504,"SNS")+COUNTIFS($E$5:$E$504,"GBP(地図検索)")+COUNTIFS($E$5:$E$504,"公式LINE")+COUNTIFS($E$5:$E$504,"アフィリエイト")+COUNTIFS($E$5:$E$504,"LINE/SMS再販")+COUNTIFS($E$5:$E$504,"SMS")+COUNTIFS($E$5:$E$504,"広告") | S4: =SUMIFS($L$5:$L$504,$E$5:$E$504,"HP")+SUMIFS($L$5:$L$504,$E$5:$E$504,"LP")+SUMIFS($L$5:$L$504,$E$5:$E$504,"SNS")+SUMIFS($L$5:$L$504,$E$5:$E$504,"GBP(地図検索)")+SUMIFS($L$5:$L$504,$E$5:$E$504,"公式LINE")+SUMIFS($L$5:$L$504,$E$5:$E$504,"アフィリエイト")+SUMIFS($L$5:$L$504,$E$5:$E$504,"LINE/SMS再販")+SUMIFS($L$5:$L$504,$E$5:$E$504,"SMS")+SUMIFS($L$5:$L$504,$E$5:$E$504,"広告")

Sheet 6月_売上顧客
A1: ◆ 6月の売上・顧客。入力は 5 行目から。2行目＝今月の目標、4行目＝自動集計（数式・触らない）
A2: 今月目標(売上) | B2: 3400000 | C2: 売上 現在 | D2: =$L$4 | E2: 過不足 | F2: =D2-B2 | G2: 達成率 | H2: =IFERROR(D2/B2,0) | I2: 必要件数 | J2: 82 | K2: 件数 現在 | L2: =$E$4 | M2: 残り件数 | N2: =J2-L2 | O2: ④ネット新規 目標 | P2: 17 | Q2: ④ 現在 | R2: =$R$4
A3: 通し番号 | B3: 売上種類 | C3: 受注日 | D3: 施工日付 | E3: 流入経路 | F3: 流入元の識別子(?src=) | G3: 紹介者（顧客ID） | H3: 氏名 | I3: TEL(-無し) | J3: 郵便番号(-無し) | K3: 住所 | L3: 売上（税込） | M3: 実施メニュー | N3: 施工担当 | O3: フォローコール日 | P3: 早期予約提案 | Q3: フォローコール | R3: 備考(お客様の声) | S3: 入金経路 | T3: 入金額照合 | U3: ＯＨ打診 | V3: 本舗ロイ区分 | W3: お客様周辺/環境情報 | X3: カウント用
A4: ="▼自動集計" | B4: =COUNTIFS($B$5:$B$504,"One Hitter") | C4: =IFERROR(SUMPRODUCT(($C$5:$C$504<>"")*($D$5:$D$504<>"")*($D$5:$D$504-$C$5:$C$504))/SUMPRODUCT(($C$5:$C$504<>"")*($D$5:$D$504<>"")),0) | D4: =COUNTIFS($B$5:$B$504,"本舗") | E4: =COUNTA($D$5:$D$504) | F4: =IFERROR(SUM($L$5:$L$504)/COUNTA($D$5:$D$504),0) | G4: =COUNTA($G$5:$G$504) | H4: =IFERROR(SUMIFS($L$5:$L$504,$B$5:$B$504,"One Hitter")/COUNTIFS($B$5:$B$504,"One Hitter"),0) | I4: =IFERROR(SUMIFS($L$5:$L$504,$B$5:$B$504,"本舗")/COUNTIFS($B$5:$B$504,"本舗"),0) | J4: =SUMIFS($L$5:$L$504,$B$5:$B$504,"One Hitter") | K4: =SUMIFS($L$5:$L$504,$B$5:$B$504,"本舗") | L4: =SUM($L$5:$L$504) | R4: =COUNTIFS($E$5:$E$504,"HP")+COUNTIFS($E$5:$E$504,"LP")+COUNTIFS($E$5:$E$504,"SNS")+COUNTIFS($E$5:$E$504,"GBP(地図検索)")+COUNTIFS($E$5:$E$504,"公式LINE")+COUNTIFS($E$5:$E$504,"アフィリエイト")+COUNTIFS($E$5:$E$504,"LINE/SMS再販")+COUNTIFS($E$5:$E$504,"SMS")+COUNTIFS($E$5:$E$504,"広告") | S4: =SUMIFS($L$5:$L$504,$E$5:$E$504,"HP")+SUMIFS($L$5:$L$504,$E$5:$E$504,"LP")+SUMIFS($L$5:$L$504,$E$5:$E$504,"SNS")+SUMIFS($L$5:$L$504,$E$5:$E$504,"GBP(地図検索)")+SUMIFS($L$5:$L$504,$E$5:$E$504,"公式LINE")+SUMIFS($L$5:$L$504,$E$5:$E$504,"アフィリエイト")+SUMIFS($L$5:$L$504,$E$5:$E$504,"LINE/SMS再販")+SUMIFS($L$5:$L$504,$E$5:$E$504,"SMS")+SUMIFS($L$5:$L$504,$E$5:$E$504,"広告")

Sheet 7月_売上顧客
A1: ◆ 7月の売上・顧客。入力は 5 行目から。2行目＝今月の目標、4行目＝自動集計（数式・触らない）
A2: 今月目標(売上) | B2: 2740000 | C2: 売上 現在 | D2: =$L$4 | E2: 過不足 | F2: =D2-B2 | G2: 達成率 | H2: =IFERROR(D2/B2,0) | I2: 必要件数 | J2: 68 | K2: 件数 現在 | L2: =$E$4 | M2: 残り件数 | N2: =J2-L2 | O2: ④ネット新規 目標 | P2: 15 | Q2: ④ 現在 | R2: =$R$4
A3: 通し番号 | B3: 売上種類 | C3: 受注日 | D3: 施工日付 | E3: 流入経路 | F3: 流入元の識別子(?src=) | G3: 紹介者（顧客ID） | H3: 氏名 | I3: TEL(-無し) | J3: 郵便番号(-無し) | K3: 住所 | L3: 売上（税込） | M3: 実施メニュー | N3: 施工担当 | O3: フォローコール日 | P3: 早期予約提案 | Q3: フォローコール | R3: 備考(お客様の声) | S3: 入金経路 | T3: 入金額照合 | U3: ＯＨ打診 | V3: 本舗ロイ区分 | W3: お客様周辺/環境情報 | X3: カウント用
A4: ="▼自動集計" | B4: =COUNTIFS($B$5:$B$504,"One Hitter") | C4: =IFERROR(SUMPRODUCT(($C$5:$C$504<>"")*($D$5:$D$504<>"")*($D$5:$D$504-$C$5:$C$504))/SUMPRODUCT(($C$5:$C$504<>"")*($D$5:$D$504<>"")),0) | D4: =COUNTIFS($B$5:$B$504,"本舗") | E4: =COUNTA($D$5:$D$504) | F4: =IFERROR(SUM($L$5:$L$504)/COUNTA($D$5:$D$504),0) | G4: =COUNTA($G$5:$G$504) | H4: =IFERROR(SUMIFS($L$5:$L$504,$B$5:$B$504,"One Hitter")/COUNTIFS($B$5:$B$504,"One Hitter"),0) | I4: =IFERROR(SUMIFS($L$5:$L$504,$B$5:$B$504,"本舗")/COUNTIFS($B$5:$B$504,"本舗"),0) | J4: =SUMIFS($L$5:$L$504,$B$5:$B$504,"One Hitter") | K4: =SUMIFS($L$5:$L$504,$B$5:$B$504,"本舗") | L4: =SUM($L$5:$L$504) | R4: =COUNTIFS($E$5:$E$504,"HP")+COUNTIFS($E$5:$E$504,"LP")+COUNTIFS($E$5:$E$504,"SNS")+COUNTIFS($E$5:$E$504,"GBP(地図検索)")+COUNTIFS($E$5:$E$504,"公式LINE")+COUNTIFS($E$5:$E$504,"アフィリエイト")+COUNTIFS($E$5:$E$504,"LINE/SMS再販")+COUNTIFS($E$5:$E$504,"SMS")+COUNTIFS($E$5:$E$504,"広告") | S4: =SUMIFS($L$5:$L$504,$E$5:$E$504,"HP")+SUMIFS($L$5:$L$504,$E$5:$E$504,"LP")+SUMIFS($L$5:$L$504,$E$5:$E$504,"SNS")+SUMIFS($L$5:$L$504,$E$5:$E$504,"GBP(地図検索)")+SUMIFS($L$5:$L$504,$E$5:$E$504,"公式LINE")+SUMIFS($L$5:$L$504,$E$5:$E$504,"アフィリエイト")+SUMIFS($L$5:$L$504,$E$5:$E$504,"LINE/SMS再販")+SUMIFS($L$5:$L$504,$E$5:$E$504,"SMS")+SUMIFS($L$5:$L$504,$E$5:$E$504,"広告")

Sheet 8月_売上顧客
A1: ◆ 8月の売上・顧客。入力は 5 行目から。2行目＝今月の目標、4行目＝自動集計（数式・触らない）
A2: 今月目標(売上) | B2: 1600000 | C2: 売上 現在 | D2: =$L$4 | E2: 過不足 | F2: =D2-B2 | G2: 達成率 | H2: =IFERROR(D2/B2,0) | I2: 必要件数 | J2: 42 | K2: 件数 現在 | L2: =$E$4 | M2: 残り件数 | N2: =J2-L2 | O2: ④ネット新規 目標 | P2: 10 | Q2: ④ 現在 | R2: =$R$4
A3: 通し番号 | B3: 売上種類 | C3: 受注日 | D3: 施工日付 | E3: 流入経路 | F3: 流入元の識別子(?src=) | G3: 紹介者（顧客ID） | H3: 氏名 | I3: TEL(-無し) | J3: 郵便番号(-無し) | K3: 住所 | L3: 売上（税込） | M3: 実施メニュー | N3: 施工担当 | O3: フォローコール日 | P3: 早期予約提案 | Q3: フォローコール | R3: 備考(お客様の声) | S3: 入金経路 | T3: 入金額照合 | U3: ＯＨ打診 | V3: 本舗ロイ区分 | W3: お客様周辺/環境情報 | X3: カウント用
A4: ="▼自動集計" | B4: =COUNTIFS($B$5:$B$504,"One Hitter") | C4: =IFERROR(SUMPRODUCT(($C$5:$C$504<>"")*($D$5:$D$504<>"")*($D$5:$D$504-$C$5:$C$504))/SUMPRODUCT(($C$5:$C$504<>"")*($D$5:$D$504<>"")),0) | D4: =COUNTIFS($B$5:$B$504,"本舗") | E4: =COUNTA($D$5:$D$504) | F4: =IFERROR(SUM($L$5:$L$504)/COUNTA($D$5:$D$504),0) | G4: =COUNTA($G$5:$G$504) | H4: =IFERROR(SUMIFS($L$5:$L$504,$B$5:$B$504,"One Hitter")/COUNTIFS($B$5:$B$504,"One Hitter"),0) | I4: =IFERROR(SUMIFS($L$5:$L$504,$B$5:$B$504,"本舗")/COUNTIFS($B$5:$B$504,"本舗"),0) | J4: =SUMIFS($L$5:$L$504,$B$5:$B$504,"One Hitter") | K4: =SUMIFS($L$5:$L$504,$B$5:$B$504,"本舗") | L4: =SUM($L$5:$L$504) | R4: =COUNTIFS($E$5:$E$504,"HP")+COUNTIFS($E$5:$E$504,"LP")+COUNTIFS($E$5:$E$504,"SNS")+COUNTIFS($E$5:$E$504,"GBP(地図検索)")+COUNTIFS($E$5:$E$504,"公式LINE")+COUNTIFS($E$5:$E$504,"アフィリエイト")+COUNTIFS($E$5:$E$504,"LINE/SMS再販")+COUNTIFS($E$5:$E$504,"SMS")+COUNTIFS($E$5:$E$504,"広告") | S4: =SUMIFS($L$5:$L$504,$E$5:$E$504,"HP")+SUMIFS($L$5:$L$504,$E$5:$E$504,"LP")+SUMIFS($L$5:$L$504,$E$5:$E$504,"SNS")+SUMIFS($L$5:$L$504,$E$5:$E$504,"GBP(地図検索)")+SUMIFS($L$5:$L$504,$E$5:$E$504,"公式LINE")+SUMIFS($L$5:$L$504,$E$5:$E$504,"アフィリエイト")+SUMIFS($L$5:$L$504,$E$5:$E$504,"LINE/SMS再販")+SUMIFS($L$5:$L$504,$E$5:$E$504,"SMS")+SUMIFS($L$5:$L$504,$E$5:$E$504,"広告")

Sheet 9月_売上顧客
A1: ◆ 9月の売上・顧客。入力は 5 行目から。2行目＝今月の目標、4行目＝自動集計（数式・触らない）
A2: 今月目標(売上) | B2: 1800000 | C2: 売上 現在 | D2: =$L$4 | E2: 過不足 | F2: =D2-B2 | G2: 達成率 | H2: =IFERROR(D2/B2,0) | I2: 必要件数 | J2: 46 | K2: 件数 現在 | L2: =$E$4 | M2: 残り件数 | N2: =J2-L2 | O2: ④ネット新規 目標 | P2: 12 | Q2: ④ 現在 | R2: =$R$4
A3: 通し番号 | B3: 売上種類 | C3: 受注日 | D3: 施工日付 | E3: 流入経路 | F3: 流入元の識別子(?src=) | G3: 紹介者（顧客ID） | H3: 氏名 | I3: TEL(-無し) | J3: 郵便番号(-無し) | K3: 住所 | L3: 売上（税込） | M3: 実施メニュー | N3: 施工担当 | O3: フォローコール日 | P3: 早期予約提案 | Q3: フォローコール | R3: 備考(お客様の声) | S3: 入金経路 | T3: 入金額照合 | U3: ＯＨ打診 | V3: 本舗ロイ区分 | W3: お客様周辺/環境情報 | X3: カウント用
A4: ="▼自動集計" | B4: =COUNTIFS($B$5:$B$504,"One Hitter") | C4: =IFERROR(SUMPRODUCT(($C$5:$C$504<>"")*($D$5:$D$504<>"")*($D$5:$D$504-$C$5:$C$504))/SUMPRODUCT(($C$5:$C$504<>"")*($D$5:$D$504<>"")),0) | D4: =COUNTIFS($B$5:$B$504,"本舗") | E4: =COUNTA($D$5:$D$504) | F4: =IFERROR(SUM($L$5:$L$504)/COUNTA($D$5:$D$504),0) | G4: =COUNTA($G$5:$G$504) | H4: =IFERROR(SUMIFS($L$5:$L$504,$B$5:$B$504,"One Hitter")/COUNTIFS($B$5:$B$504,"One Hitter"),0) | I4: =IFERROR(SUMIFS($L$5:$L$504,$B$5:$B$504,"本舗")/COUNTIFS($B$5:$B$504,"本舗"),0) | J4: =SUMIFS($L$5:$L$504,$B$5:$B$504,"One Hitter") | K4: =SUMIFS($L$5:$L$504,$B$5:$B$504,"本舗") | L4: =SUM($L$5:$L$504) | R4: =COUNTIFS($E$5:$E$504,"HP")+COUNTIFS($E$5:$E$504,"LP")+COUNTIFS($E$5:$E$504,"SNS")+COUNTIFS($E$5:$E$504,"GBP(地図検索)")+COUNTIFS($E$5:$E$504,"公式LINE")+COUNTIFS($E$5:$E$504,"アフィリエイト")+COUNTIFS($E$5:$E$504,"LINE/SMS再販")+COUNTIFS($E$5:$E$504,"SMS")+COUNTIFS($E$5:$E$504,"広告") | S4: =SUMIFS($L$5:$L$504,$E$5:$E$504,"HP")+SUMIFS($L$5:$L$504,$E$5:$E$504,"LP")+SUMIFS($L$5:$L$504,$E$5:$E$504,"SNS")+SUMIFS($L$5:$L$504,$E$5:$E$504,"GBP(地図検索)")+SUMIFS($L$5:$L$504,$E$5:$E$504,"公式LINE")+SUMIFS($L$5:$L$504,$E$5:$E$504,"アフィリエイト")+SUMIFS($L$5:$L$504,$E$5:$E$504,"LINE/SMS再販")+SUMIFS($L$5:$L$504,$E$5:$E$504,"SMS")+SUMIFS($L$5:$L$504,$E$5:$E$504,"広告")

Sheet 10月_売上顧客
A1: ◆ 10月の売上・顧客。入力は 5 行目から。2行目＝今月の目標、4行目＝自動集計（数式・触らない）
A2: 今月目標(売上) | B2: 2320000 | C2: 売上 現在 | D2: =$L$4 | E2: 過不足 | F2: =D2-B2 | G2: 達成率 | H2: =IFERROR(D2/B2,0) | I2: 必要件数 | J2: 60 | K2: 件数 現在 | L2: =$E$4 | M2: 残り件数 | N2: =J2-L2 | O2: ④ネット新規 目標 | P2: 16 | Q2: ④ 現在 | R2: =$R$4
A3: 通し番号 | B3: 売上種類 | C3: 受注日 | D3: 施工日付 | E3: 流入経路 | F3: 流入元の識別子(?src=) | G3: 紹介者（顧客ID） | H3: 氏名 | I3: TEL(-無し) | J3: 郵便番号(-無し) | K3: 住所 | L3: 売上（税込） | M3: 実施メニュー | N3: 施工担当 | O3: フォローコール日 | P3: 早期予約提案 | Q3: フォローコール | R3: 備考(お客様の声) | S3: 入金経路 | T3: 入金額照合 | U3: ＯＨ打診 | V3: 本舗ロイ区分 | W3: お客様周辺/環境情報 | X3: カウント用
A4: ="▼自動集計" | B4: =COUNTIFS($B$5:$B$504,"One Hitter") | C4: =IFERROR(SUMPRODUCT(($C$5:$C$504<>"")*($D$5:$D$504<>"")*($D$5:$D$504-$C$5:$C$504))/SUMPRODUCT(($C$5:$C$504<>"")*($D$5:$D$504<>"")),0) | D4: =COUNTIFS($B$5:$B$504,"本舗") | E4: =COUNTA($D$5:$D$504) | F4: =IFERROR(SUM($L$5:$L$504)/COUNTA($D$5:$D$504),0) | G4: =COUNTA($G$5:$G$504) | H4: =IFERROR(SUMIFS($L$5:$L$504,$B$5:$B$504,"One Hitter")/COUNTIFS($B$5:$B$504,"One Hitter"),0) | I4: =IFERROR(SUMIFS($L$5:$L$504,$B$5:$B$504,"本舗")/COUNTIFS($B$5:$B$504,"本舗"),0) | J4: =SUMIFS($L$5:$L$504,$B$5:$B$504,"One Hitter") | K4: =SUMIFS($L$5:$L$504,$B$5:$B$504,"本舗") | L4: =SUM($L$5:$L$504) | R4: =COUNTIFS($E$5:$E$504,"HP")+COUNTIFS($E$5:$E$504,"LP")+COUNTIFS($E$5:$E$504,"SNS")+COUNTIFS($E$5:$E$504,"GBP(地図検索)")+COUNTIFS($E$5:$E$504,"公式LINE")+COUNTIFS($E$5:$E$504,"アフィリエイト")+COUNTIFS($E$5:$E$504,"LINE/SMS再販")+COUNTIFS($E$5:$E$504,"SMS")+COUNTIFS($E$5:$E$504,"広告") | S4: =SUMIFS($L$5:$L$504,$E$5:$E$504,"HP")+SUMIFS($L$5:$L$504,$E$5:$E$504,"LP")+SUMIFS($L$5:$L$504,$E$5:$E$504,"SNS")+SUMIFS($L$5:$L$504,$E$5:$E$504,"GBP(地図検索)")+SUMIFS($L$5:$L$504,$E$5:$E$504,"公式LINE")+SUMIFS($L$5:$L$504,$E$5:$E$504,"アフィリエイト")+SUMIFS($L$5:$L$504,$E$5:$E$504,"LINE/SMS再販")+SUMIFS($L$5:$L$504,$E$5:$E$504,"SMS")+SUMIFS($L$5:$L$504,$E$5:$E$504,"広告")

Sheet 11月_売上顧客
A1: ◆ 11月の売上・顧客。入力は 5 行目から。2行目＝今月の目標、4行目＝自動集計（数式・触らない）
A2: 今月目標(売上) | B2: 2480000 | C2: 売上 現在 | D2: =$L$4 | E2: 過不足 | F2: =D2-B2 | G2: 達成率 | H2: =IFERROR(D2/B2,0) | I2: 必要件数 | J2: 64 | K2: 件数 現在 | L2: =$E$4 | M2: 残り件数 | N2: =J2-L2 | O2: ④ネット新規 目標 | P2: 18 | Q2: ④ 現在 | R2: =$R$4
A3: 通し番号 | B3: 売上種類 | C3: 受注日 | D3: 施工日付 | E3: 流入経路 | F3: 流入元の識別子(?src=) | G3: 紹介者（顧客ID） | H3: 氏名 | I3: TEL(-無し) | J3: 郵便番号(-無し) | K3: 住所 | L3: 売上（税込） | M3: 実施メニュー | N3: 施工担当 | O3: フォローコール日 | P3: 早期予約提案 | Q3: フォローコール | R3: 備考(お客様の声) | S3: 入金経路 | T3: 入金額照合 | U3: ＯＨ打診 | V3: 本舗ロイ区分 | W3: お客様周辺/環境情報 | X3: カウント用
A4: ="▼自動集計" | B4: =COUNTIFS($B$5:$B$504,"One Hitter") | C4: =IFERROR(SUMPRODUCT(($C$5:$C$504<>"")*($D$5:$D$504<>"")*($D$5:$D$504-$C$5:$C$504))/SUMPRODUCT(($C$5:$C$504<>"")*($D$5:$D$504<>"")),0) | D4: =COUNTIFS($B$5:$B$504,"本舗") | E4: =COUNTA($D$5:$D$504) | F4: =IFERROR(SUM($L$5:$L$504)/COUNTA($D$5:$D$504),0) | G4: =COUNTA($G$5:$G$504) | H4: =IFERROR(SUMIFS($L$5:$L$504,$B$5:$B$504,"One Hitter")/COUNTIFS($B$5:$B$504,"One Hitter"),0) | I4: =IFERROR(SUMIFS($L$5:$L$504,$B$5:$B$504,"本舗")/COUNTIFS($B$5:$B$504,"本舗"),0) | J4: =SUMIFS($L$5:$L$504,$B$5:$B$504,"One Hitter") | K4: =SUMIFS($L$5:$L$504,$B$5:$B$504,"本舗") | L4: =SUM($L$5:$L$504) | R4: =COUNTIFS($E$5:$E$504,"HP")+COUNTIFS($E$5:$E$504,"LP")+COUNTIFS($E$5:$E$504,"SNS")+COUNTIFS($E$5:$E$504,"GBP(地図検索)")+COUNTIFS($E$5:$E$504,"公式LINE")+COUNTIFS($E$5:$E$504,"アフィリエイト")+COUNTIFS($E$5:$E$504,"LINE/SMS再販")+COUNTIFS($E$5:$E$504,"SMS")+COUNTIFS($E$5:$E$504,"広告") | S4: =SUMIFS($L$5:$L$504,$E$5:$E$504,"HP")+SUMIFS($L$5:$L$504,$E$5:$E$504,"LP")+SUMIFS($L$5:$L$504,$E$5:$E$504,"SNS")+SUMIFS($L$5:$L$504,$E$5:$E$504,"GBP(地図検索)")+SUMIFS($L$5:$L$504,$E$5:$E$504,"公式LINE")+SUMIFS($L$5:$L$504,$E$5:$E$504,"アフィリエイト")+SUMIFS($L$5:$L$504,$E$5:$E$504,"LINE/SMS再販")+SUMIFS($L$5:$L$504,$E$5:$E$504,"SMS")+SUMIFS($L$5:$L$504,$E$5:$E$504,"広告")

Sheet 12月_売上顧客
A1: ◆ 12月の売上・顧客。入力は 5 行目から。2行目＝今月の目標、4行目＝自動集計（数式・触らない）
A2: 今月目標(売上) | B2: 1940000 | C2: 売上 現在 | D2: =$L$4 | E2: 過不足 | F2: =D2-B2 | G2: 達成率 | H2: =IFERROR(D2/B2,0) | I2: 必要件数 | J2: 45 | K2: 件数 現在 | L2: =$E$4 | M2: 残り件数 | N2: =J2-L2 | O2: ④ネット新規 目標 | P2: 13 | Q2: ④ 現在 | R2: =$R$4
A3: 通し番号 | B3: 売上種類 | C3: 受注日 | D3: 施工日付 | E3: 流入経路 | F3: 流入元の識別子(?src=) | G3: 紹介者（顧客ID） | H3: 氏名 | I3: TEL(-無し) | J3: 郵便番号(-無し) | K3: 住所 | L3: 売上（税込） | M3: 実施メニュー | N3: 施工担当 | O3: フォローコール日 | P3: 早期予約提案 | Q3: フォローコール | R3: 備考(お客様の声) | S3: 入金経路 | T3: 入金額照合 | U3: ＯＨ打診 | V3: 本舗ロイ区分 | W3: お客様周辺/環境情報 | X3: カウント用
A4: ="▼自動集計" | B4: =COUNTIFS($B$5:$B$504,"One Hitter") | C4: =IFERROR(SUMPRODUCT(($C$5:$C$504<>"")*($D$5:$D$504<>"")*($D$5:$D$504-$C$5:$C$504))/SUMPRODUCT(($C$5:$C$504<>"")*($D$5:$D$504<>"")),0) | D4: =COUNTIFS($B$5:$B$504,"本舗") | E4: =COUNTA($D$5:$D$504) | F4: =IFERROR(SUM($L$5:$L$504)/COUNTA($D$5:$D$504),0) | G4: =COUNTA($G$5:$G$504) | H4: =IFERROR(SUMIFS($L$5:$L$504,$B$5:$B$504,"One Hitter")/COUNTIFS($B$5:$B$504,"One Hitter"),0) | I4: =IFERROR(SUMIFS($L$5:$L$504,$B$5:$B$504,"本舗")/COUNTIFS($B$5:$B$504,"本舗"),0) | J4: =SUMIFS($L$5:$L$504,$B$5:$B$504,"One Hitter") | K4: =SUMIFS($L$5:$L$504,$B$5:$B$504,"本舗") | L4: =SUM($L$5:$L$504) | R4: =COUNTIFS($E$5:$E$504,"HP")+COUNTIFS($E$5:$E$504,"LP")+COUNTIFS($E$5:$E$504,"SNS")+COUNTIFS($E$5:$E$504,"GBP(地図検索)")+COUNTIFS($E$5:$E$504,"公式LINE")+COUNTIFS($E$5:$E$504,"アフィリエイト")+COUNTIFS($E$5:$E$504,"LINE/SMS再販")+COUNTIFS($E$5:$E$504,"SMS")+COUNTIFS($E$5:$E$504,"広告") | S4: =SUMIFS($L$5:$L$504,$E$5:$E$504,"HP")+SUMIFS($L$5:$L$504,$E$5:$E$504,"LP")+SUMIFS($L$5:$L$504,$E$5:$E$504,"SNS")+SUMIFS($L$5:$L$504,$E$5:$E$504,"GBP(地図検索)")+SUMIFS($L$5:$L$504,$E$5:$E$504,"公式LINE")+SUMIFS($L$5:$L$504,$E$5:$E$504,"アフィリエイト")+SUMIFS($L$5:$L$504,$E$5:$E$504,"LINE/SMS再販")+SUMIFS($L$5:$L$504,$E$5:$E$504,"SMS")+SUMIFS($L$5:$L$504,$E$5:$E$504,"広告")

Sheet 1月_支出成績
A1: ◆ 1月の経費入力。3行目から下へ足していってよい。右の月次P/Lは行が動かないので壊れない | M1: ▼ 月次P/L（この位置は固定。左の経費表を何行足してもずれません）
A2: No. | B2: 日付 | C2: 時刻 | D2: 品目 | E2: 科目 | F2: 金額 | G2: 備考 | H2: 現金立替え | M2: 項目 | N2: 金額 | O2: 計算の中身 | Q2: ▼ 科目別 集計
M3: 売上 | N3: ='1月_売上顧客'!$L$4 | O3: 1月_売上顧客 の合計売上 | Q3: 科目 | R3: 金額
M4: エアコン台数(参考) | N4: =COUNTIFS('1月_売上顧客'!$M$5:$M$504,"エアコン(ノーマル)")+COUNTIFS('1月_売上顧客'!$M$5:$M$504,"エアコン(ロボ)")+COUNTIFS('1月_売上顧客'!$M$5:$M$504,"天カセ")+COUNTIFS('1月_売上顧客'!$M$5:$M$504,"業務用エアコン1方向") | O4: エアコン(ノーマル/ロボ)・天カセ・業務用1方向 | Q4: 交通費 | R4: =SUMIFS($F$3:$F$302,$E$3:$E$302,"交通費")
M5: 換気扇台数(参考) | N5: =COUNTIFS('1月_売上顧客'!$M$5:$M$504,"換気扇") | O5: 実施メニュー＝換気扇 | Q5: 保険料 | R5: =SUMIFS($F$3:$F$302,$E$3:$E$302,"保険料")
M6: 浴室台数(参考) | N6: =COUNTIFS('1月_売上顧客'!$M$5:$M$504,"浴室") | O6: 実施メニュー＝浴室 | Q6: 通信費 | R6: =SUMIFS($F$3:$F$302,$E$3:$E$302,"通信費")
M7: 資材費 | N7: =N4*373+N5*176+N6*149 | O7: エアコン373 + 換気扇176 + 浴室149 | Q7: 広告費 | R7: =SUMIFS($F$3:$F$302,$E$3:$E$302,"広告費")
M8: 外注費（協力業者） | N8: =SUMIFS($F$3:$F$302,$E$3:$E$302,"外注費") | O8: 経費表の科目＝外注費。★2027年から原価として独立 | Q8: 耐久品 | R8: =SUMIFS($F$3:$F$302,$E$3:$E$302,"耐久品")
M9: 現場人件費（原価） | N9: =SUMIFS($F$3:$F$302,$E$3:$E$302,"現場人件費(原価)") | O9: 経費表の科目＝現場人件費(原価) | Q9: 備品 | R9: =SUMIFS($F$3:$F$302,$E$3:$E$302,"備品")
M10: 原価合計 | N10: =N7+N8+N9 | O10: 資材費＋外注費＋現場人件費 | Q10: 個別ロイ | R10: =SUMIFS($F$3:$F$302,$E$3:$E$302,"個別ロイ")
M11: 売上総利益 | N11: =N3-N10 | O11: 売上 − 原価合計 | Q11: 現場人件費(原価) | R11: =SUMIFS($F$3:$F$302,$E$3:$E$302,"現場人件費(原価)")
Q12: 固定給(販管費) | R12: =SUMIFS($F$3:$F$302,$E$3:$E$302,"固定給(販管費)")
M13: 経費合計（左の表） | N13: =SUM($F$3:$F$302) | O13: 左の経費入力表の金額合計 | Q13: 外注費 | R13: =SUMIFS($F$3:$F$302,$E$3:$E$302,"外注費")
M14: − 原価へ回した分 | N14: =-(N8+N9) | O14: 外注費・現場人件費は原価で数えたので戻す | Q14: その他(備考へ) | R14: =SUMIFS($F$3:$F$302,$E$3:$E$302,"その他(備考へ)")
M15: − 個別ロイ（下で計上） | N15: =-SUMIFS($F$3:$F$302,$E$3:$E$302,"個別ロイ") | O15: ★二重計上を防ぐため、ここで一度引く | Q15: 合計 | R15: =SUM(R4:R14)
M16: ロイヤリティ 固定分 | N16: =IF($N$3+$N$13=0,0,50050) | O16: ★50,050円。左の経費表には入力しないこと（まだ動いていない月は0）
M17: ロイヤリティ 38%分 | N17: =SUMIFS('1月_売上顧客'!$L$5:$L$504,'1月_売上顧客'!$V$5:$V$504,"38%")*0.38 | O17: 本舗ロイ区分＝38% の売上 × 38%
M18: ロイヤリティ 10%分 | N18: =SUMIFS('1月_売上顧客'!$L$5:$L$504,'1月_売上顧客'!$V$5:$V$504,"10%")*0.1 | O18: 本舗ロイ区分＝10% の売上 × 10%
M19: ロイヤリティ 個別実額 | N19: =SUMIFS($F$3:$F$302,$E$3:$E$302,"個別ロイ") | O19: 経費表の科目＝個別ロイ（toB・楽ラクーン等）
M20: ロイヤリティ 合計 | N20: =N16+N17+N18+N19 | O20: 固定＋38%＋10%＋個別
M21: 販売管理費 | N21: =N13+N14+N15+N20 | O21: 経費合計 − 原価分 − 個別ロイ ＋ ロイヤリティ合計
M22: 営業利益 | N22: =N11-N21 | O22: 売上総利益 − 販売管理費
M23: 融資返済 | N23: =IF($N$3+$N$13=0,0,38059) | O23: 固定 38,059円（まだ動いていない月は0）
M24: 経常利益 | N24: =N22-N23 | O24: 営業利益 − 融資返済
M26: 経常利益率 | N26: =IFERROR(N24/N3,0) | O26: 経常利益 ÷ 売上
M28: ▼ 計画（中立）との比較
M29: 計画 売上 | N29: 1440000
M30: 実績 − 計画（売上） | N30: =N3-N29 | O30: マイナスなら赤
M31: 計画 経常利益 | N31: 231914
M32: 実績 − 計画（経常） | N32: =N24-N31 | O32: マイナスなら赤
M33: 計画 件数 | N33: 37
M34: 実績 件数 | N34: ='1月_売上顧客'!$E$4
M36: 【ロイヤリティはこのP/Lだけで数えます】
M37: ・固定分 50,050円は左の経費表に入力しないこと（2026年版はここが二重計上の疑いだった）
M38: ・個別ロイは左の経費表に科目「個別ロイ」で入力する。P/Lは15行目で引いて19行目で足すので、数えるのは1回だけ
M39: 【人件費は2つに分けます】
M40: ・現場人件費(原価) … 現場に出た分。原価に入る
M41: ・固定給(販管費) … 和真さんの固定給40万＋プール10万、新人の給与。販管費に入る
M42: ・歩合（経常利益×45%）の行は2027年から使いません
M43: 【保険料・通信費は「その他」に入れないこと】
M44: ・賠償保険 43,760／通信費 8,470／日新火災 18,050 ＝ 月70,280円。科目を独立させました

Sheet 2月_支出成績
A1: ◆ 2月の経費入力。3行目から下へ足していってよい。右の月次P/Lは行が動かないので壊れない | M1: ▼ 月次P/L（この位置は固定。左の経費表を何行足してもずれません）
A2: No. | B2: 日付 | C2: 時刻 | D2: 品目 | E2: 科目 | F2: 金額 | G2: 備考 | H2: 現金立替え | M2: 項目 | N2: 金額 | O2: 計算の中身 | Q2: ▼ 科目別 集計
M3: 売上 | N3: ='2月_売上顧客'!$L$4 | O3: 2月_売上顧客 の合計売上 | Q3: 科目 | R3: 金額
M4: エアコン台数(参考) | N4: =COUNTIFS('2月_売上顧客'!$M$5:$M$504,"エアコン(ノーマル)")+COUNTIFS('2月_売上顧客'!$M$5:$M$504,"エアコン(ロボ)")+COUNTIFS('2月_売上顧客'!$M$5:$M$504,"天カセ")+COUNTIFS('2月_売上顧客'!$M$5:$M$504,"業務用エアコン1方向") | O4: エアコン(ノーマル/ロボ)・天カセ・業務用1方向 | Q4: 交通費 | R4: =SUMIFS($F$3:$F$302,$E$3:$E$302,"交通費")
M5: 換気扇台数(参考) | N5: =COUNTIFS('2月_売上顧客'!$M$5:$M$504,"換気扇") | O5: 実施メニュー＝換気扇 | Q5: 保険料 | R5: =SUMIFS($F$3:$F$302,$E$3:$E$302,"保険料")
M6: 浴室台数(参考) | N6: =COUNTIFS('2月_売上顧客'!$M$5:$M$504,"浴室") | O6: 実施メニュー＝浴室 | Q6: 通信費 | R6: =SUMIFS($F$3:$F$302,$E$3:$E$302,"通信費")
M7: 資材費 | N7: =N4*373+N5*176+N6*149 | O7: エアコン373 + 換気扇176 + 浴室149 | Q7: 広告費 | R7: =SUMIFS($F$3:$F$302,$E$3:$E$302,"広告費")
M8: 外注費（協力業者） | N8: =SUMIFS($F$3:$F$302,$E$3:$E$302,"外注費") | O8: 経費表の科目＝外注費。★2027年から原価として独立 | Q8: 耐久品 | R8: =SUMIFS($F$3:$F$302,$E$3:$E$302,"耐久品")
M9: 現場人件費（原価） | N9: =SUMIFS($F$3:$F$302,$E$3:$E$302,"現場人件費(原価)") | O9: 経費表の科目＝現場人件費(原価) | Q9: 備品 | R9: =SUMIFS($F$3:$F$302,$E$3:$E$302,"備品")
M10: 原価合計 | N10: =N7+N8+N9 | O10: 資材費＋外注費＋現場人件費 | Q10: 個別ロイ | R10: =SUMIFS($F$3:$F$302,$E$3:$E$302,"個別ロイ")
M11: 売上総利益 | N11: =N3-N10 | O11: 売上 − 原価合計 | Q11: 現場人件費(原価) | R11: =SUMIFS($F$3:$F$302,$E$3:$E$302,"現場人件費(原価)")
Q12: 固定給(販管費) | R12: =SUMIFS($F$3:$F$302,$E$3:$E$302,"固定給(販管費)")
M13: 経費合計（左の表） | N13: =SUM($F$3:$F$302) | O13: 左の経費入力表の金額合計 | Q13: 外注費 | R13: =SUMIFS($F$3:$F$302,$E$3:$E$302,"外注費")
M14: − 原価へ回した分 | N14: =-(N8+N9) | O14: 外注費・現場人件費は原価で数えたので戻す | Q14: その他(備考へ) | R14: =SUMIFS($F$3:$F$302,$E$3:$E$302,"その他(備考へ)")
M15: − 個別ロイ（下で計上） | N15: =-SUMIFS($F$3:$F$302,$E$3:$E$302,"個別ロイ") | O15: ★二重計上を防ぐため、ここで一度引く | Q15: 合計 | R15: =SUM(R4:R14)
M16: ロイヤリティ 固定分 | N16: =IF($N$3+$N$13=0,0,50050) | O16: ★50,050円。左の経費表には入力しないこと（まだ動いていない月は0）
M17: ロイヤリティ 38%分 | N17: =SUMIFS('2月_売上顧客'!$L$5:$L$504,'2月_売上顧客'!$V$5:$V$504,"38%")*0.38 | O17: 本舗ロイ区分＝38% の売上 × 38%
M18: ロイヤリティ 10%分 | N18: =SUMIFS('2月_売上顧客'!$L$5:$L$504,'2月_売上顧客'!$V$5:$V$504,"10%")*0.1 | O18: 本舗ロイ区分＝10% の売上 × 10%
M19: ロイヤリティ 個別実額 | N19: =SUMIFS($F$3:$F$302,$E$3:$E$302,"個別ロイ") | O19: 経費表の科目＝個別ロイ（toB・楽ラクーン等）
M20: ロイヤリティ 合計 | N20: =N16+N17+N18+N19 | O20: 固定＋38%＋10%＋個別
M21: 販売管理費 | N21: =N13+N14+N15+N20 | O21: 経費合計 − 原価分 − 個別ロイ ＋ ロイヤリティ合計
M22: 営業利益 | N22: =N11-N21 | O22: 売上総利益 − 販売管理費
M23: 融資返済 | N23: =IF($N$3+$N$13=0,0,38059) | O23: 固定 38,059円（まだ動いていない月は0）
M24: 経常利益 | N24: =N22-N23 | O24: 営業利益 − 融資返済
M26: 経常利益率 | N26: =IFERROR(N24/N3,0) | O26: 経常利益 ÷ 売上
M28: ▼ 計画（中立）との比較
M29: 計画 売上 | N29: 1280000
M30: 実績 − 計画（売上） | N30: =N3-N29 | O30: マイナスなら赤
M31: 計画 経常利益 | N31: -6745
M32: 実績 − 計画（経常） | N32: =N24-N31 | O32: マイナスなら赤
M33: 計画 件数 | N33: 32
M34: 実績 件数 | N34: ='2月_売上顧客'!$E$4
M36: 【ロイヤリティはこのP/Lだけで数えます】
M37: ・固定分 50,050円は左の経費表に入力しないこと（2026年版はここが二重計上の疑いだった）
M38: ・個別ロイは左の経費表に科目「個別ロイ」で入力する。P/Lは15行目で引いて19行目で足すので、数えるのは1回だけ
M39: 【人件費は2つに分けます】
M40: ・現場人件費(原価) … 現場に出た分。原価に入る
M41: ・固定給(販管費) … 和真さんの固定給40万＋プール10万、新人の給与。販管費に入る
M42: ・歩合（経常利益×45%）の行は2027年から使いません
M43: 【保険料・通信費は「その他」に入れないこと】
M44: ・賠償保険 43,760／通信費 8,470／日新火災 18,050 ＝ 月70,280円。科目を独立させました

Sheet 3月_支出成績
A1: ◆ 3月の経費入力。3行目から下へ足していってよい。右の月次P/Lは行が動かないので壊れない | M1: ▼ 月次P/L（この位置は固定。左の経費表を何行足してもずれません）
A2: No. | B2: 日付 | C2: 時刻 | D2: 品目 | E2: 科目 | F2: 金額 | G2: 備考 | H2: 現金立替え | M2: 項目 | N2: 金額 | O2: 計算の中身 | Q2: ▼ 科目別 集計
M3: 売上 | N3: ='3月_売上顧客'!$L$4 | O3: 3月_売上顧客 の合計売上 | Q3: 科目 | R3: 金額
M4: エアコン台数(参考) | N4: =COUNTIFS('3月_売上顧客'!$M$5:$M$504,"エアコン(ノーマル)")+COUNTIFS('3月_売上顧客'!$M$5:$M$504,"エアコン(ロボ)")+COUNTIFS('3月_売上顧客'!$M$5:$M$504,"天カセ")+COUNTIFS('3月_売上顧客'!$M$5:$M$504,"業務用エアコン1方向") | O4: エアコン(ノーマル/ロボ)・天カセ・業務用1方向 | Q4: 交通費 | R4: =SUMIFS($F$3:$F$302,$E$3:$E$302,"交通費")
M5: 換気扇台数(参考) | N5: =COUNTIFS('3月_売上顧客'!$M$5:$M$504,"換気扇") | O5: 実施メニュー＝換気扇 | Q5: 保険料 | R5: =SUMIFS($F$3:$F$302,$E$3:$E$302,"保険料")
M6: 浴室台数(参考) | N6: =COUNTIFS('3月_売上顧客'!$M$5:$M$504,"浴室") | O6: 実施メニュー＝浴室 | Q6: 通信費 | R6: =SUMIFS($F$3:$F$302,$E$3:$E$302,"通信費")
M7: 資材費 | N7: =N4*373+N5*176+N6*149 | O7: エアコン373 + 換気扇176 + 浴室149 | Q7: 広告費 | R7: =SUMIFS($F$3:$F$302,$E$3:$E$302,"広告費")
M8: 外注費（協力業者） | N8: =SUMIFS($F$3:$F$302,$E$3:$E$302,"外注費") | O8: 経費表の科目＝外注費。★2027年から原価として独立 | Q8: 耐久品 | R8: =SUMIFS($F$3:$F$302,$E$3:$E$302,"耐久品")
M9: 現場人件費（原価） | N9: =SUMIFS($F$3:$F$302,$E$3:$E$302,"現場人件費(原価)") | O9: 経費表の科目＝現場人件費(原価) | Q9: 備品 | R9: =SUMIFS($F$3:$F$302,$E$3:$E$302,"備品")
M10: 原価合計 | N10: =N7+N8+N9 | O10: 資材費＋外注費＋現場人件費 | Q10: 個別ロイ | R10: =SUMIFS($F$3:$F$302,$E$3:$E$302,"個別ロイ")
M11: 売上総利益 | N11: =N3-N10 | O11: 売上 − 原価合計 | Q11: 現場人件費(原価) | R11: =SUMIFS($F$3:$F$302,$E$3:$E$302,"現場人件費(原価)")
Q12: 固定給(販管費) | R12: =SUMIFS($F$3:$F$302,$E$3:$E$302,"固定給(販管費)")
M13: 経費合計（左の表） | N13: =SUM($F$3:$F$302) | O13: 左の経費入力表の金額合計 | Q13: 外注費 | R13: =SUMIFS($F$3:$F$302,$E$3:$E$302,"外注費")
M14: − 原価へ回した分 | N14: =-(N8+N9) | O14: 外注費・現場人件費は原価で数えたので戻す | Q14: その他(備考へ) | R14: =SUMIFS($F$3:$F$302,$E$3:$E$302,"その他(備考へ)")
M15: − 個別ロイ（下で計上） | N15: =-SUMIFS($F$3:$F$302,$E$3:$E$302,"個別ロイ") | O15: ★二重計上を防ぐため、ここで一度引く | Q15: 合計 | R15: =SUM(R4:R14)
M16: ロイヤリティ 固定分 | N16: =IF($N$3+$N$13=0,0,50050) | O16: ★50,050円。左の経費表には入力しないこと（まだ動いていない月は0）
M17: ロイヤリティ 38%分 | N17: =SUMIFS('3月_売上顧客'!$L$5:$L$504,'3月_売上顧客'!$V$5:$V$504,"38%")*0.38 | O17: 本舗ロイ区分＝38% の売上 × 38%
M18: ロイヤリティ 10%分 | N18: =SUMIFS('3月_売上顧客'!$L$5:$L$504,'3月_売上顧客'!$V$5:$V$504,"10%")*0.1 | O18: 本舗ロイ区分＝10% の売上 × 10%
M19: ロイヤリティ 個別実額 | N19: =SUMIFS($F$3:$F$302,$E$3:$E$302,"個別ロイ") | O19: 経費表の科目＝個別ロイ（toB・楽ラクーン等）
M20: ロイヤリティ 合計 | N20: =N16+N17+N18+N19 | O20: 固定＋38%＋10%＋個別
M21: 販売管理費 | N21: =N13+N14+N15+N20 | O21: 経費合計 − 原価分 − 個別ロイ ＋ ロイヤリティ合計
M22: 営業利益 | N22: =N11-N21 | O22: 売上総利益 − 販売管理費
M23: 融資返済 | N23: =IF($N$3+$N$13=0,0,38059) | O23: 固定 38,059円（まだ動いていない月は0）
M24: 経常利益 | N24: =N22-N23 | O24: 営業利益 − 融資返済
M26: 経常利益率 | N26: =IFERROR(N24/N3,0) | O26: 経常利益 ÷ 売上
M28: ▼ 計画（中立）との比較
M29: 計画 売上 | N29: 1850000
M30: 実績 − 計画（売上） | N30: =N3-N29 | O30: マイナスなら赤
M31: 計画 経常利益 | N31: 303086
M32: 実績 − 計画（経常） | N32: =N24-N31 | O32: マイナスなら赤
M33: 計画 件数 | N33: 46
M34: 実績 件数 | N34: ='3月_売上顧客'!$E$4
M36: 【ロイヤリティはこのP/Lだけで数えます】
M37: ・固定分 50,050円は左の経費表に入力しないこと（2026年版はここが二重計上の疑いだった）
M38: ・個別ロイは左の経費表に科目「個別ロイ」で入力する。P/Lは15行目で引いて19行目で足すので、数えるのは1回だけ
M39: 【人件費は2つに分けます】
M40: ・現場人件費(原価) … 現場に出た分。原価に入る
M41: ・固定給(販管費) … 和真さんの固定給40万＋プール10万、新人の給与。販管費に入る
M42: ・歩合（経常利益×45%）の行は2027年から使いません
M43: 【保険料・通信費は「その他」に入れないこと】
M44: ・賠償保険 43,760／通信費 8,470／日新火災 18,050 ＝ 月70,280円。科目を独立させました

Sheet 4月_支出成績
A1: ◆ 4月の経費入力。3行目から下へ足していってよい。右の月次P/Lは行が動かないので壊れない | M1: ▼ 月次P/L（この位置は固定。左の経費表を何行足してもずれません）
A2: No. | B2: 日付 | C2: 時刻 | D2: 品目 | E2: 科目 | F2: 金額 | G2: 備考 | H2: 現金立替え | M2: 項目 | N2: 金額 | O2: 計算の中身 | Q2: ▼ 科目別 集計
M3: 売上 | N3: ='4月_売上顧客'!$L$4 | O3: 4月_売上顧客 の合計売上 | Q3: 科目 | R3: 金額
M4: エアコン台数(参考) | N4: =COUNTIFS('4月_売上顧客'!$M$5:$M$504,"エアコン(ノーマル)")+COUNTIFS('4月_売上顧客'!$M$5:$M$504,"エアコン(ロボ)")+COUNTIFS('4月_売上顧客'!$M$5:$M$504,"天カセ")+COUNTIFS('4月_売上顧客'!$M$5:$M$504,"業務用エアコン1方向") | O4: エアコン(ノーマル/ロボ)・天カセ・業務用1方向 | Q4: 交通費 | R4: =SUMIFS($F$3:$F$302,$E$3:$E$302,"交通費")
M5: 換気扇台数(参考) | N5: =COUNTIFS('4月_売上顧客'!$M$5:$M$504,"換気扇") | O5: 実施メニュー＝換気扇 | Q5: 保険料 | R5: =SUMIFS($F$3:$F$302,$E$3:$E$302,"保険料")
M6: 浴室台数(参考) | N6: =COUNTIFS('4月_売上顧客'!$M$5:$M$504,"浴室") | O6: 実施メニュー＝浴室 | Q6: 通信費 | R6: =SUMIFS($F$3:$F$302,$E$3:$E$302,"通信費")
M7: 資材費 | N7: =N4*373+N5*176+N6*149 | O7: エアコン373 + 換気扇176 + 浴室149 | Q7: 広告費 | R7: =SUMIFS($F$3:$F$302,$E$3:$E$302,"広告費")
M8: 外注費（協力業者） | N8: =SUMIFS($F$3:$F$302,$E$3:$E$302,"外注費") | O8: 経費表の科目＝外注費。★2027年から原価として独立 | Q8: 耐久品 | R8: =SUMIFS($F$3:$F$302,$E$3:$E$302,"耐久品")
M9: 現場人件費（原価） | N9: =SUMIFS($F$3:$F$302,$E$3:$E$302,"現場人件費(原価)") | O9: 経費表の科目＝現場人件費(原価) | Q9: 備品 | R9: =SUMIFS($F$3:$F$302,$E$3:$E$302,"備品")
M10: 原価合計 | N10: =N7+N8+N9 | O10: 資材費＋外注費＋現場人件費 | Q10: 個別ロイ | R10: =SUMIFS($F$3:$F$302,$E$3:$E$302,"個別ロイ")
M11: 売上総利益 | N11: =N3-N10 | O11: 売上 − 原価合計 | Q11: 現場人件費(原価) | R11: =SUMIFS($F$3:$F$302,$E$3:$E$302,"現場人件費(原価)")
Q12: 固定給(販管費) | R12: =SUMIFS($F$3:$F$302,$E$3:$E$302,"固定給(販管費)")
M13: 経費合計（左の表） | N13: =SUM($F$3:$F$302) | O13: 左の経費入力表の金額合計 | Q13: 外注費 | R13: =SUMIFS($F$3:$F$302,$E$3:$E$302,"外注費")
M14: − 原価へ回した分 | N14: =-(N8+N9) | O14: 外注費・現場人件費は原価で数えたので戻す | Q14: その他(備考へ) | R14: =SUMIFS($F$3:$F$302,$E$3:$E$302,"その他(備考へ)")
M15: − 個別ロイ（下で計上） | N15: =-SUMIFS($F$3:$F$302,$E$3:$E$302,"個別ロイ") | O15: ★二重計上を防ぐため、ここで一度引く | Q15: 合計 | R15: =SUM(R4:R14)
M16: ロイヤリティ 固定分 | N16: =IF($N$3+$N$13=0,0,50050) | O16: ★50,050円。左の経費表には入力しないこと（まだ動いていない月は0）
M17: ロイヤリティ 38%分 | N17: =SUMIFS('4月_売上顧客'!$L$5:$L$504,'4月_売上顧客'!$V$5:$V$504,"38%")*0.38 | O17: 本舗ロイ区分＝38% の売上 × 38%
M18: ロイヤリティ 10%分 | N18: =SUMIFS('4月_売上顧客'!$L$5:$L$504,'4月_売上顧客'!$V$5:$V$504,"10%")*0.1 | O18: 本舗ロイ区分＝10% の売上 × 10%
M19: ロイヤリティ 個別実額 | N19: =SUMIFS($F$3:$F$302,$E$3:$E$302,"個別ロイ") | O19: 経費表の科目＝個別ロイ（toB・楽ラクーン等）
M20: ロイヤリティ 合計 | N20: =N16+N17+N18+N19 | O20: 固定＋38%＋10%＋個別
M21: 販売管理費 | N21: =N13+N14+N15+N20 | O21: 経費合計 − 原価分 − 個別ロイ ＋ ロイヤリティ合計
M22: 営業利益 | N22: =N11-N21 | O22: 売上総利益 − 販売管理費
M23: 融資返済 | N23: =IF($N$3+$N$13=0,0,38059) | O23: 固定 38,059円（まだ動いていない月は0）
M24: 経常利益 | N24: =N22-N23 | O24: 営業利益 − 融資返済
M26: 経常利益率 | N26: =IFERROR(N24/N3,0) | O26: 経常利益 ÷ 売上
M28: ▼ 計画（中立）との比較
M29: 計画 売上 | N29: 2260000
M30: 実績 − 計画（売上） | N30: =N3-N29 | O30: マイナスなら赤
M31: 計画 経常利益 | N31: 570807
M32: 実績 − 計画（経常） | N32: =N24-N31 | O32: マイナスなら赤
M33: 計画 件数 | N33: 57
M34: 実績 件数 | N34: ='4月_売上顧客'!$E$4
M36: 【ロイヤリティはこのP/Lだけで数えます】
M37: ・固定分 50,050円は左の経費表に入力しないこと（2026年版はここが二重計上の疑いだった）
M38: ・個別ロイは左の経費表に科目「個別ロイ」で入力する。P/Lは15行目で引いて19行目で足すので、数えるのは1回だけ
M39: 【人件費は2つに分けます】
M40: ・現場人件費(原価) … 現場に出た分。原価に入る
M41: ・固定給(販管費) … 和真さんの固定給40万＋プール10万、新人の給与。販管費に入る
M42: ・歩合（経常利益×45%）の行は2027年から使いません
M43: 【保険料・通信費は「その他」に入れないこと】
M44: ・賠償保険 43,760／通信費 8,470／日新火災 18,050 ＝ 月70,280円。科目を独立させました

Sheet 5月_支出成績
A1: ◆ 5月の経費入力。3行目から下へ足していってよい。右の月次P/Lは行が動かないので壊れない | M1: ▼ 月次P/L（この位置は固定。左の経費表を何行足してもずれません）
A2: No. | B2: 日付 | C2: 時刻 | D2: 品目 | E2: 科目 | F2: 金額 | G2: 備考 | H2: 現金立替え | M2: 項目 | N2: 金額 | O2: 計算の中身 | Q2: ▼ 科目別 集計
M3: 売上 | N3: ='5月_売上顧客'!$L$4 | O3: 5月_売上顧客 の合計売上 | Q3: 科目 | R3: 金額
M4: エアコン台数(参考) | N4: =COUNTIFS('5月_売上顧客'!$M$5:$M$504,"エアコン(ノーマル)")+COUNTIFS('5月_売上顧客'!$M$5:$M$504,"エアコン(ロボ)")+COUNTIFS('5月_売上顧客'!$M$5:$M$504,"天カセ")+COUNTIFS('5月_売上顧客'!$M$5:$M$504,"業務用エアコン1方向") | O4: エアコン(ノーマル/ロボ)・天カセ・業務用1方向 | Q4: 交通費 | R4: =SUMIFS($F$3:$F$302,$E$3:$E$302,"交通費")
M5: 換気扇台数(参考) | N5: =COUNTIFS('5月_売上顧客'!$M$5:$M$504,"換気扇") | O5: 実施メニュー＝換気扇 | Q5: 保険料 | R5: =SUMIFS($F$3:$F$302,$E$3:$E$302,"保険料")
M6: 浴室台数(参考) | N6: =COUNTIFS('5月_売上顧客'!$M$5:$M$504,"浴室") | O6: 実施メニュー＝浴室 | Q6: 通信費 | R6: =SUMIFS($F$3:$F$302,$E$3:$E$302,"通信費")
M7: 資材費 | N7: =N4*373+N5*176+N6*149 | O7: エアコン373 + 換気扇176 + 浴室149 | Q7: 広告費 | R7: =SUMIFS($F$3:$F$302,$E$3:$E$302,"広告費")
M8: 外注費（協力業者） | N8: =SUMIFS($F$3:$F$302,$E$3:$E$302,"外注費") | O8: 経費表の科目＝外注費。★2027年から原価として独立 | Q8: 耐久品 | R8: =SUMIFS($F$3:$F$302,$E$3:$E$302,"耐久品")
M9: 現場人件費（原価） | N9: =SUMIFS($F$3:$F$302,$E$3:$E$302,"現場人件費(原価)") | O9: 経費表の科目＝現場人件費(原価) | Q9: 備品 | R9: =SUMIFS($F$3:$F$302,$E$3:$E$302,"備品")
M10: 原価合計 | N10: =N7+N8+N9 | O10: 資材費＋外注費＋現場人件費 | Q10: 個別ロイ | R10: =SUMIFS($F$3:$F$302,$E$3:$E$302,"個別ロイ")
M11: 売上総利益 | N11: =N3-N10 | O11: 売上 − 原価合計 | Q11: 現場人件費(原価) | R11: =SUMIFS($F$3:$F$302,$E$3:$E$302,"現場人件費(原価)")
Q12: 固定給(販管費) | R12: =SUMIFS($F$3:$F$302,$E$3:$E$302,"固定給(販管費)")
M13: 経費合計（左の表） | N13: =SUM($F$3:$F$302) | O13: 左の経費入力表の金額合計 | Q13: 外注費 | R13: =SUMIFS($F$3:$F$302,$E$3:$E$302,"外注費")
M14: − 原価へ回した分 | N14: =-(N8+N9) | O14: 外注費・現場人件費は原価で数えたので戻す | Q14: その他(備考へ) | R14: =SUMIFS($F$3:$F$302,$E$3:$E$302,"その他(備考へ)")
M15: − 個別ロイ（下で計上） | N15: =-SUMIFS($F$3:$F$302,$E$3:$E$302,"個別ロイ") | O15: ★二重計上を防ぐため、ここで一度引く | Q15: 合計 | R15: =SUM(R4:R14)
M16: ロイヤリティ 固定分 | N16: =IF($N$3+$N$13=0,0,50050) | O16: ★50,050円。左の経費表には入力しないこと（まだ動いていない月は0）
M17: ロイヤリティ 38%分 | N17: =SUMIFS('5月_売上顧客'!$L$5:$L$504,'5月_売上顧客'!$V$5:$V$504,"38%")*0.38 | O17: 本舗ロイ区分＝38% の売上 × 38%
M18: ロイヤリティ 10%分 | N18: =SUMIFS('5月_売上顧客'!$L$5:$L$504,'5月_売上顧客'!$V$5:$V$504,"10%")*0.1 | O18: 本舗ロイ区分＝10% の売上 × 10%
M19: ロイヤリティ 個別実額 | N19: =SUMIFS($F$3:$F$302,$E$3:$E$302,"個別ロイ") | O19: 経費表の科目＝個別ロイ（toB・楽ラクーン等）
M20: ロイヤリティ 合計 | N20: =N16+N17+N18+N19 | O20: 固定＋38%＋10%＋個別
M21: 販売管理費 | N21: =N13+N14+N15+N20 | O21: 経費合計 − 原価分 − 個別ロイ ＋ ロイヤリティ合計
M22: 営業利益 | N22: =N11-N21 | O22: 売上総利益 − 販売管理費
M23: 融資返済 | N23: =IF($N$3+$N$13=0,0,38059) | O23: 固定 38,059円（まだ動いていない月は0）
M24: 経常利益 | N24: =N22-N23 | O24: 営業利益 − 融資返済
M26: 経常利益率 | N26: =IFERROR(N24/N3,0) | O26: 経常利益 ÷ 売上
M28: ▼ 計画（中立）との比較
M29: 計画 売上 | N29: 2890000
M30: 実績 − 計画（売上） | N30: =N3-N29 | O30: マイナスなら赤
M31: 計画 経常利益 | N31: 892282
M32: 実績 − 計画（経常） | N32: =N24-N31 | O32: マイナスなら赤
M33: 計画 件数 | N33: 70
M34: 実績 件数 | N34: ='5月_売上顧客'!$E$4
M36: 【ロイヤリティはこのP/Lだけで数えます】
M37: ・固定分 50,050円は左の経費表に入力しないこと（2026年版はここが二重計上の疑いだった）
M38: ・個別ロイは左の経費表に科目「個別ロイ」で入力する。P/Lは15行目で引いて19行目で足すので、数えるのは1回だけ
M39: 【人件費は2つに分けます】
M40: ・現場人件費(原価) … 現場に出た分。原価に入る
M41: ・固定給(販管費) … 和真さんの固定給40万＋プール10万、新人の給与。販管費に入る
M42: ・歩合（経常利益×45%）の行は2027年から使いません
M43: 【保険料・通信費は「その他」に入れないこと】
M44: ・賠償保険 43,760／通信費 8,470／日新火災 18,050 ＝ 月70,280円。科目を独立させました

Sheet 6月_支出成績
A1: ◆ 6月の経費入力。3行目から下へ足していってよい。右の月次P/Lは行が動かないので壊れない | M1: ▼ 月次P/L（この位置は固定。左の経費表を何行足してもずれません）
A2: No. | B2: 日付 | C2: 時刻 | D2: 品目 | E2: 科目 | F2: 金額 | G2: 備考 | H2: 現金立替え | M2: 項目 | N2: 金額 | O2: 計算の中身 | Q2: ▼ 科目別 集計
M3: 売上 | N3: ='6月_売上顧客'!$L$4 | O3: 6月_売上顧客 の合計売上 | Q3: 科目 | R3: 金額
M4: エアコン台数(参考) | N4: =COUNTIFS('6月_売上顧客'!$M$5:$M$504,"エアコン(ノーマル)")+COUNTIFS('6月_売上顧客'!$M$5:$M$504,"エアコン(ロボ)")+COUNTIFS('6月_売上顧客'!$M$5:$M$504,"天カセ")+COUNTIFS('6月_売上顧客'!$M$5:$M$504,"業務用エアコン1方向") | O4: エアコン(ノーマル/ロボ)・天カセ・業務用1方向 | Q4: 交通費 | R4: =SUMIFS($F$3:$F$302,$E$3:$E$302,"交通費")
M5: 換気扇台数(参考) | N5: =COUNTIFS('6月_売上顧客'!$M$5:$M$504,"換気扇") | O5: 実施メニュー＝換気扇 | Q5: 保険料 | R5: =SUMIFS($F$3:$F$302,$E$3:$E$302,"保険料")
M6: 浴室台数(参考) | N6: =COUNTIFS('6月_売上顧客'!$M$5:$M$504,"浴室") | O6: 実施メニュー＝浴室 | Q6: 通信費 | R6: =SUMIFS($F$3:$F$302,$E$3:$E$302,"通信費")
M7: 資材費 | N7: =N4*373+N5*176+N6*149 | O7: エアコン373 + 換気扇176 + 浴室149 | Q7: 広告費 | R7: =SUMIFS($F$3:$F$302,$E$3:$E$302,"広告費")
M8: 外注費（協力業者） | N8: =SUMIFS($F$3:$F$302,$E$3:$E$302,"外注費") | O8: 経費表の科目＝外注費。★2027年から原価として独立 | Q8: 耐久品 | R8: =SUMIFS($F$3:$F$302,$E$3:$E$302,"耐久品")
M9: 現場人件費（原価） | N9: =SUMIFS($F$3:$F$302,$E$3:$E$302,"現場人件費(原価)") | O9: 経費表の科目＝現場人件費(原価) | Q9: 備品 | R9: =SUMIFS($F$3:$F$302,$E$3:$E$302,"備品")
M10: 原価合計 | N10: =N7+N8+N9 | O10: 資材費＋外注費＋現場人件費 | Q10: 個別ロイ | R10: =SUMIFS($F$3:$F$302,$E$3:$E$302,"個別ロイ")
M11: 売上総利益 | N11: =N3-N10 | O11: 売上 − 原価合計 | Q11: 現場人件費(原価) | R11: =SUMIFS($F$3:$F$302,$E$3:$E$302,"現場人件費(原価)")
Q12: 固定給(販管費) | R12: =SUMIFS($F$3:$F$302,$E$3:$E$302,"固定給(販管費)")
M13: 経費合計（左の表） | N13: =SUM($F$3:$F$302) | O13: 左の経費入力表の金額合計 | Q13: 外注費 | R13: =SUMIFS($F$3:$F$302,$E$3:$E$302,"外注費")
M14: − 原価へ回した分 | N14: =-(N8+N9) | O14: 外注費・現場人件費は原価で数えたので戻す | Q14: その他(備考へ) | R14: =SUMIFS($F$3:$F$302,$E$3:$E$302,"その他(備考へ)")
M15: − 個別ロイ（下で計上） | N15: =-SUMIFS($F$3:$F$302,$E$3:$E$302,"個別ロイ") | O15: ★二重計上を防ぐため、ここで一度引く | Q15: 合計 | R15: =SUM(R4:R14)
M16: ロイヤリティ 固定分 | N16: =IF($N$3+$N$13=0,0,50050) | O16: ★50,050円。左の経費表には入力しないこと（まだ動いていない月は0）
M17: ロイヤリティ 38%分 | N17: =SUMIFS('6月_売上顧客'!$L$5:$L$504,'6月_売上顧客'!$V$5:$V$504,"38%")*0.38 | O17: 本舗ロイ区分＝38% の売上 × 38%
M18: ロイヤリティ 10%分 | N18: =SUMIFS('6月_売上顧客'!$L$5:$L$504,'6月_売上顧客'!$V$5:$V$504,"10%")*0.1 | O18: 本舗ロイ区分＝10% の売上 × 10%
M19: ロイヤリティ 個別実額 | N19: =SUMIFS($F$3:$F$302,$E$3:$E$302,"個別ロイ") | O19: 経費表の科目＝個別ロイ（toB・楽ラクーン等）
M20: ロイヤリティ 合計 | N20: =N16+N17+N18+N19 | O20: 固定＋38%＋10%＋個別
M21: 販売管理費 | N21: =N13+N14+N15+N20 | O21: 経費合計 − 原価分 − 個別ロイ ＋ ロイヤリティ合計
M22: 営業利益 | N22: =N11-N21 | O22: 売上総利益 − 販売管理費
M23: 融資返済 | N23: =IF($N$3+$N$13=0,0,38059) | O23: 固定 38,059円（まだ動いていない月は0）
M24: 経常利益 | N24: =N22-N23 | O24: 営業利益 − 融資返済
M26: 経常利益率 | N26: =IFERROR(N24/N3,0) | O26: 経常利益 ÷ 売上
M28: ▼ 計画（中立）との比較
M29: 計画 売上 | N29: 3400000
M30: 実績 − 計画（売上） | N30: =N3-N29 | O30: マイナスなら赤
M31: 計画 経常利益 | N31: 1231143
M32: 実績 − 計画（経常） | N32: =N24-N31 | O32: マイナスなら赤
M33: 計画 件数 | N33: 82
M34: 実績 件数 | N34: ='6月_売上顧客'!$E$4
M36: 【ロイヤリティはこのP/Lだけで数えます】
M37: ・固定分 50,050円は左の経費表に入力しないこと（2026年版はここが二重計上の疑いだった）
M38: ・個別ロイは左の経費表に科目「個別ロイ」で入力する。P/Lは15行目で引いて19行目で足すので、数えるのは1回だけ
M39: 【人件費は2つに分けます】
M40: ・現場人件費(原価) … 現場に出た分。原価に入る
M41: ・固定給(販管費) … 和真さんの固定給40万＋プール10万、新人の給与。販管費に入る
M42: ・歩合（経常利益×45%）の行は2027年から使いません
M43: 【保険料・通信費は「その他」に入れないこと】
M44: ・賠償保険 43,760／通信費 8,470／日新火災 18,050 ＝ 月70,280円。科目を独立させました

Sheet 7月_支出成績
A1: ◆ 7月の経費入力。3行目から下へ足していってよい。右の月次P/Lは行が動かないので壊れない | M1: ▼ 月次P/L（この位置は固定。左の経費表を何行足してもずれません）
A2: No. | B2: 日付 | C2: 時刻 | D2: 品目 | E2: 科目 | F2: 金額 | G2: 備考 | H2: 現金立替え | M2: 項目 | N2: 金額 | O2: 計算の中身 | Q2: ▼ 科目別 集計
M3: 売上 | N3: ='7月_売上顧客'!$L$4 | O3: 7月_売上顧客 の合計売上 | Q3: 科目 | R3: 金額
M4: エアコン台数(参考) | N4: =COUNTIFS('7月_売上顧客'!$M$5:$M$504,"エアコン(ノーマル)")+COUNTIFS('7月_売上顧客'!$M$5:$M$504,"エアコン(ロボ)")+COUNTIFS('7月_売上顧客'!$M$5:$M$504,"天カセ")+COUNTIFS('7月_売上顧客'!$M$5:$M$504,"業務用エアコン1方向") | O4: エアコン(ノーマル/ロボ)・天カセ・業務用1方向 | Q4: 交通費 | R4: =SUMIFS($F$3:$F$302,$E$3:$E$302,"交通費")
M5: 換気扇台数(参考) | N5: =COUNTIFS('7月_売上顧客'!$M$5:$M$504,"換気扇") | O5: 実施メニュー＝換気扇 | Q5: 保険料 | R5: =SUMIFS($F$3:$F$302,$E$3:$E$302,"保険料")
M6: 浴室台数(参考) | N6: =COUNTIFS('7月_売上顧客'!$M$5:$M$504,"浴室") | O6: 実施メニュー＝浴室 | Q6: 通信費 | R6: =SUMIFS($F$3:$F$302,$E$3:$E$302,"通信費")
M7: 資材費 | N7: =N4*373+N5*176+N6*149 | O7: エアコン373 + 換気扇176 + 浴室149 | Q7: 広告費 | R7: =SUMIFS($F$3:$F$302,$E$3:$E$302,"広告費")
M8: 外注費（協力業者） | N8: =SUMIFS($F$3:$F$302,$E$3:$E$302,"外注費") | O8: 経費表の科目＝外注費。★2027年から原価として独立 | Q8: 耐久品 | R8: =SUMIFS($F$3:$F$302,$E$3:$E$302,"耐久品")
M9: 現場人件費（原価） | N9: =SUMIFS($F$3:$F$302,$E$3:$E$302,"現場人件費(原価)") | O9: 経費表の科目＝現場人件費(原価) | Q9: 備品 | R9: =SUMIFS($F$3:$F$302,$E$3:$E$302,"備品")
M10: 原価合計 | N10: =N7+N8+N9 | O10: 資材費＋外注費＋現場人件費 | Q10: 個別ロイ | R10: =SUMIFS($F$3:$F$302,$E$3:$E$302,"個別ロイ")
M11: 売上総利益 | N11: =N3-N10 | O11: 売上 − 原価合計 | Q11: 現場人件費(原価) | R11: =SUMIFS($F$3:$F$302,$E$3:$E$302,"現場人件費(原価)")
Q12: 固定給(販管費) | R12: =SUMIFS($F$3:$F$302,$E$3:$E$302,"固定給(販管費)")
M13: 経費合計（左の表） | N13: =SUM($F$3:$F$302) | O13: 左の経費入力表の金額合計 | Q13: 外注費 | R13: =SUMIFS($F$3:$F$302,$E$3:$E$302,"外注費")
M14: − 原価へ回した分 | N14: =-(N8+N9) | O14: 外注費・現場人件費は原価で数えたので戻す | Q14: その他(備考へ) | R14: =SUMIFS($F$3:$F$302,$E$3:$E$302,"その他(備考へ)")
M15: − 個別ロイ（下で計上） | N15: =-SUMIFS($F$3:$F$302,$E$3:$E$302,"個別ロイ") | O15: ★二重計上を防ぐため、ここで一度引く | Q15: 合計 | R15: =SUM(R4:R14)
M16: ロイヤリティ 固定分 | N16: =IF($N$3+$N$13=0,0,50050) | O16: ★50,050円。左の経費表には入力しないこと（まだ動いていない月は0）
M17: ロイヤリティ 38%分 | N17: =SUMIFS('7月_売上顧客'!$L$5:$L$504,'7月_売上顧客'!$V$5:$V$504,"38%")*0.38 | O17: 本舗ロイ区分＝38% の売上 × 38%
M18: ロイヤリティ 10%分 | N18: =SUMIFS('7月_売上顧客'!$L$5:$L$504,'7月_売上顧客'!$V$5:$V$504,"10%")*0.1 | O18: 本舗ロイ区分＝10% の売上 × 10%
M19: ロイヤリティ 個別実額 | N19: =SUMIFS($F$3:$F$302,$E$3:$E$302,"個別ロイ") | O19: 経費表の科目＝個別ロイ（toB・楽ラクーン等）
M20: ロイヤリティ 合計 | N20: =N16+N17+N18+N19 | O20: 固定＋38%＋10%＋個別
M21: 販売管理費 | N21: =N13+N14+N15+N20 | O21: 経費合計 − 原価分 − 個別ロイ ＋ ロイヤリティ合計
M22: 営業利益 | N22: =N11-N21 | O22: 売上総利益 − 販売管理費
M23: 融資返済 | N23: =IF($N$3+$N$13=0,0,38059) | O23: 固定 38,059円（まだ動いていない月は0）
M24: 経常利益 | N24: =N22-N23 | O24: 営業利益 − 融資返済
M26: 経常利益率 | N26: =IFERROR(N24/N3,0) | O26: 経常利益 ÷ 売上
M28: ▼ 計画（中立）との比較
M29: 計画 売上 | N29: 2740000
M30: 実績 − 計画（売上） | N30: =N3-N29 | O30: マイナスなら赤
M31: 計画 経常利益 | N31: 813684
M32: 実績 − 計画（経常） | N32: =N24-N31 | O32: マイナスなら赤
M33: 計画 件数 | N33: 68
M34: 実績 件数 | N34: ='7月_売上顧客'!$E$4
M36: 【ロイヤリティはこのP/Lだけで数えます】
M37: ・固定分 50,050円は左の経費表に入力しないこと（2026年版はここが二重計上の疑いだった）
M38: ・個別ロイは左の経費表に科目「個別ロイ」で入力する。P/Lは15行目で引いて19行目で足すので、数えるのは1回だけ
M39: 【人件費は2つに分けます】
M40: ・現場人件費(原価) … 現場に出た分。原価に入る
M41: ・固定給(販管費) … 和真さんの固定給40万＋プール10万、新人の給与。販管費に入る
M42: ・歩合（経常利益×45%）の行は2027年から使いません
M43: 【保険料・通信費は「その他」に入れないこと】
M44: ・賠償保険 43,760／通信費 8,470／日新火災 18,050 ＝ 月70,280円。科目を独立させました

Sheet 8月_支出成績
A1: ◆ 8月の経費入力。3行目から下へ足していってよい。右の月次P/Lは行が動かないので壊れない | M1: ▼ 月次P/L（この位置は固定。左の経費表を何行足してもずれません）
A2: No. | B2: 日付 | C2: 時刻 | D2: 品目 | E2: 科目 | F2: 金額 | G2: 備考 | H2: 現金立替え | M2: 項目 | N2: 金額 | O2: 計算の中身 | Q2: ▼ 科目別 集計
M3: 売上 | N3: ='8月_売上顧客'!$L$4 | O3: 8月_売上顧客 の合計売上 | Q3: 科目 | R3: 金額
M4: エアコン台数(参考) | N4: =COUNTIFS('8月_売上顧客'!$M$5:$M$504,"エアコン(ノーマル)")+COUNTIFS('8月_売上顧客'!$M$5:$M$504,"エアコン(ロボ)")+COUNTIFS('8月_売上顧客'!$M$5:$M$504,"天カセ")+COUNTIFS('8月_売上顧客'!$M$5:$M$504,"業務用エアコン1方向") | O4: エアコン(ノーマル/ロボ)・天カセ・業務用1方向 | Q4: 交通費 | R4: =SUMIFS($F$3:$F$302,$E$3:$E$302,"交通費")
M5: 換気扇台数(参考) | N5: =COUNTIFS('8月_売上顧客'!$M$5:$M$504,"換気扇") | O5: 実施メニュー＝換気扇 | Q5: 保険料 | R5: =SUMIFS($F$3:$F$302,$E$3:$E$302,"保険料")
M6: 浴室台数(参考) | N6: =COUNTIFS('8月_売上顧客'!$M$5:$M$504,"浴室") | O6: 実施メニュー＝浴室 | Q6: 通信費 | R6: =SUMIFS($F$3:$F$302,$E$3:$E$302,"通信費")
M7: 資材費 | N7: =N4*373+N5*176+N6*149 | O7: エアコン373 + 換気扇176 + 浴室149 | Q7: 広告費 | R7: =SUMIFS($F$3:$F$302,$E$3:$E$302,"広告費")
M8: 外注費（協力業者） | N8: =SUMIFS($F$3:$F$302,$E$3:$E$302,"外注費") | O8: 経費表の科目＝外注費。★2027年から原価として独立 | Q8: 耐久品 | R8: =SUMIFS($F$3:$F$302,$E$3:$E$302,"耐久品")
M9: 現場人件費（原価） | N9: =SUMIFS($F$3:$F$302,$E$3:$E$302,"現場人件費(原価)") | O9: 経費表の科目＝現場人件費(原価) | Q9: 備品 | R9: =SUMIFS($F$3:$F$302,$E$3:$E$302,"備品")
M10: 原価合計 | N10: =N7+N8+N9 | O10: 資材費＋外注費＋現場人件費 | Q10: 個別ロイ | R10: =SUMIFS($F$3:$F$302,$E$3:$E$302,"個別ロイ")
M11: 売上総利益 | N11: =N3-N10 | O11: 売上 − 原価合計 | Q11: 現場人件費(原価) | R11: =SUMIFS($F$3:$F$302,$E$3:$E$302,"現場人件費(原価)")
Q12: 固定給(販管費) | R12: =SUMIFS($F$3:$F$302,$E$3:$E$302,"固定給(販管費)")
M13: 経費合計（左の表） | N13: =SUM($F$3:$F$302) | O13: 左の経費入力表の金額合計 | Q13: 外注費 | R13: =SUMIFS($F$3:$F$302,$E$3:$E$302,"外注費")
M14: − 原価へ回した分 | N14: =-(N8+N9) | O14: 外注費・現場人件費は原価で数えたので戻す | Q14: その他(備考へ) | R14: =SUMIFS($F$3:$F$302,$E$3:$E$302,"その他(備考へ)")
M15: − 個別ロイ（下で計上） | N15: =-SUMIFS($F$3:$F$302,$E$3:$E$302,"個別ロイ") | O15: ★二重計上を防ぐため、ここで一度引く | Q15: 合計 | R15: =SUM(R4:R14)
M16: ロイヤリティ 固定分 | N16: =IF($N$3+$N$13=0,0,50050) | O16: ★50,050円。左の経費表には入力しないこと（まだ動いていない月は0）
M17: ロイヤリティ 38%分 | N17: =SUMIFS('8月_売上顧客'!$L$5:$L$504,'8月_売上顧客'!$V$5:$V$504,"38%")*0.38 | O17: 本舗ロイ区分＝38% の売上 × 38%
M18: ロイヤリティ 10%分 | N18: =SUMIFS('8月_売上顧客'!$L$5:$L$504,'8月_売上顧客'!$V$5:$V$504,"10%")*0.1 | O18: 本舗ロイ区分＝10% の売上 × 10%
M19: ロイヤリティ 個別実額 | N19: =SUMIFS($F$3:$F$302,$E$3:$E$302,"個別ロイ") | O19: 経費表の科目＝個別ロイ（toB・楽ラクーン等）
M20: ロイヤリティ 合計 | N20: =N16+N17+N18+N19 | O20: 固定＋38%＋10%＋個別
M21: 販売管理費 | N21: =N13+N14+N15+N20 | O21: 経費合計 − 原価分 − 個別ロイ ＋ ロイヤリティ合計
M22: 営業利益 | N22: =N11-N21 | O22: 売上総利益 − 販売管理費
M23: 融資返済 | N23: =IF($N$3+$N$13=0,0,38059) | O23: 固定 38,059円（まだ動いていない月は0）
M24: 経常利益 | N24: =N22-N23 | O24: 営業利益 − 融資返済
M26: 経常利益率 | N26: =IFERROR(N24/N3,0) | O26: 経常利益 ÷ 売上
M28: ▼ 計画（中立）との比較
M29: 計画 売上 | N29: 1600000
M30: 実績 − 計画（売上） | N30: =N3-N29 | O30: マイナスなら赤
M31: 計画 経常利益 | N31: 115573
M32: 実績 − 計画（経常） | N32: =N24-N31 | O32: マイナスなら赤
M33: 計画 件数 | N33: 42
M34: 実績 件数 | N34: ='8月_売上顧客'!$E$4
M36: 【ロイヤリティはこのP/Lだけで数えます】
M37: ・固定分 50,050円は左の経費表に入力しないこと（2026年版はここが二重計上の疑いだった）
M38: ・個別ロイは左の経費表に科目「個別ロイ」で入力する。P/Lは15行目で引いて19行目で足すので、数えるのは1回だけ
M39: 【人件費は2つに分けます】
M40: ・現場人件費(原価) … 現場に出た分。原価に入る
M41: ・固定給(販管費) … 和真さんの固定給40万＋プール10万、新人の給与。販管費に入る
M42: ・歩合（経常利益×45%）の行は2027年から使いません
M43: 【保険料・通信費は「その他」に入れないこと】
M44: ・賠償保険 43,760／通信費 8,470／日新火災 18,050 ＝ 月70,280円。科目を独立させました

Sheet 9月_支出成績
A1: ◆ 9月の経費入力。3行目から下へ足していってよい。右の月次P/Lは行が動かないので壊れない | M1: ▼ 月次P/L（この位置は固定。左の経費表を何行足してもずれません）
A2: No. | B2: 日付 | C2: 時刻 | D2: 品目 | E2: 科目 | F2: 金額 | G2: 備考 | H2: 現金立替え | M2: 項目 | N2: 金額 | O2: 計算の中身 | Q2: ▼ 科目別 集計
M3: 売上 | N3: ='9月_売上顧客'!$L$4 | O3: 9月_売上顧客 の合計売上 | Q3: 科目 | R3: 金額
M4: エアコン台数(参考) | N4: =COUNTIFS('9月_売上顧客'!$M$5:$M$504,"エアコン(ノーマル)")+COUNTIFS('9月_売上顧客'!$M$5:$M$504,"エアコン(ロボ)")+COUNTIFS('9月_売上顧客'!$M$5:$M$504,"天カセ")+COUNTIFS('9月_売上顧客'!$M$5:$M$504,"業務用エアコン1方向") | O4: エアコン(ノーマル/ロボ)・天カセ・業務用1方向 | Q4: 交通費 | R4: =SUMIFS($F$3:$F$302,$E$3:$E$302,"交通費")
M5: 換気扇台数(参考) | N5: =COUNTIFS('9月_売上顧客'!$M$5:$M$504,"換気扇") | O5: 実施メニュー＝換気扇 | Q5: 保険料 | R5: =SUMIFS($F$3:$F$302,$E$3:$E$302,"保険料")
M6: 浴室台数(参考) | N6: =COUNTIFS('9月_売上顧客'!$M$5:$M$504,"浴室") | O6: 実施メニュー＝浴室 | Q6: 通信費 | R6: =SUMIFS($F$3:$F$302,$E$3:$E$302,"通信費")
M7: 資材費 | N7: =N4*373+N5*176+N6*149 | O7: エアコン373 + 換気扇176 + 浴室149 | Q7: 広告費 | R7: =SUMIFS($F$3:$F$302,$E$3:$E$302,"広告費")
M8: 外注費（協力業者） | N8: =SUMIFS($F$3:$F$302,$E$3:$E$302,"外注費") | O8: 経費表の科目＝外注費。★2027年から原価として独立 | Q8: 耐久品 | R8: =SUMIFS($F$3:$F$302,$E$3:$E$302,"耐久品")
M9: 現場人件費（原価） | N9: =SUMIFS($F$3:$F$302,$E$3:$E$302,"現場人件費(原価)") | O9: 経費表の科目＝現場人件費(原価) | Q9: 備品 | R9: =SUMIFS($F$3:$F$302,$E$3:$E$302,"備品")
M10: 原価合計 | N10: =N7+N8+N9 | O10: 資材費＋外注費＋現場人件費 | Q10: 個別ロイ | R10: =SUMIFS($F$3:$F$302,$E$3:$E$302,"個別ロイ")
M11: 売上総利益 | N11: =N3-N10 | O11: 売上 − 原価合計 | Q11: 現場人件費(原価) | R11: =SUMIFS($F$3:$F$302,$E$3:$E$302,"現場人件費(原価)")
Q12: 固定給(販管費) | R12: =SUMIFS($F$3:$F$302,$E$3:$E$302,"固定給(販管費)")
M13: 経費合計（左の表） | N13: =SUM($F$3:$F$302) | O13: 左の経費入力表の金額合計 | Q13: 外注費 | R13: =SUMIFS($F$3:$F$302,$E$3:$E$302,"外注費")
M14: − 原価へ回した分 | N14: =-(N8+N9) | O14: 外注費・現場人件費は原価で数えたので戻す | Q14: その他(備考へ) | R14: =SUMIFS($F$3:$F$302,$E$3:$E$302,"その他(備考へ)")
M15: − 個別ロイ（下で計上） | N15: =-SUMIFS($F$3:$F$302,$E$3:$E$302,"個別ロイ") | O15: ★二重計上を防ぐため、ここで一度引く | Q15: 合計 | R15: =SUM(R4:R14)
M16: ロイヤリティ 固定分 | N16: =IF($N$3+$N$13=0,0,50050) | O16: ★50,050円。左の経費表には入力しないこと（まだ動いていない月は0）
M17: ロイヤリティ 38%分 | N17: =SUMIFS('9月_売上顧客'!$L$5:$L$504,'9月_売上顧客'!$V$5:$V$504,"38%")*0.38 | O17: 本舗ロイ区分＝38% の売上 × 38%
M18: ロイヤリティ 10%分 | N18: =SUMIFS('9月_売上顧客'!$L$5:$L$504,'9月_売上顧客'!$V$5:$V$504,"10%")*0.1 | O18: 本舗ロイ区分＝10% の売上 × 10%
M19: ロイヤリティ 個別実額 | N19: =SUMIFS($F$3:$F$302,$E$3:$E$302,"個別ロイ") | O19: 経費表の科目＝個別ロイ（toB・楽ラクーン等）
M20: ロイヤリティ 合計 | N20: =N16+N17+N18+N19 | O20: 固定＋38%＋10%＋個別
M21: 販売管理費 | N21: =N13+N14+N15+N20 | O21: 経費合計 − 原価分 − 個別ロイ ＋ ロイヤリティ合計
M22: 営業利益 | N22: =N11-N21 | O22: 売上総利益 − 販売管理費
M23: 融資返済 | N23: =IF($N$3+$N$13=0,0,38059) | O23: 固定 38,059円（まだ動いていない月は0）
M24: 経常利益 | N24: =N22-N23 | O24: 営業利益 − 融資返済
M26: 経常利益率 | N26: =IFERROR(N24/N3,0) | O26: 経常利益 ÷ 売上
M28: ▼ 計画（中立）との比較
M29: 計画 売上 | N29: 1800000
M30: 実績 − 計画（売上） | N30: =N3-N29 | O30: マイナスなら赤
M31: 計画 経常利益 | N31: 231903
M32: 実績 − 計画（経常） | N32: =N24-N31 | O32: マイナスなら赤
M33: 計画 件数 | N33: 46
M34: 実績 件数 | N34: ='9月_売上顧客'!$E$4
M36: 【ロイヤリティはこのP/Lだけで数えます】
M37: ・固定分 50,050円は左の経費表に入力しないこと（2026年版はここが二重計上の疑いだった）
M38: ・個別ロイは左の経費表に科目「個別ロイ」で入力する。P/Lは15行目で引いて19行目で足すので、数えるのは1回だけ
M39: 【人件費は2つに分けます】
M40: ・現場人件費(原価) … 現場に出た分。原価に入る
M41: ・固定給(販管費) … 和真さんの固定給40万＋プール10万、新人の給与。販管費に入る
M42: ・歩合（経常利益×45%）の行は2027年から使いません
M43: 【保険料・通信費は「その他」に入れないこと】
M44: ・賠償保険 43,760／通信費 8,470／日新火災 18,050 ＝ 月70,280円。科目を独立させました

Sheet 10月_支出成績
A1: ◆ 10月の経費入力。3行目から下へ足していってよい。右の月次P/Lは行が動かないので壊れない | M1: ▼ 月次P/L（この位置は固定。左の経費表を何行足してもずれません）
A2: No. | B2: 日付 | C2: 時刻 | D2: 品目 | E2: 科目 | F2: 金額 | G2: 備考 | H2: 現金立替え | M2: 項目 | N2: 金額 | O2: 計算の中身 | Q2: ▼ 科目別 集計
M3: 売上 | N3: ='10月_売上顧客'!$L$4 | O3: 10月_売上顧客 の合計売上 | Q3: 科目 | R3: 金額
M4: エアコン台数(参考) | N4: =COUNTIFS('10月_売上顧客'!$M$5:$M$504,"エアコン(ノーマル)")+COUNTIFS('10月_売上顧客'!$M$5:$M$504,"エアコン(ロボ)")+COUNTIFS('10月_売上顧客'!$M$5:$M$504,"天カセ")+COUNTIFS('10月_売上顧客'!$M$5:$M$504,"業務用エアコン1方向") | O4: エアコン(ノーマル/ロボ)・天カセ・業務用1方向 | Q4: 交通費 | R4: =SUMIFS($F$3:$F$302,$E$3:$E$302,"交通費")
M5: 換気扇台数(参考) | N5: =COUNTIFS('10月_売上顧客'!$M$5:$M$504,"換気扇") | O5: 実施メニュー＝換気扇 | Q5: 保険料 | R5: =SUMIFS($F$3:$F$302,$E$3:$E$302,"保険料")
M6: 浴室台数(参考) | N6: =COUNTIFS('10月_売上顧客'!$M$5:$M$504,"浴室") | O6: 実施メニュー＝浴室 | Q6: 通信費 | R6: =SUMIFS($F$3:$F$302,$E$3:$E$302,"通信費")
M7: 資材費 | N7: =N4*373+N5*176+N6*149 | O7: エアコン373 + 換気扇176 + 浴室149 | Q7: 広告費 | R7: =SUMIFS($F$3:$F$302,$E$3:$E$302,"広告費")
M8: 外注費（協力業者） | N8: =SUMIFS($F$3:$F$302,$E$3:$E$302,"外注費") | O8: 経費表の科目＝外注費。★2027年から原価として独立 | Q8: 耐久品 | R8: =SUMIFS($F$3:$F$302,$E$3:$E$302,"耐久品")
M9: 現場人件費（原価） | N9: =SUMIFS($F$3:$F$302,$E$3:$E$302,"現場人件費(原価)") | O9: 経費表の科目＝現場人件費(原価) | Q9: 備品 | R9: =SUMIFS($F$3:$F$302,$E$3:$E$302,"備品")
M10: 原価合計 | N10: =N7+N8+N9 | O10: 資材費＋外注費＋現場人件費 | Q10: 個別ロイ | R10: =SUMIFS($F$3:$F$302,$E$3:$E$302,"個別ロイ")
M11: 売上総利益 | N11: =N3-N10 | O11: 売上 − 原価合計 | Q11: 現場人件費(原価) | R11: =SUMIFS($F$3:$F$302,$E$3:$E$302,"現場人件費(原価)")
Q12: 固定給(販管費) | R12: =SUMIFS($F$3:$F$302,$E$3:$E$302,"固定給(販管費)")
M13: 経費合計（左の表） | N13: =SUM($F$3:$F$302) | O13: 左の経費入力表の金額合計 | Q13: 外注費 | R13: =SUMIFS($F$3:$F$302,$E$3:$E$302,"外注費")
M14: − 原価へ回した分 | N14: =-(N8+N9) | O14: 外注費・現場人件費は原価で数えたので戻す | Q14: その他(備考へ) | R14: =SUMIFS($F$3:$F$302,$E$3:$E$302,"その他(備考へ)")
M15: − 個別ロイ（下で計上） | N15: =-SUMIFS($F$3:$F$302,$E$3:$E$302,"個別ロイ") | O15: ★二重計上を防ぐため、ここで一度引く | Q15: 合計 | R15: =SUM(R4:R14)
M16: ロイヤリティ 固定分 | N16: =IF($N$3+$N$13=0,0,50050) | O16: ★50,050円。左の経費表には入力しないこと（まだ動いていない月は0）
M17: ロイヤリティ 38%分 | N17: =SUMIFS('10月_売上顧客'!$L$5:$L$504,'10月_売上顧客'!$V$5:$V$504,"38%")*0.38 | O17: 本舗ロイ区分＝38% の売上 × 38%
M18: ロイヤリティ 10%分 | N18: =SUMIFS('10月_売上顧客'!$L$5:$L$504,'10月_売上顧客'!$V$5:$V$504,"10%")*0.1 | O18: 本舗ロイ区分＝10% の売上 × 10%
M19: ロイヤリティ 個別実額 | N19: =SUMIFS($F$3:$F$302,$E$3:$E$302,"個別ロイ") | O19: 経費表の科目＝個別ロイ（toB・楽ラクーン等）
M20: ロイヤリティ 合計 | N20: =N16+N17+N18+N19 | O20: 固定＋38%＋10%＋個別
M21: 販売管理費 | N21: =N13+N14+N15+N20 | O21: 経費合計 − 原価分 − 個別ロイ ＋ ロイヤリティ合計
M22: 営業利益 | N22: =N11-N21 | O22: 売上総利益 − 販売管理費
M23: 融資返済 | N23: =IF($N$3+$N$13=0,0,38059) | O23: 固定 38,059円（まだ動いていない月は0）
M24: 経常利益 | N24: =N22-N23 | O24: 営業利益 − 融資返済
M26: 経常利益率 | N26: =IFERROR(N24/N3,0) | O26: 経常利益 ÷ 売上
M28: ▼ 計画（中立）との比較
M29: 計画 売上 | N29: 2320000
M30: 実績 − 計画（売上） | N30: =N3-N29 | O30: マイナスなら赤
M31: 計画 経常利益 | N31: 503051
M32: 実績 − 計画（経常） | N32: =N24-N31 | O32: マイナスなら赤
M33: 計画 件数 | N33: 60
M34: 実績 件数 | N34: ='10月_売上顧客'!$E$4
M36: 【ロイヤリティはこのP/Lだけで数えます】
M37: ・固定分 50,050円は左の経費表に入力しないこと（2026年版はここが二重計上の疑いだった）
M38: ・個別ロイは左の経費表に科目「個別ロイ」で入力する。P/Lは15行目で引いて19行目で足すので、数えるのは1回だけ
M39: 【人件費は2つに分けます】
M40: ・現場人件費(原価) … 現場に出た分。原価に入る
M41: ・固定給(販管費) … 和真さんの固定給40万＋プール10万、新人の給与。販管費に入る
M42: ・歩合（経常利益×45%）の行は2027年から使いません
M43: 【保険料・通信費は「その他」に入れないこと】
M44: ・賠償保険 43,760／通信費 8,470／日新火災 18,050 ＝ 月70,280円。科目を独立させました

Sheet 11月_支出成績
A1: ◆ 11月の経費入力。3行目から下へ足していってよい。右の月次P/Lは行が動かないので壊れない | M1: ▼ 月次P/L（この位置は固定。左の経費表を何行足してもずれません）
A2: No. | B2: 日付 | C2: 時刻 | D2: 品目 | E2: 科目 | F2: 金額 | G2: 備考 | H2: 現金立替え | M2: 項目 | N2: 金額 | O2: 計算の中身 | Q2: ▼ 科目別 集計
M3: 売上 | N3: ='11月_売上顧客'!$L$4 | O3: 11月_売上顧客 の合計売上 | Q3: 科目 | R3: 金額
M4: エアコン台数(参考) | N4: =COUNTIFS('11月_売上顧客'!$M$5:$M$504,"エアコン(ノーマル)")+COUNTIFS('11月_売上顧客'!$M$5:$M$504,"エアコン(ロボ)")+COUNTIFS('11月_売上顧客'!$M$5:$M$504,"天カセ")+COUNTIFS('11月_売上顧客'!$M$5:$M$504,"業務用エアコン1方向") | O4: エアコン(ノーマル/ロボ)・天カセ・業務用1方向 | Q4: 交通費 | R4: =SUMIFS($F$3:$F$302,$E$3:$E$302,"交通費")
M5: 換気扇台数(参考) | N5: =COUNTIFS('11月_売上顧客'!$M$5:$M$504,"換気扇") | O5: 実施メニュー＝換気扇 | Q5: 保険料 | R5: =SUMIFS($F$3:$F$302,$E$3:$E$302,"保険料")
M6: 浴室台数(参考) | N6: =COUNTIFS('11月_売上顧客'!$M$5:$M$504,"浴室") | O6: 実施メニュー＝浴室 | Q6: 通信費 | R6: =SUMIFS($F$3:$F$302,$E$3:$E$302,"通信費")
M7: 資材費 | N7: =N4*373+N5*176+N6*149 | O7: エアコン373 + 換気扇176 + 浴室149 | Q7: 広告費 | R7: =SUMIFS($F$3:$F$302,$E$3:$E$302,"広告費")
M8: 外注費（協力業者） | N8: =SUMIFS($F$3:$F$302,$E$3:$E$302,"外注費") | O8: 経費表の科目＝外注費。★2027年から原価として独立 | Q8: 耐久品 | R8: =SUMIFS($F$3:$F$302,$E$3:$E$302,"耐久品")
M9: 現場人件費（原価） | N9: =SUMIFS($F$3:$F$302,$E$3:$E$302,"現場人件費(原価)") | O9: 経費表の科目＝現場人件費(原価) | Q9: 備品 | R9: =SUMIFS($F$3:$F$302,$E$3:$E$302,"備品")
M10: 原価合計 | N10: =N7+N8+N9 | O10: 資材費＋外注費＋現場人件費 | Q10: 個別ロイ | R10: =SUMIFS($F$3:$F$302,$E$3:$E$302,"個別ロイ")
M11: 売上総利益 | N11: =N3-N10 | O11: 売上 − 原価合計 | Q11: 現場人件費(原価) | R11: =SUMIFS($F$3:$F$302,$E$3:$E$302,"現場人件費(原価)")
Q12: 固定給(販管費) | R12: =SUMIFS($F$3:$F$302,$E$3:$E$302,"固定給(販管費)")
M13: 経費合計（左の表） | N13: =SUM($F$3:$F$302) | O13: 左の経費入力表の金額合計 | Q13: 外注費 | R13: =SUMIFS($F$3:$F$302,$E$3:$E$302,"外注費")
M14: − 原価へ回した分 | N14: =-(N8+N9) | O14: 外注費・現場人件費は原価で数えたので戻す | Q14: その他(備考へ) | R14: =SUMIFS($F$3:$F$302,$E$3:$E$302,"その他(備考へ)")
M15: − 個別ロイ（下で計上） | N15: =-SUMIFS($F$3:$F$302,$E$3:$E$302,"個別ロイ") | O15: ★二重計上を防ぐため、ここで一度引く | Q15: 合計 | R15: =SUM(R4:R14)
M16: ロイヤリティ 固定分 | N16: =IF($N$3+$N$13=0,0,50050) | O16: ★50,050円。左の経費表には入力しないこと（まだ動いていない月は0）
M17: ロイヤリティ 38%分 | N17: =SUMIFS('11月_売上顧客'!$L$5:$L$504,'11月_売上顧客'!$V$5:$V$504,"38%")*0.38 | O17: 本舗ロイ区分＝38% の売上 × 38%
M18: ロイヤリティ 10%分 | N18: =SUMIFS('11月_売上顧客'!$L$5:$L$504,'11月_売上顧客'!$V$5:$V$504,"10%")*0.1 | O18: 本舗ロイ区分＝10% の売上 × 10%
M19: ロイヤリティ 個別実額 | N19: =SUMIFS($F$3:$F$302,$E$3:$E$302,"個別ロイ") | O19: 経費表の科目＝個別ロイ（toB・楽ラクーン等）
M20: ロイヤリティ 合計 | N20: =N16+N17+N18+N19 | O20: 固定＋38%＋10%＋個別
M21: 販売管理費 | N21: =N13+N14+N15+N20 | O21: 経費合計 − 原価分 − 個別ロイ ＋ ロイヤリティ合計
M22: 営業利益 | N22: =N11-N21 | O22: 売上総利益 − 販売管理費
M23: 融資返済 | N23: =IF($N$3+$N$13=0,0,38059) | O23: 固定 38,059円（まだ動いていない月は0）
M24: 経常利益 | N24: =N22-N23 | O24: 営業利益 − 融資返済
M26: 経常利益率 | N26: =IFERROR(N24/N3,0) | O26: 経常利益 ÷ 売上
M28: ▼ 計画（中立）との比較
M29: 計画 売上 | N29: 2480000
M30: 実績 − 計画（売上） | N30: =N3-N29 | O30: マイナスなら赤
M31: 計画 経常利益 | N31: 579935
M32: 実績 − 計画（経常） | N32: =N24-N31 | O32: マイナスなら赤
M33: 計画 件数 | N33: 64
M34: 実績 件数 | N34: ='11月_売上顧客'!$E$4
M36: 【ロイヤリティはこのP/Lだけで数えます】
M37: ・固定分 50,050円は左の経費表に入力しないこと（2026年版はここが二重計上の疑いだった）
M38: ・個別ロイは左の経費表に科目「個別ロイ」で入力する。P/Lは15行目で引いて19行目で足すので、数えるのは1回だけ
M39: 【人件費は2つに分けます】
M40: ・現場人件費(原価) … 現場に出た分。原価に入る
M41: ・固定給(販管費) … 和真さんの固定給40万＋プール10万、新人の給与。販管費に入る
M42: ・歩合（経常利益×45%）の行は2027年から使いません
M43: 【保険料・通信費は「その他」に入れないこと】
M44: ・賠償保険 43,760／通信費 8,470／日新火災 18,050 ＝ 月70,280円。科目を独立させました

Sheet 12月_支出成績
A1: ◆ 12月の経費入力。3行目から下へ足していってよい。右の月次P/Lは行が動かないので壊れない | M1: ▼ 月次P/L（この位置は固定。左の経費表を何行足してもずれません）
A2: No. | B2: 日付 | C2: 時刻 | D2: 品目 | E2: 科目 | F2: 金額 | G2: 備考 | H2: 現金立替え | M2: 項目 | N2: 金額 | O2: 計算の中身 | Q2: ▼ 科目別 集計
M3: 売上 | N3: ='12月_売上顧客'!$L$4 | O3: 12月_売上顧客 の合計売上 | Q3: 科目 | R3: 金額
M4: エアコン台数(参考) | N4: =COUNTIFS('12月_売上顧客'!$M$5:$M$504,"エアコン(ノーマル)")+COUNTIFS('12月_売上顧客'!$M$5:$M$504,"エアコン(ロボ)")+COUNTIFS('12月_売上顧客'!$M$5:$M$504,"天カセ")+COUNTIFS('12月_売上顧客'!$M$5:$M$504,"業務用エアコン1方向") | O4: エアコン(ノーマル/ロボ)・天カセ・業務用1方向 | Q4: 交通費 | R4: =SUMIFS($F$3:$F$302,$E$3:$E$302,"交通費")
M5: 換気扇台数(参考) | N5: =COUNTIFS('12月_売上顧客'!$M$5:$M$504,"換気扇") | O5: 実施メニュー＝換気扇 | Q5: 保険料 | R5: =SUMIFS($F$3:$F$302,$E$3:$E$302,"保険料")
M6: 浴室台数(参考) | N6: =COUNTIFS('12月_売上顧客'!$M$5:$M$504,"浴室") | O6: 実施メニュー＝浴室 | Q6: 通信費 | R6: =SUMIFS($F$3:$F$302,$E$3:$E$302,"通信費")
M7: 資材費 | N7: =N4*373+N5*176+N6*149 | O7: エアコン373 + 換気扇176 + 浴室149 | Q7: 広告費 | R7: =SUMIFS($F$3:$F$302,$E$3:$E$302,"広告費")
M8: 外注費（協力業者） | N8: =SUMIFS($F$3:$F$302,$E$3:$E$302,"外注費") | O8: 経費表の科目＝外注費。★2027年から原価として独立 | Q8: 耐久品 | R8: =SUMIFS($F$3:$F$302,$E$3:$E$302,"耐久品")
M9: 現場人件費（原価） | N9: =SUMIFS($F$3:$F$302,$E$3:$E$302,"現場人件費(原価)") | O9: 経費表の科目＝現場人件費(原価) | Q9: 備品 | R9: =SUMIFS($F$3:$F$302,$E$3:$E$302,"備品")
M10: 原価合計 | N10: =N7+N8+N9 | O10: 資材費＋外注費＋現場人件費 | Q10: 個別ロイ | R10: =SUMIFS($F$3:$F$302,$E$3:$E$302,"個別ロイ")
M11: 売上総利益 | N11: =N3-N10 | O11: 売上 − 原価合計 | Q11: 現場人件費(原価) | R11: =SUMIFS($F$3:$F$302,$E$3:$E$302,"現場人件費(原価)")
Q12: 固定給(販管費) | R12: =SUMIFS($F$3:$F$302,$E$3:$E$302,"固定給(販管費)")
M13: 経費合計（左の表） | N13: =SUM($F$3:$F$302) | O13: 左の経費入力表の金額合計 | Q13: 外注費 | R13: =SUMIFS($F$3:$F$302,$E$3:$E$302,"外注費")
M14: − 原価へ回した分 | N14: =-(N8+N9) | O14: 外注費・現場人件費は原価で数えたので戻す | Q14: その他(備考へ) | R14: =SUMIFS($F$3:$F$302,$E$3:$E$302,"その他(備考へ)")
M15: − 個別ロイ（下で計上） | N15: =-SUMIFS($F$3:$F$302,$E$3:$E$302,"個別ロイ") | O15: ★二重計上を防ぐため、ここで一度引く | Q15: 合計 | R15: =SUM(R4:R14)
M16: ロイヤリティ 固定分 | N16: =IF($N$3+$N$13=0,0,50050) | O16: ★50,050円。左の経費表には入力しないこと（まだ動いていない月は0）
M17: ロイヤリティ 38%分 | N17: =SUMIFS('12月_売上顧客'!$L$5:$L$504,'12月_売上顧客'!$V$5:$V$504,"38%")*0.38 | O17: 本舗ロイ区分＝38% の売上 × 38%
M18: ロイヤリティ 10%分 | N18: =SUMIFS('12月_売上顧客'!$L$5:$L$504,'12月_売上顧客'!$V$5:$V$504,"10%")*0.1 | O18: 本舗ロイ区分＝10% の売上 × 10%
M19: ロイヤリティ 個別実額 | N19: =SUMIFS($F$3:$F$302,$E$3:$E$302,"個別ロイ") | O19: 経費表の科目＝個別ロイ（toB・楽ラクーン等）
M20: ロイヤリティ 合計 | N20: =N16+N17+N18+N19 | O20: 固定＋38%＋10%＋個別
M21: 販売管理費 | N21: =N13+N14+N15+N20 | O21: 経費合計 − 原価分 − 個別ロイ ＋ ロイヤリティ合計
M22: 営業利益 | N22: =N11-N21 | O22: 売上総利益 − 販売管理費
M23: 融資返済 | N23: =IF($N$3+$N$13=0,0,38059) | O23: 固定 38,059円（まだ動いていない月は0）
M24: 経常利益 | N24: =N22-N23 | O24: 営業利益 − 融資返済
M26: 経常利益率 | N26: =IFERROR(N24/N3,0) | O26: 経常利益 ÷ 売上
M28: ▼ 計画（中立）との比較
M29: 計画 売上 | N29: 1940000
M30: 実績 − 計画（売上） | N30: =N3-N29 | O30: マイナスなら赤
M31: 計画 経常利益 | N31: 188439
M32: 実績 − 計画（経常） | N32: =N24-N31 | O32: マイナスなら赤
M33: 計画 件数 | N33: 45
M34: 実績 件数 | N34: ='12月_売上顧客'!$E$4
M36: 【ロイヤリティはこのP/Lだけで数えます】
M37: ・固定分 50,050円は左の経費表に入力しないこと（2026年版はここが二重計上の疑いだった）
M38: ・個別ロイは左の経費表に科目「個別ロイ」で入力する。P/Lは15行目で引いて19行目で足すので、数えるのは1回だけ
M39: 【人件費は2つに分けます】
M40: ・現場人件費(原価) … 現場に出た分。原価に入る
M41: ・固定給(販管費) … 和真さんの固定給40万＋プール10万、新人の給与。販管費に入る
M42: ・歩合（経常利益×45%）の行は2027年から使いません
M43: 【保険料・通信費は「その他」に入れないこと】
M44: ・賠償保険 43,760／通信費 8,470／日新火災 18,050 ＝ 月70,280円。科目を独立させました

Sheet 2027年計画
A1: 2027年 計画（正式目標＝中立）
A2: tools/plan2027.py --json の値をそのまま。ここは実績で書き換えないこと。
A4: 項目 | B4: 1月 | C4: 2月 | D4: 3月 | E4: 4月 | F4: 5月 | G4: 6月 | H4: 7月 | I4: 8月 | J4: 9月 | K4: 10月 | L4: 11月 | M4: 12月 | N4: 年計
A5: 売上 | B5: 1440000 | C5: 1280000 | D5: 1850000 | E5: 2260000 | F5: 2890000 | G5: 3400000 | H5: 2740000 | I5: 1600000 | J5: 1800000 | K5: 2320000 | L5: 2480000 | M5: 1940000 | N5: 26000000
A6: 件数 | B6: 37 | C6: 32 | D6: 46 | E6: 57 | F6: 70 | G6: 82 | H6: 68 | I6: 42 | J6: 46 | K6: 60 | L6: 64 | M6: 45 | N6: 649
A7: 平均単価 | B7: 38919 | C7: 40000 | D7: 40217 | E7: 39649 | F7: 41286 | G7: 41463 | H7: 40294 | I7: 38095 | J7: 39130 | K7: 38667 | L7: 38750 | M7: 43111 | N7: 40062
A8: 本舗売上 | B8: 215446 | C8: 191508 | D8: 276788 | E8: 338131 | F8: 432388 | G8: 508692 | H8: 409946 | I8: 239385 | J8: 269308 | K8: 347108 | L8: 371046 | M8: 290254 | N8: 3890000
A9: 原価_資材費 | B9: 8325 | C9: 7200 | D9: 10350 | E9: 12825 | F9: 15750 | G9: 18450 | H9: 15300 | I9: 9450 | J9: 10350 | K9: 13500 | L9: 14400 | M9: 10125 | N9: 146025
A10: 原価_外注費 | B10: 0 | C10: 0 | D10: 130000 | E10: 208000 | F10: 364000 | G10: 468000 | H10: 312000 | I10: 130000 | J10: 130000 | K10: 260000 | L10: 312000 | M10: 286000 | N10: 2600000
A11: 原価_補助人件費 | B11: 20000 | C11: 20000 | D11: 20000 | E11: 30000 | F11: 40000 | G11: 40000 | H11: 40000 | I11: 20000 | J11: 20000 | K11: 30000 | L11: 40000 | M11: 40000 | N11: 360000
A12: 原価_計 | B12: 28325 | C12: 27200 | D12: 160350 | E12: 250825 | F12: 419750 | G12: 526450 | H12: 367300 | I12: 159450 | J12: 160350 | K12: 303500 | L12: 366400 | M12: 336125 | N12: 3106025
A13: 売上総利益 | B13: 1411675 | C13: 1252800 | D13: 1689650 | E13: 2009175 | F13: 2470250 | G13: 2873550 | H13: 2372700 | I13: 1440550 | J13: 1639650 | K13: 2016500 | L13: 2113600 | M13: 1603875 | N13: 22893975
A14: 販管_固定経費 | B14: 159708 | C14: 159708 | D14: 159708 | E14: 159708 | F14: 159708 | G14: 159708 | H14: 159708 | I14: 159708 | J14: 159708 | K14: 159708 | L14: 159708 | M14: 159708 | N14: 1916496
A15: 販管_ロイヤリティ固定 | B15: 50050 | C15: 50050 | D15: 50050 | E15: 50050 | F15: 50050 | G15: 50050 | H15: 50050 | I15: 50050 | J15: 50050 | K15: 50050 | L15: 50050 | M15: 50050 | N15: 600600
A16: 販管_ロイヤリティ | B16: 84024 | C16: 74688 | D16: 107947 | E16: 131871 | F16: 168631 | G16: 198390 | H16: 159879 | I16: 93360 | J16: 105030 | K16: 135372 | L16: 144708 | M16: 113199 | N16: 1517099
... A26: 外注件数 | B26: 0 | C26: 0 | D26: 5 | E26: 8 | F26: 14 | G26: 18 | H26: 12 | I26: 5 | J26: 5 | K26: 10 | L26: 12 | M26: 11 | N26: 100
A29: ▼ 3パターンの年計（参考）
A30: シナリオ | B30: 売上 | C30: 件数 | D30: 平均単価 | E30: 経常利益 | F30: 広告費(年) | G30: ④自社ネット新規(年) | H30: 備考
A31: 保守 | B31: 20000000 | C31: 513 | D31: 38986 | E31: 2113670 | F31: 25万 | G31: 61 | H31: テストして伸びなかった形
A32: 中立 | B32: 26000000 | C32: 649 | D32: 40062 | E32: 5655072 | F32: 80万 | G32: 143 | H32: ★正式目標。段2まで上がった形
A33: 攻め | B33: 32000000 | C33: 774 | D33: 41344 | E33: 8818945 | F33: 100万 | G33: 192 | H33: 段3まで上がった形
A35: 【判定ゲート】
A36: 3月末 … Q1累計が 380万に届いているか（保守290万／攻め465万）。届かなければ保守の組み方へ切り替え
A37: 6月末 … 上期累計が中立比85%以上か。下回れば広告の段を落とし、協力業者の稼働を縮小
A38: 9月末 … Q3累計が中立比85%以上か。年末商戦の打ち手を前倒し。10月1日のLP公開は死守
A39: 12月末 … 通年着地を2028年の人員計画へ
A41: 【前提】正社員1名を3月入社／協力業者3社を1〜2月に契約し3月から稼働（オーナー指示 2026-09-13）
A42: 【出典】docs/2027-数値目標.md ／ tools/plan2027.py

Sheet 年間成績
A1: 2027年 年間成績（予算対実績・月別P/L）
A2: 青い数字は計画。白い数字は各月タブから自動で入ります。手入力するのは「2026年 売上」の行だけです。
A4: 年間 計画売上 | B4: =$N$18 | D4: ★ ここだけ見れば「計画に乗っているか」が分かります。詳しくはダッシュボード。
A5: 売上 実績累計 | B5: =$N$20
A6: 対計画 差額 | B6: =B5-B4
A7: 達成率 | B7: =IFERROR(B5/B4,0)
A9: 年間 計画 経常利益 | B9: 5655072
A10: 経常利益 実績累計 | B10: =$N$43
A12: ④自社ネット新規 年間目標 | B12: =$N$29
A13: ④自社ネット新規 実績 | B13: =$N$30
A14: 経常利益がマイナスの月数 | B14: =COUNTIF($B$43:$M$43,"<0")
A17: 項目 | B17: 1月 | C17: 2月 | D17: 3月 | E17: 4月 | F17: 5月 | G17: 6月 | H17: 7月 | I17: 8月 | J17: 9月 | K17: 10月 | L17: 11月 | M17: 12月 | N17: 年計 | O17: 説明
A18: 予算（計画売上） | B18: 1440000 | C18: 1280000 | D18: 1850000 | E18: 2260000 | F18: 2890000 | G18: 3400000 | H18: 2740000 | I18: 1600000 | J18: 1800000 | K18: 2320000 | L18: 2480000 | M18: 1940000 | N18: =SUM(B18:M18) | O18: tools/plan2027.py の中立
A19: 年間割合 | B19: =IFERROR(B18/$N$18,0) | C19: =IFERROR(C18/$N$18,0) | D19: =IFERROR(D18/$N$18,0) | E19: =IFERROR(E18/$N$18,0) | F19: =IFERROR(F18/$N$18,0) | G19: =IFERROR(G18/$N$18,0) | H19: =IFERROR(H18/$N$18,0) | I19: =IFERROR(I18/$N$18,0) | ... M19: =IFERROR(M18/$N$18,0) | N19: =SUM(B19:M19) | O19: その月が年間の何%か
A20: 売上実績 | B20: ='1月_売上顧客'!$L$4 | C20: ='2月_売上顧客'!$L$4 | D20: ='3月_売上顧客'!$L$4 | E20: ='4月_売上顧客'!$L$4 | F20: ='5月_売上顧客'!$L$4 | G20: ='6月_売上顧客'!$L$4 | H20: ='7月_売上顧客'!$L$4 | I20: ='8月_売上顧客'!$L$4 | J20: ='9月_売上顧客'!$L$4 | K20: ='10月_売上顧客'!$L$4 | L20: ='11月_売上顧客'!$L$4 | M20: ='12月_売上顧客'!$L$4 | N20: =SUM(B20:M20) | O20: 各月タブの合計売上
A21: 売上累計 | B21: =B20 | C21: =B21+C20 | D21: =C21+D20 | E21: =D21+E20 | F21: =E21+F20 | G21: =F21+G20 | H21: =G21+H20 | I21: =H21+I20 | J21: =I21+J20 | ... M21: =L21+M20 | N21: =M21 | O21: 実績の積み上げ
A22: 予算累計 | B22: =B18 | C22: =B22+C18 | D22: =C22+D18 | E22: =D22+E18 | F22: =E22+F18 | G22: =F22+G18 | H22: =G22+H18 | I22: =H22+I18 | J22: =I22+J18 | ... M22: =L22+M18 | N22: =M22 | O22: 計画の積み上げ
A23: ★対計画の差額（当月） | B23: =B20-B18 | C23: =C20-C18 | D23: =D20-D18 | E23: =E20-E18 | F23: =F20-F18 | G23: =G20-G18 | H23: =H20-H18 | I23: =I20-I18 | ... M23: =M20-M18 | N23: =SUM(B23:M23) | O23: 毎月いちばんに見る数字。マイナスなら赤
A24: ★累計の対計画の差額 | B24: =B21-B22 | C24: =C21-C22 | D24: =D21-D22 | E24: =E21-E22 | F24: =F21-F22 | G24: =G21-G22 | H24: =H21-H22 | I24: =I21-I22 | ... M24: =M21-M22 | N24: =M24 | O24: 年の着地を決める数字。マイナスなら赤
A25: 達成率（当月） | B25: =IFERROR(B20/B18,0) | C25: =IFERROR(C20/C18,0) | D25: =IFERROR(D20/D18,0) | E25: =IFERROR(E20/E18,0) | F25: =IFERROR(F20/F18,0) | G25: =IFERROR(G20/G18,0) | H25: =IFERROR(H20/H18,0) | I25: =IFERROR(I20/I18,0) | ... M25: =IFERROR(M20/M18,0) | N25: =IFERROR(AVERAGE(B25:M25),0)
A26: 達成率（累計） | B26: =IFERROR(B21/B22,0) | C26: =IFERROR(C21/C22,0) | D26: =IFERROR(D21/D22,0) | E26: =IFERROR(E21/E22,0) | F26: =IFERROR(F21/F22,0) | G26: =IFERROR(G21/G22,0) | H26: =IFERROR(H21/H22,0) | I26: =IFERROR(I21/I22,0) | ... M26: =IFERROR(M21/M22,0) | N26: =M26
A27: 件数 計画 | B27: 37 | C27: 32 | D27: 46 | E27: 57 | F27: 70 | G27: 82 | H27: 68 | I27: 42 | J27: 46 | K27: 60 | L27: 64 | M27: 45 | N27: =SUM(B27:M27)
A28: 件数 実績 | B28: ='1月_売上顧客'!$E$4 | C28: ='2月_売上顧客'!$E$4 | D28: ='3月_売上顧客'!$E$4 | E28: ='4月_売上顧客'!$E$4 | F28: ='5月_売上顧客'!$E$4 | G28: ='6月_売上顧客'!$E$4 | H28: ='7月_売上顧客'!$E$4 | I28: ='8月_売上顧客'!$E$4 | J28: ='9月_売上顧客'!$E$4 | K28: ='10月_売上顧客'!$E$4 | L28: ='11月_売上顧客'!$E$4 | M28: ='12月_売上顧客'!$E$4 | N28: =SUM(B28:M28)
A29: ④自社ネット新規 計画 | B29: 5 | C29: 5 | D29: 8 | E29: 10 | F29: 14 | G29: 17 | H29: 15 | I29: 10 | J29: 12 | K29: 16 | L29: 18 | M29: 13 | N29: =SUM(B29:M29) | O29: 年143件（中立）。HP/LP/SNS/GBP/公式LINE/アフィリ/LINE・SMS再販
A30: ★④自社ネット新規 実績 | B30: ='1月_売上顧客'!$R$4 | C30: ='2月_売上顧客'!$R$4 | D30: ='3月_売上顧客'!$R$4 | E30: ='4月_売上顧客'!$R$4 | F30: ='5月_売上顧客'!$R$4 | G30: ='6月_売上顧客'!$R$4 | H30: ='7月_売上顧客'!$R$4 | I30: ='8月_売上顧客'!$R$4 | J30: ='9月_売上顧客'!$R$4 | K30: ='10月_売上顧客'!$R$4 | L30: ='11月_売上顧客'!$R$4 | M30: ='12月_売上顧客'!$R$4 | N30: =SUM(B30:M30) | O30: 2027年の最重要KPI。これが動かないと他は後追い
A31: 平均単価 実績 | B31: ='1月_売上顧客'!$F$4 | C31: ='2月_売上顧客'!$F$4 | D31: ='3月_売上顧客'!$F$4 | E31: ='4月_売上顧客'!$F$4 | F31: ='5月_売上顧客'!$F$4 | G31: ='6月_売上顧客'!$F$4 | H31: ='7月_売上顧客'!$F$4 | I31: ='8月_売上顧客'!$F$4 | J31: ='9月_売上顧客'!$F$4 | K31: ='10月_売上顧客'!$F$4 | L31: ='11月_売上顧客'!$F$4 | M31: ='12月_売上顧客'!$F$4 | N31: =IFERROR(AVERAGE(B31:M31),0)
A32: エアコン台数 | B32: ='1月_支出成績'!$N$4 | C32: ='2月_支出成績'!$N$4 | D32: ='3月_支出成績'!$N$4 | E32: ='4月_支出成績'!$N$4 | F32: ='5月_支出成績'!$N$4 | G32: ='6月_支出成績'!$N$4 | H32: ='7月_支出成績'!$N$4 | I32: ='8月_支出成績'!$N$4 | J32: ='9月_支出成績'!$N$4 | K32: ='10月_支出成績'!$N$4 | L32: ='11月_支出成績'!$N$4 | M32: ='12月_支出成績'!$N$4 | N32: =SUM(B32:M32)
A33: 換気扇台数 | B33: ='1月_支出成績'!$N$5 | C33: ='2月_支出成績'!$N$5 | D33: ='3月_支出成績'!$N$5 | E33: ='4月_支出成績'!$N$5 | F33: ='5月_支出成績'!$N$5 | G33: ='6月_支出成績'!$N$5 | H33: ='7月_支出成績'!$N$5 | I33: ='8月_支出成績'!$N$5 | J33: ='9月_支出成績'!$N$5 | K33: ='10月_支出成績'!$N$5 | L33: ='11月_支出成績'!$N$5 | M33: ='12月_支出成績'!$N$5 | N33: =SUM(B33:M33)
A34: 浴室台数 | B34: ='1月_支出成績'!$N$6 | C34: ='2月_支出成績'!$N$6 | D34: ='3月_支出成績'!$N$6 | E34: ='4月_支出成績'!$N$6 | F34: ='5月_支出成績'!$N$6 | G34: ='6月_支出成績'!$N$6 | H34: ='7月_支出成績'!$N$6 | I34: ='8月_支出成績'!$N$6 | J34: ='9月_支出成績'!$N$6 | K34: ='10月_支出成績'!$N$6 | L34: ='11月_支出成績'!$N$6 | M34: ='12月_支出成績'!$N$6 | N34: =SUM(B34:M34)
A35: 資材費 | B35: ='1月_支出成績'!$N$7 | C35: ='2月_支出成績'!$N$7 | D35: ='3月_支出成績'!$N$7 | E35: ='4月_支出成績'!$N$7 | F35: ='5月_支出成績'!$N$7 | G35: ='6月_支出成績'!$N$7 | H35: ='7月_支出成績'!$N$7 | I35: ='8月_支出成績'!$N$7 | J35: ='9月_支出成績'!$N$7 | K35: ='10月_支出成績'!$N$7 | L35: ='11月_支出成績'!$N$7 | M35: ='12月_支出成績'!$N$7 | N35: =SUM(B35:M35)
A36: 外注費 | B36: ='1月_支出成績'!$N$8 | C36: ='2月_支出成績'!$N$8 | D36: ='3月_支出成績'!$N$8 | E36: ='4月_支出成績'!$N$8 | F36: ='5月_支出成績'!$N$8 | G36: ='6月_支出成績'!$N$8 | H36: ='7月_支出成績'!$N$8 | I36: ='8月_支出成績'!$N$8 | J36: ='9月_支出成績'!$N$8 | K36: ='10月_支出成績'!$N$8 | L36: ='11月_支出成績'!$N$8 | M36: ='12月_支出成績'!$N$8 | N36: =SUM(B36:M36) | O36: 協力業者3社へ回した分
A37: 現場人件費（原価） | B37: ='1月_支出成績'!$N$9 | C37: ='2月_支出成績'!$N$9 | D37: ='3月_支出成績'!$N$9 | E37: ='4月_支出成績'!$N$9 | F37: ='5月_支出成績'!$N$9 | G37: ='6月_支出成績'!$N$9 | H37: ='7月_支出成績'!$N$9 | I37: ='8月_支出成績'!$N$9 | J37: ='9月_支出成績'!$N$9 | K37: ='10月_支出成績'!$N$9 | L37: ='11月_支出成績'!$N$9 | M37: ='12月_支出成績'!$N$9 | N37: =SUM(B37:M37)
A38: 原価合計 | B38: ='1月_支出成績'!$N$10 | C38: ='2月_支出成績'!$N$10 | D38: ='3月_支出成績'!$N$10 | E38: ='4月_支出成績'!$N$10 | F38: ='5月_支出成績'!$N$10 | G38: ='6月_支出成績'!$N$10 | H38: ='7月_支出成績'!$N$10 | I38: ='8月_支出成績'!$N$10 | J38: ='9月_支出成績'!$N$10 | K38: ='10月_支出成績'!$N$10 | L38: ='11月_支出成績'!$N$10 | M38: ='12月_支出成績'!$N$10 | N38: =SUM(B38:M38)
A39: 売上総利益 | B39: ='1月_支出成績'!$N$11 | C39: ='2月_支出成績'!$N$11 | D39: ='3月_支出成績'!$N$11 | E39: ='4月_支出成績'!$N$11 | F39: ='5月_支出成績'!$N$11 | G39: ='6月_支出成績'!$N$11 | H39: ='7月_支出成績'!$N$11 | I39: ='8月_支出成績'!$N$11 | J39: ='9月_支出成績'!$N$11 | K39: ='10月_支出成績'!$N$11 | L39: ='11月_支出成績'!$N$11 | M39: ='12月_支出成績'!$N$11 | N39: =SUM(B39:M39)
A40: 販売管理費 | B40: ='1月_支出成績'!$N$21 | C40: ='2月_支出成績'!$N$21 | D40: ='3月_支出成績'!$N$21 | E40: ='4月_支出成績'!$N$21 | F40: ='5月_支出成績'!$N$21 | G40: ='6月_支出成績'!$N$21 | H40: ='7月_支出成績'!$N$21 | I40: ='8月_支出成績'!$N$21 | J40: ='9月_支出成績'!$N$21 | K40: ='10月_支出成績'!$N$21 | L40: ='11月_支出成績'!$N$21 | M40: ='12月_支出成績'!$N$21 | N40: =SUM(B40:M40) | O40: 固定給・ロイヤリティ込み
A41: 営業利益 | B41: ='1月_支出成績'!$N$22 | C41: ='2月_支出成績'!$N$22 | D41: ='3月_支出成績'!$N$22 | E41: ='4月_支出成績'!$N$22 | F41: ='5月_支出成績'!$N$22 | G41: ='6月_支出成績'!$N$22 | H41: ='7月_支出成績'!$N$22 | I41: ='8月_支出成績'!$N$22 | J41: ='9月_支出成績'!$N$22 | K41: ='10月_支出成績'!$N$22 | L41: ='11月_支出成績'!$N$22 | M41: ='12月_支出成績'!$N$22 | N41: =SUM(B41:M41)
A42: 融資返済 | B42: ='1月_支出成績'!$N$23 | C42: ='2月_支出成績'!$N$23 | D42: ='3月_支出成績'!$N$23 | E42: ='4月_支出成績'!$N$23 | F42: ='5月_支出成績'!$N$23 | G42: ='6月_支出成績'!$N$23 | H42: ='7月_支出成績'!$N$23 | I42: ='8月_支出成績'!$N$23 | J42: ='9月_支出成績'!$N$23 | K42: ='10月_支出成績'!$N$23 | L42: ='11月_支出成績'!$N$23 | M42: ='12月_支出成績'!$N$23 | N42: =SUM(B42:M42)
A43: 経常利益 | B43: ='1月_支出成績'!$N$24 | C43: ='2月_支出成績'!$N$24 | D43: ='3月_支出成績'!$N$24 | E43: ='4月_支出成績'!$N$24 | F43: ='5月_支出成績'!$N$24 | G43: ='6月_支出成績'!$N$24 | H43: ='7月_支出成績'!$N$24 | I43: ='8月_支出成績'!$N$24 | J43: ='9月_支出成績'!$N$24 | K43: ='10月_支出成績'!$N$24 | L43: ='11月_支出成績'!$N$24 | M43: ='12月_支出成績'!$N$24 | N43: =SUM(B43:M43)
A44: 経常利益 累計 | B44: =B43 | C44: =B44+C43 | D44: =C44+D43 | E44: =D44+E43 | F44: =E44+F43 | G44: =F44+G43 | H44: =G44+H43 | I44: =H44+I43 | J44: =I44+J43 | ... M44: =L44+M43 | N44: =M44
A45: 2026年 売上（手入力） | N45: =SUM(B45:M45) | O45: ★年末に2026年の確定値を貼ってください。ここだけ手入力です
A46: 前年比 | B46: =IFERROR(B20/B45,"") | C46: =IFERROR(C20/C45,"") | D46: =IFERROR(D20/D45,"") | E46: =IFERROR(E20/E45,"") | F46: =IFERROR(F20/F45,"") | G46: =IFERROR(G20/G45,"") | H46: =IFERROR(H20/H45,"") | I46: =IFERROR(I20/I45,"") | ... N46: =IFERROR(N20/N45,"") | O46: 2027 ÷ 2026
A48: ▼ ここから下はダッシュボード用の累計です（触らないでください）
A49: ④自社ネット新規 計画 累計 | B49: =B29 | C49: =B49+C29 | D49: =C49+D29 | E49: =D49+E29 | F49: =E49+F29 | G49: =F49+G29 | H49: =G49+H29 | I49: =H49+I29 | J49: =I49+J29 | ... M49: =L49+M29 | N49: =M49 | O49: ダッシュボード用
A50: ④自社ネット新規 実績 累計 | B50: =B30 | C50: =B50+C30 | D50: =C50+D30 | E50: =D50+E30 | F50: =E50+F30 | G50: =F50+G30 | H50: =G50+H30 | I50: =H50+I30 | J50: =I50+J30 | ... M50: =L50+M30 | N50: =M50 | O50: ダッシュボード用
A51: 経常利益 計画（月次） | B51: 231914 | C51: -6745 | D51: 303086 | E51: 570807 | F51: 892282 | G51: 1231143 | H51: 813684 | I51: 115573 | J51: 231903 | K51: 503051 | L51: 579935 | M51: 188439 | N51: =SUM(B51:M51) | O51: tools/plan2027.py の中立
A52: 経常利益 計画 累計 | B52: =B51 | C52: =B52+C51 | D52: =C52+D51 | E52: =D52+E51 | F52: =E52+F51 | G52: =F52+G51 | H52: =G52+H51 | I52: =H52+I51 | J52: =I52+J51 | ... M52: =L52+M51 | N52: =M52 | O52: ダッシュボード用
A53: 売上 計画（月次・再掲） | B53: =B18 | C53: =C18 | D53: =D18 | E53: =E18 | F53: =F18 | G53: =G18 | H53: =H18 | I53: =I18 | ... M53: =M18 | N53: =SUM(B53:M53) | O53: ダッシュボード用
A55: ▼ 自社／本舗（売上種類で見る）
A56: 自社（One Hitter）売上 | B56: ='1月_売上顧客'!$J$4 | C56: ='2月_売上顧客'!$J$4 | D56: ='3月_売上顧客'!$J$4 | E56: ='4月_売上顧客'!$J$4 | F56: ='5月_売上顧客'!$J$4 | G56: ='6月_売上顧客'!$J$4 | H56: ='7月_売上顧客'!$J$4 | I56: ='8月_売上顧客'!$J$4 | J56: ='9月_売上顧客'!$J$4 | K56: ='10月_売上顧客'!$J$4 | L56: ='11月_売上顧客'!$J$4 | M56: ='12月_売上顧客'!$J$4 | N56: =SUM(B56:M56) | O56: 2026年は1〜9月で +26%。伸びているのはこちら
A57: おそうじ本舗 売上 | B57: ='1月_売上顧客'!$K$4 | C57: ='2月_売上顧客'!$K$4 | D57: ='3月_売上顧客'!$K$4 | E57: ='4月_売上顧客'!$K$4 | F57: ='5月_売上顧客'!$K$4 | G57: ='6月_売上顧客'!$K$4 | H57: ='7月_売上顧客'!$K$4 | I57: ='8月_売上顧客'!$K$4 | J57: ='9月_売上顧客'!$K$4 | K57: ='10月_売上顧客'!$K$4 | L57: ='11月_売上顧客'!$K$4 | M57: ='12月_売上顧客'!$K$4 | N57: =SUM(B57:M57) | O57: 2026年は1〜9月で −27%。楽ラクーン・スケジュールマッチング・入札はここ
A58: 自社の比率 | B58: =IFERROR(B56/B20,"") | C58: =IFERROR(C56/C20,"") | D58: =IFERROR(D56/D20,"") | E58: =IFERROR(E56/E20,"") | F58: =IFERROR(F56/F20,"") | G58: =IFERROR(G56/G20,"") | H58: =IFERROR(H56/H20,"") | I58: =IFERROR(I56/I20,"") | ... N58: =IFERROR(N56/N20,"") | O58: 自社売上 ÷ 売上実績

Sheet ネット流入_週次
A1: ネット流入 週次（★2027年の最重要）
A2: 毎週金曜に埋める。CPAは自動計算。9,500円を超えたセルは赤くなります＝その月は広告を止める合図。
A3: 週あたりの目安 | D3: 5 | E3: 1 | F3: 2 | G3: 全件 | K3: 9500 | L3: SNS週5本・ブログ週1本・GBP週2本・クチコミは全件返信。CPA上限9,500円（docs/流入経路の分析.md §4） | N3: ▼ 月別ロールアップ（自動）
A4: 週 | B4: 週の開始日(月) | C4: 月 | D4: SNS投稿数 | E4: ブログ本数 | F4: GBP投稿数 | G4: クチコミ返信数 | H4: 予約フォーム到達数 | I4: 受注件数 | J4: 広告費 | K4: CPA(自動) | L4: 主な施策・気づき | N4: 月 | O4: 予約フォーム到達 | P4: 受注件数 | Q4: 広告費 | R4: CPA
A5: 1 | B5: 46391 | C5: =IFERROR(MONTH($B5),"") | K5: =IFERROR($J5/$I5,"") | N5: 1 | O5: =SUMIFS($H$5:$H$56,$C$5:$C$56,1) | P5: =SUMIFS($I$5:$I$56,$C$5:$C$56,1) | Q5: =SUMIFS($J$5:$J$56,$C$5:$C$56,1) | R5: =IFERROR($Q5/$P5,"")
A6: 2 | B6: 46398 | C6: =IFERROR(MONTH($B6),"") | K6: =IFERROR($J6/$I6,"") | N6: 2 | O6: =SUMIFS($H$5:$H$56,$C$5:$C$56,2) | P6: =SUMIFS($I$5:$I$56,$C$5:$C$56,2) | Q6: =SUMIFS($J$5:$J$56,$C$5:$C$56,2) | R6: =IFERROR($Q6/$P6,"")
A7: 3 | B7: 46405 | C7: =IFERROR(MONTH($B7),"") | K7: =IFERROR($J7/$I7,"") | N7: 3 | O7: =SUMIFS($H$5:$H$56,$C$5:$C$56,3) | P7: =SUMIFS($I$5:$I$56,$C$5:$C$56,3) | Q7: =SUMIFS($J$5:$J$56,$C$5:$C$56,3) | R7: =IFERROR($Q7/$P7,"")
A8: 4 | B8: 46412 | C8: =IFERROR(MONTH($B8),"") | K8: =IFERROR($J8/$I8,"") | N8: 4 | O8: =SUMIFS($H$5:$H$56,$C$5:$C$56,4) | P8: =SUMIFS($I$5:$I$56,$C$5:$C$56,4) | Q8: =SUMIFS($J$5:$J$56,$C$5:$C$56,4) | R8: =IFERROR($Q8/$P8,"")
A9: 5 | B9: 46419 | C9: =IFERROR(MONTH($B9),"") | K9: =IFERROR($J9/$I9,"") | N9: 5 | O9: =SUMIFS($H$5:$H$56,$C$5:$C$56,5) | P9: =SUMIFS($I$5:$I$56,$C$5:$C$56,5) | Q9: =SUMIFS($J$5:$J$56,$C$5:$C$56,5) | R9: =IFERROR($Q9/$P9,"")
A10: 6 | B10: 46426 | C10: =IFERROR(MONTH($B10),"") | K10: =IFERROR($J10/$I10,"") | N10: 6 | O10: =SUMIFS($H$5:$H$56,$C$5:$C$56,6) | P10: =SUMIFS($I$5:$I$56,$C$5:$C$56,6) | Q10: =SUMIFS($J$5:$J$56,$C$5:$C$56,6) | R10: =IFERROR($Q10/$P10,"")
A11: 7 | B11: 46433 | C11: =IFERROR(MONTH($B11),"") | K11: =IFERROR($J11/$I11,"") | N11: 7 | O11: =SUMIFS($H$5:$H$56,$C$5:$C$56,7) | P11: =SUMIFS($I$5:$I$56,$C$5:$C$56,7) | Q11: =SUMIFS($J$5:$J$56,$C$5:$C$56,7) | R11: =IFERROR($Q11/$P11,"")
A12: 8 | B12: 46440 | C12: =IFERROR(MONTH($B12),"") | K12: =IFERROR($J12/$I12,"") | N12: 8 | O12: =SUMIFS($H$5:$H$56,$C$5:$C$56,8) | P12: =SUMIFS($I$5:$I$56,$C$5:$C$56,8) | Q12: =SUMIFS($J$5:$J$56,$C$5:$C$56,8) | R12: =IFERROR($Q12/$P12,"")
A13: 9 | B13: 46447 | C13: =IFERROR(MONTH($B13),"") | K13: =IFERROR($J13/$I13,"") | N13: 9 | O13: =SUMIFS($H$5:$H$56,$C$5:$C$56,9) | P13: =SUMIFS($I$5:$I$56,$C$5:$C$56,9) | Q13: =SUMIFS($J$5:$J$56,$C$5:$C$56,9) | R13: =IFERROR($Q13/$P13,"")
A14: 10 | B14: 46454 | C14: =IFERROR(MONTH($B14),"") | K14: =IFERROR($J14/$I14,"") | N14: 10 | O14: =SUMIFS($H$5:$H$56,$C$5:$C$56,10) | P14: =SUMIFS($I$5:$I$56,$C$5:$C$56,10) | Q14: =SUMIFS($J$5:$J$56,$C$5:$C$56,10) | R14: =IFERROR($Q14/$P14,"")
A15: 11 | B15: 46461 | C15: =IFERROR(MONTH($B15),"") | K15: =IFERROR($J15/$I15,"") | N15: 11 | O15: =SUMIFS($H$5:$H$56,$C$5:$C$56,11) | P15: =SUMIFS($I$5:$I$56,$C$5:$C$56,11) | Q15: =SUMIFS($J$5:$J$56,$C$5:$C$56,11) | R15: =IFERROR($Q15/$P15,"")
A16: 12 | B16: 46468 | C16: =IFERROR(MONTH($B16),"") | K16: =IFERROR($J16/$I16,"") | N16: 12 | O16: =SUMIFS($H$5:$H$56,$C$5:$C$56,12) | P16: =SUMIFS($I$5:$I$56,$C$5:$C$56,12) | Q16: =SUMIFS($J$5:$J$56,$C$5:$C$56,12) | R16: =IFERROR($Q16/$P16,"")
A17: 13 | B17: 46475 | C17: =IFERROR(MONTH($B17),"") | K17: =IFERROR($J17/$I17,"")
A18: 14 | B18: 46482 | C18: =IFERROR(MONTH($B18),"") | K18: =IFERROR($J18/$I18,"")
A19: 15 | B19: 46489 | C19: =IFERROR(MONTH($B19),"") | K19: =IFERROR($J19/$I19,"")
A20: 16 | B20: 46496 | C20: =IFERROR(MONTH($B20),"") | K20: =IFERROR($J20/$I20,"")
A21: 17 | B21: 46503 | C21: =IFERROR(MONTH($B21),"") | K21: =IFERROR($J21/$I21,"")
A22: 18 | B22: 46510 | C22: =IFERROR(MONTH($B22),"") | K22: =IFERROR($J22/$I22,"")
A23: 19 | B23: 46517 | C23: =IFERROR(MONTH($B23),"") | K23: =IFERROR($J23/$I23,"")
A24: 20 | B24: 46524 | C24: =IFERROR(MONTH($B24),"") | K24: =IFERROR($J24/$I24,"")
A25: 21 | B25: 46531 | C25: =IFERROR(MONTH($B25),"") | K25: =IFERROR($J25/$I25,"")
A26: 22 | B26: 46538 | C26: =IFERROR(MONTH($B26),"") | K26: =IFERROR($J26/$I26,"")
A27: 23 | B27: 46545 | C27: =IFERROR(MONTH($B27),"") | K27: =IFERROR($J27/$I27,"")
A28: 24 | B28: 46552 | C28: =IFERROR(MONTH($B28),"") | K28: =IFERROR($J28/$I28,"")
... A56: 52 | B56: 46748 | C56: =IFERROR(MONTH($B56),"") | K56: =IFERROR($J56/$I56,"")

Sheet 広告_段管理
A1: 広告 段管理 — 小さく試して、成果が出たら加速する
A2: 年額を先に決めない。段と、次の段へ上がる条件を先に決める（docs/2027-数値目標.md §5）。
K3: ▼ 段の定義とルール
A4: 月 | B4: 段 | C4: 予算(円) | D4: 実績(円) | E4: 獲得件数 | F4: CPA(自動) | G4: 判定 | H4: 判定の目安(自動) | I4: メモ | K4: 段／ルール | L4: 金額 | M4: 内容
A5: 1 | B5: 段0（テスト） | C5: 50000 | F5: =IFERROR($D5/$E5,"") | G5: 未判定 | H5: =IF($E5=0,"データなし",IF($F5>9500,"止める（CPA超過）","この月はクリア")) | K5: 段0（テスト） | L5: 月5万 | M5: 1〜2月に実施。ここは無条件で出す
A6: 2 | B6: 段0（テスト） | C6: 50000 | F6: =IFERROR($D6/$E6,"") | G6: 未判定 | H6: =IF($E6=0,"データなし",IF($F6>9500,"止める（CPA超過）","この月はクリア")) | K6: 段1 | L6: 月6〜10万 | M6: 段0でCPA 9,500円以下なら上がる
A7: 3 | B7: 段1 | C7: 60000 | F7: =IFERROR($D7/$E7,"") | G7: 未判定 | H7: =IF($E7=0,"データなし",IF($F7>9500,"止める（CPA超過）","この月はクリア")) | K7: 段2（繁忙期） | L7: 月12〜15万 | M7: 段1を2か月連続クリア。5〜7月に当てる
A8: 4 | B8: 段1 | C8: 60000 | F8: =IFERROR($D8/$E8,"") | G8: 未判定 | H8: =IF($E8=0,"データなし",IF($F8>9500,"止める（CPA超過）","この月はクリア")) | K8: 段3（年末） | L8: 月7〜10万 | M8: 段2をクリア。10〜11月に当てる
A9: 5 | B9: 段2（繁忙期） | C9: 120000 | F9: =IFERROR($D9/$E9,"") | G9: 未判定 | H9: =IF($E9=0,"データなし",IF($F9>9500,"止める（CPA超過）","この月はクリア"))
A10: 6 | B10: 段2（繁忙期） | C10: 120000 | F10: =IFERROR($D10/$E10,"") | G10: 未判定 | H10: =IF($E10=0,"データなし",IF($F10>9500,"止める（CPA超過）","この月はクリア")) | K10: 上限 | L10: CPA 9,500円 | M10: マッチングPFに払っている実質手数料と同額
A11: 7 | B11: 段2（繁忙期） | C11: 120000 | F11: =IFERROR($D11/$E11,"") | G11: 未判定 | H11: =IF($E11=0,"データなし",IF($F11>9500,"止める（CPA超過）","この月はクリア")) | K11: 止める条件 | M11: 月次でCPAが9,500円を超えたら、その月で止める。次の段へ上がらない
A12: 8 | B12: 段1 | C12: 30000 | F12: =IFERROR($D12/$E12,"") | G12: 未判定 | H12: =IF($E12=0,"データなし",IF($F12>9500,"止める（CPA超過）","この月はクリア")) | K12: 上げる条件 | M12: 2か月連続でCPA 9,500円以下、かつ受注が実際に付いている
A13: 9 | B13: 段1 | C13: 30000 | F13: =IFERROR($D13/$E13,"") | G13: 未判定 | H13: =IF($E13=0,"データなし",IF($F13>9500,"止める（CPA超過）","この月はクリア")) | K13: 使わない | M13: Facebook広告は再開しない（CPC95.39円で撃沈済み）。チラシ単独配布もしない
A14: 10 | B14: 段3（年末） | C14: 70000 | F14: =IFERROR($D14/$E14,"") | G14: 未判定 | H14: =IF($E14=0,"データなし",IF($F14>9500,"止める（CPA超過）","この月はクリア")) | K14: 出さない | M14: レントラックスとの関係上、指名検索への出稿はしない
A15: 11 | B15: 段3（年末） | C15: 70000 | F15: =IFERROR($D15/$E15,"") | G15: 未判定 | H15: =IF($E15=0,"データなし",IF($F15>9500,"止める（CPA超過）","この月はクリア"))
A16: 12 | B16: 段1 | C16: 20000 | F16: =IFERROR($D16/$E16,"") | G16: 未判定 | H16: =IF($E16=0,"データなし",IF($F16>9500,"止める（CPA超過）","この月はクリア"))
A17: 年計 | C17: =SUM(C5:C16) | D17: =SUM(D5:D16) | E17: =SUM(E5:E16) | F17: =IFERROR(D17/E17,"")

Sheet 提携先_パイプライン
A1: 提携先パイプライン — アクティブ10社 → 15社（中立）
A2: 平均単価100,128円（大型案件込み）／大型を除いた実力 49,130円／秋（9〜12月）の実単価 56,931円。LTV186,272円・リピート率45%。1社増えると年50万円規模で効きます。
A3: 新規の成約 社数 | B3: =COUNTIF($G$5:$G$104,"成約") | C3: 目標 | D3: 5 | E3: アクティブ10社（2026-09-14 時点）を 保守12社／中立15社／攻め18社 へ。目標欄は新規の成約社数＝保守2社／中立5社／攻め8社。入口は施設ターゲットリスト291件（BREXAのような施設・法人の天カセ案件が最も現実的）。※不動産管理会社の空室清掃はやらない（オーナー決定 2026-09-14）
A4: 先方名 | B4: 業種 | C4: 担当者 | D4: 初回接触日 | E4: 最終接触日 | F4: 接触回数(累計) | G4: ステージ | H4: 紹介件数(累計) | I4: 売上(累計) | J4: 次アクション | K4: 次アクション期日 | L4: 担当 | M4: メモ

Sheet 協力業者_管理
A1: 協力業者 管理 — 3社（1〜2月に契約・3月から稼働）
A2: 「安く回す先」ではなく「ピークを取りこぼさないための保険」。品質が崩れると入口が全部止まります。
A3: 契約済み 社数 | B3: =COUNTIFS($B$5:$B$24,"<>未契約",$A$5:$A$24,"<>") | C3: 目標 | D3: 3 | E3: 年間 外注件数 目標 | F3: 100 | G3: 支払条件は未決定（案A歩合65%／案Bメニュー別固定単価／案C日当22,000円）。12月中に方針を決める（docs/2027-数値目標.md §6）
A4: 社名 | B4: 契約形態 | C4: 条件（%・単価・日当） | D4: 対応エリア | E4: 契約日 | F4: 今年回した件数 | G4: 支払額(累計) | H4: クレーム件数 | I4: 写真提出率 | J4: 品質 | K4: メモ
A27: 【必ず守ること】
A28: ・協力業者の案件でも、お客様に届くもの（連絡・名乗り）は台帳の「最新の施工の名義」と機械で照合してから出す
A29: （tools/derive-soushin-keitou.py の meigi_hyou()。2026-09-11に名義取り違えの事故あり）
A30: ・施工チェックリストと写真報告を必須にする。契約書に品質条項を入れる
A31: ・★5.0（24件）と満足度98.6%が崩れると、入口が全部止まります

Sheet Web予約受信
A1: Web予約 受信ログ（予約フォーム・LP）
A2: 受信したら当日中に連絡。受注になったら月次タブへ転記して「台帳へ転記済み」をTRUEに。
A3: 受信件数 | B3: =COUNTA($A$5:$A$504) | C3: 受注件数 | D3: =COUNTIF($B$5:$B$504,"受注") | E3: 受注率 | F3: =IFERROR(COUNTIF($B$5:$B$504,"受注")/COUNTA($A$5:$A$504),0) | G3: 未対応 | H3: =COUNTIF($B$5:$B$504,"未対応")
A4: 受信日時 | B4: 状態 | C4: お名前 | D4: 連絡先 | E4: ご希望日 | F4: ご希望の内容 | G4: 流入元(?src=) | H4: 台帳へ転記済み | I4: 対応メモ
A506: ※ 個人情報が入る表です。共有範囲を広げないこと。お客様に送るURLは独自ドメインから（docs/事故報告-2026-09-12-セーフブラウジング.md）

Sheet 顧客管理台帳
A1: 顧客管理台帳（2027年版・空の器）
A2: 2026年からの実データ移行は年末にオーナーが行います。ヘッダーは15行目、データは16行目から（2026年版と同じ）。
A4: ▼ ダッシュボード（自動）
A5: 顧客数 | B5: =COUNTA($A$16:$A$2015) | D5: 2026年実績：957名・平均LTV 54,650円・リピート率25.0%。2027年目標 リピート率30%（中立）
A6: 2回以上ご利用 | B6: =COUNTIF($S$16:$S$2015,">=2")
A7: リピート率 | B7: =IFERROR(COUNTIF($S$16:$S$2015,">=2")/COUNTA($A$16:$A$2015),0) | D7: ★お客様に届くもの（SMS・LINE・電話）は、この台帳の「最終施工の名義」と機械照合してから作ること
A8: 総受注額 | B8: =SUM($T$16:$T$2015) | D8: tools/derive-soushin-keitou.py の meigi_hyou()。列の値を信じないこと（2026-09-11 名義取り違え事故）
A9: 平均LTV | B9: =IFERROR(SUM($T$16:$T$2015)/COUNTA($A$16:$A$2015),0) | D9: ★楽ラクーン経由はフォロー連絡ができません。送信系統＝連絡不可 にしてリストから恒久的に外します
A10: 自社名義 | B10: =COUNTIF($B$16:$B$2015,"自社") | D10: ★紹介者（法人）と実際のご利用者（個人）が別の案件があります。氏名欄・TEL欄に押し込まないこと
A11: 本舗名義 | B11: =COUNTIF($B$16:$B$2015,"本舗")
A12: 連絡不可（楽ラクーン等） | B12: =COUNTIF($C$16:$C$2015,"連絡不可")
A15: 顧客ID | B15: 名義 | C15: 送信系統 | D15: 氏名 | E15: フリガナ | F15: 法人/個人 | G15: 紹介者（法人名など） | H15: TEL1 | I15: TEL2 | J15: 郵便番号 | K15: 都県 | L15: 住所 | M15: メール | N15: 公式LINE | O15: 初回施工日 | P15: 初回の入口 | Q15: 最終施工日 | R15: 最終施工の名義 | S15: 施工回数 | T15: 総受注額 | U15: 平均単価 | V15: 主な流入経路 | W15: 実施済みメニュー（全文） | X15: エアコン | Y15: 換気扇 | Z15: 浴室 | AA15: 洗濯機 | AB15: トイレ/洗面 | AC15: 次回案内予定月 | AD15: 連絡可否 | AE15: 満足度/クチコミ | AF15: 備考

Sheet 再販リスト
A1: 再販リスト — 案内時期が来た方を抽出する器
A2: 顧客管理台帳から貼り付けて使います。次回案内月は EDATE（最終施工日, サイクル月数）で自動計算。
P3: ▼ 推奨サイクル
A4: 顧客ID | B4: 名義 | C4: 送信系統 | D4: 氏名 | E4: TEL | F4: 最終施工日 | G4: 実施メニュー | H4: サイクル(月) | I4: 次回案内月(自動) | J4: 案内状況 | K4: 案内日 | L4: 手段 | M4: 結果 | N4: メモ | P4: メニュー | Q4: サイクル(月) | R4: 案内の時期
I5: =IFERROR(EDATE($F5,$H5),"") | P5: エアコン(ノーマル/ロボ) | Q5: 12 | R5: 3〜4月・9〜10月に案内
I6: =IFERROR(EDATE($F6,$H6),"") | P6: 浴室 | Q6: 12 | R6: 施工の11か月後
I7: =IFERROR(EDATE($F7,$H7),"") | P7: 換気扇（レンジフード） | Q7: 12 | R7: 11〜12月（年末）
I8: =IFERROR(EDATE($F8,$H8),"") | P8: 洗濯機 | Q8: 12 | R8: 施工の11か月後
I9: =IFERROR(EDATE($F9,$H9),"") | P9: トイレ/洗面 | Q9: 12 | R9: 他メニューと同時提案
I10: =IFERROR(EDATE($F10,$H10),"") | P10: 追焚配管 | Q10: 24 | R10: 浴室と同時提案
I11: =IFERROR(EDATE($F11,$H11),"") | P11: おそうじ定期便 | Q11: 1 | R11: 毎月
I12: =IFERROR(EDATE($F12,$H12),"") | P12: 定期清掃（法人） | Q12: 1 | R12: 契約による
I13: =IFERROR(EDATE($F13,$H13),"")
I14: =IFERROR(EDATE($F14,$H14),"")
I15: =IFERROR(EDATE($F15,$H15),"") | P15: 【送る前に必ず】
I16: =IFERROR(EDATE($F16,$H16),"") | P16: ・楽ラクーン経由は連絡不可。送信系統で外す
I17: =IFERROR(EDATE($F17,$H17),"") | P17: ・スケジュールマッチング／入札案件は「本舗の番号」から
I18: =IFERROR(EDATE($F18,$H18),"") | P18: ・名乗り（ワンヒッター／おそうじ本舗）は台帳の最終施工の名義と機械照合してから
I19: =IFERROR(EDATE($F19,$H19),"") | P19: ・実施メニュー列だけで「未購入」を判定しない。備考の全文キーワード照合を併用
I20: =IFERROR(EDATE($F20,$H20),"") | P20: （2026年分だけで21行・14名が該当。既に施工済みのお客様へ売り込むことになる）
I21: =IFERROR(EDATE($F21,$H21),"")
I22: =IFERROR(EDATE($F22,$H22),"")
I23: =IFERROR(EDATE($F23,$H23),"")
I24: =IFERROR(EDATE($F24,$H24),"")
I25: =IFERROR(EDATE($F25,$H25),"")
I26: =IFERROR(EDATE($F26,$H26),"")
I27: =IFERROR(EDATE($F27,$H27),"")
I28: =IFERROR(EDATE($F28,$H28),"")
I29: =IFERROR(EDATE($F29,$H29),"")
I30: =IFERROR(EDATE($F30,$H30),"")
I31: =IFERROR(EDATE($F31,$H31),"")
I32: =IFERROR(EDATE($F32,$H32),"")
... I1004: =IFERROR(EDATE($F1004,$H1004),"")

Sheet 分析_件数単価流入
A1: 分析：月別の件数・単価と、流入経路別の内訳
A2: すべて月次タブを SUMIFS / COUNTIFS で参照しています。手入力するところはありません。
A4: 項目 | B4: 1月 | C4: 2月 | D4: 3月 | E4: 4月 | F4: 5月 | G4: 6月 | H4: 7月 | I4: 8月 | J4: 9月 | K4: 10月 | L4: 11月 | M4: 12月 | N4: 年計
A5: 件数 | B5: ='1月_売上顧客'!$E$4 | C5: ='2月_売上顧客'!$E$4 | D5: ='3月_売上顧客'!$E$4 | E5: ='4月_売上顧客'!$E$4 | F5: ='5月_売上顧客'!$E$4 | G5: ='6月_売上顧客'!$E$4 | H5: ='7月_売上顧客'!$E$4 | I5: ='8月_売上顧客'!$E$4 | J5: ='9月_売上顧客'!$E$4 | K5: ='10月_売上顧客'!$E$4 | L5: ='11月_売上顧客'!$E$4 | M5: ='12月_売上顧客'!$E$4 | N5: =SUM(B5:M5)
A6: 売上 | B6: ='1月_売上顧客'!$L$4 | C6: ='2月_売上顧客'!$L$4 | D6: ='3月_売上顧客'!$L$4 | E6: ='4月_売上顧客'!$L$4 | F6: ='5月_売上顧客'!$L$4 | G6: ='6月_売上顧客'!$L$4 | H6: ='7月_売上顧客'!$L$4 | I6: ='8月_売上顧客'!$L$4 | J6: ='9月_売上顧客'!$L$4 | K6: ='10月_売上顧客'!$L$4 | L6: ='11月_売上顧客'!$L$4 | M6: ='12月_売上顧客'!$L$4 | N6: =SUM(B6:M6)
A7: 平均単価 | B7: ='1月_売上顧客'!$F$4 | C7: ='2月_売上顧客'!$F$4 | D7: ='3月_売上顧客'!$F$4 | E7: ='4月_売上顧客'!$F$4 | F7: ='5月_売上顧客'!$F$4 | G7: ='6月_売上顧客'!$F$4 | H7: ='7月_売上顧客'!$F$4 | I7: ='8月_売上顧客'!$F$4 | J7: ='9月_売上顧客'!$F$4 | K7: ='10月_売上顧客'!$F$4 | L7: ='11月_売上顧客'!$F$4 | M7: ='12月_売上顧客'!$F$4 | N7: =IFERROR(AVERAGE(B7:M7),0)
A8: 自社件数 | B8: ='1月_売上顧客'!$B$4 | C8: ='2月_売上顧客'!$B$4 | D8: ='3月_売上顧客'!$B$4 | E8: ='4月_売上顧客'!$B$4 | F8: ='5月_売上顧客'!$B$4 | G8: ='6月_売上顧客'!$B$4 | H8: ='7月_売上顧客'!$B$4 | I8: ='8月_売上顧客'!$B$4 | J8: ='9月_売上顧客'!$B$4 | K8: ='10月_売上顧客'!$B$4 | L8: ='11月_売上顧客'!$B$4 | M8: ='12月_売上顧客'!$B$4 | N8: =SUM(B8:M8)
A9: 本舗件数 | B9: ='1月_売上顧客'!$D$4 | C9: ='2月_売上顧客'!$D$4 | D9: ='3月_売上顧客'!$D$4 | E9: ='4月_売上顧客'!$D$4 | F9: ='5月_売上顧客'!$D$4 | G9: ='6月_売上顧客'!$D$4 | H9: ='7月_売上顧客'!$D$4 | I9: ='8月_売上顧客'!$D$4 | J9: ='9月_売上顧客'!$D$4 | K9: ='10月_売上顧客'!$D$4 | L9: ='11月_売上顧客'!$D$4 | M9: ='12月_売上顧客'!$D$4 | N9: =SUM(B9:M9)
A10: 自社単価 | B10: ='1月_売上顧客'!$H$4 | C10: ='2月_売上顧客'!$H$4 | D10: ='3月_売上顧客'!$H$4 | E10: ='4月_売上顧客'!$H$4 | F10: ='5月_売上顧客'!$H$4 | G10: ='6月_売上顧客'!$H$4 | H10: ='7月_売上顧客'!$H$4 | I10: ='8月_売上顧客'!$H$4 | J10: ='9月_売上顧客'!$H$4 | K10: ='10月_売上顧客'!$H$4 | L10: ='11月_売上顧客'!$H$4 | M10: ='12月_売上顧客'!$H$4 | N10: =IFERROR(AVERAGE(B10:M10),0)
A11: 本舗単価 | B11: ='1月_売上顧客'!$I$4 | C11: ='2月_売上顧客'!$I$4 | D11: ='3月_売上顧客'!$I$4 | E11: ='4月_売上顧客'!$I$4 | F11: ='5月_売上顧客'!$I$4 | G11: ='6月_売上顧客'!$I$4 | H11: ='7月_売上顧客'!$I$4 | I11: ='8月_売上顧客'!$I$4 | J11: ='9月_売上顧客'!$I$4 | K11: ='10月_売上顧客'!$I$4 | L11: ='11月_売上顧客'!$I$4 | M11: ='12月_売上顧客'!$I$4 | N11: =IFERROR(AVERAGE(B11:M11),0)
A12: ④自社ネット新規 件数 | B12: ='1月_売上顧客'!$R$4 | C12: ='2月_売上顧客'!$R$4 | D12: ='3月_売上顧客'!$R$4 | E12: ='4月_売上顧客'!$R$4 | F12: ='5月_売上顧客'!$R$4 | G12: ='6月_売上顧客'!$R$4 | H12: ='7月_売上顧客'!$R$4 | I12: ='8月_売上顧客'!$R$4 | J12: ='9月_売上顧客'!$R$4 | K12: ='10月_売上顧客'!$R$4 | L12: ='11月_売上顧客'!$R$4 | M12: ='12月_売上顧客'!$R$4 | N12: =SUM(B12:M12)
A13: ④自社ネット新規 売上 | B13: ='1月_売上顧客'!$S$4 | C13: ='2月_売上顧客'!$S$4 | D13: ='3月_売上顧客'!$S$4 | E13: ='4月_売上顧客'!$S$4 | F13: ='5月_売上顧客'!$S$4 | G13: ='6月_売上顧客'!$S$4 | H13: ='7月_売上顧客'!$S$4 | I13: ='8月_売上顧客'!$S$4 | J13: ='9月_売上顧客'!$S$4 | K13: ='10月_売上顧客'!$S$4 | L13: ='11月_売上顧客'!$S$4 | M13: ='12月_売上顧客'!$S$4 | N13: =SUM(B13:M13)
A16: ▼ 流入経路別 件数
A17: 流入経路 | B17: 1月 | C17: 2月 | D17: 3月 | E17: 4月 | F17: 5月 | G17: 6月 | H17: 7月 | I17: 8月 | J17: 9月 | K17: 10月 | L17: 11月 | M17: 12月 | N17: 年計
A18: リピート | B18: =COUNTIFS('1月_売上顧客'!$E$5:$E$504,$A18) | C18: =COUNTIFS('2月_売上顧客'!$E$5:$E$504,$A18) | D18: =COUNTIFS('3月_売上顧客'!$E$5:$E$504,$A18) | E18: =COUNTIFS('4月_売上顧客'!$E$5:$E$504,$A18) | F18: =COUNTIFS('5月_売上顧客'!$E$5:$E$504,$A18) | G18: =COUNTIFS('6月_売上顧客'!$E$5:$E$504,$A18) | H18: =COUNTIFS('7月_売上顧客'!$E$5:$E$504,$A18) | I18: =COUNTIFS('8月_売上顧客'!$E$5:$E$504,$A18) | J18: =COUNTIFS('9月_売上顧客'!$E$5:$E$504,$A18) | K18: =COUNTIFS('10月_売上顧客'!$E$5:$E$504,$A18) | L18: =COUNTIFS('11月_売上顧客'!$E$5:$E$504,$A18) | M18: =COUNTIFS('12月_売上顧客'!$E$5:$E$504,$A18) | N18: =SUM(B18:M18)
A19: 早期予約 | B19: =COUNTIFS('1月_売上顧客'!$E$5:$E$504,$A19) | C19: =COUNTIFS('2月_売上顧客'!$E$5:$E$504,$A19) | D19: =COUNTIFS('3月_売上顧客'!$E$5:$E$504,$A19) | E19: =COUNTIFS('4月_売上顧客'!$E$5:$E$504,$A19) | F19: =COUNTIFS('5月_売上顧客'!$E$5:$E$504,$A19) | G19: =COUNTIFS('6月_売上顧客'!$E$5:$E$504,$A19) | H19: =COUNTIFS('7月_売上顧客'!$E$5:$E$504,$A19) | I19: =COUNTIFS('8月_売上顧客'!$E$5:$E$504,$A19) | J19: =COUNTIFS('9月_売上顧客'!$E$5:$E$504,$A19) | K19: =COUNTIFS('10月_売上顧客'!$E$5:$E$504,$A19) | L19: =COUNTIFS('11月_売上顧客'!$E$5:$E$504,$A19) | M19: =COUNTIFS('12月_売上顧客'!$E$5:$E$504,$A19) | N19: =SUM(B19:M19)
A20: 楽ラクーン | B20: =COUNTIFS('1月_売上顧客'!$E$5:$E$504,$A20) | C20: =COUNTIFS('2月_売上顧客'!$E$5:$E$504,$A20) | D20: =COUNTIFS('3月_売上顧客'!$E$5:$E$504,$A20) | E20: =COUNTIFS('4月_売上顧客'!$E$5:$E$504,$A20) | F20: =COUNTIFS('5月_売上顧客'!$E$5:$E$504,$A20) | G20: =COUNTIFS('6月_売上顧客'!$E$5:$E$504,$A20) | H20: =COUNTIFS('7月_売上顧客'!$E$5:$E$504,$A20) | I20: =COUNTIFS('8月_売上顧客'!$E$5:$E$504,$A20) | J20: =COUNTIFS('9月_売上顧客'!$E$5:$E$504,$A20) | K20: =COUNTIFS('10月_売上顧客'!$E$5:$E$504,$A20) | L20: =COUNTIFS('11月_売上顧客'!$E$5:$E$504,$A20) | M20: =COUNTIFS('12月_売上顧客'!$E$5:$E$504,$A20) | N20: =SUM(B20:M20)
A21: 業務提携 | B21: =COUNTIFS('1月_売上顧客'!$E$5:$E$504,$A21) | C21: =COUNTIFS('2月_売上顧客'!$E$5:$E$504,$A21) | D21: =COUNTIFS('3月_売上顧客'!$E$5:$E$504,$A21) | E21: =COUNTIFS('4月_売上顧客'!$E$5:$E$504,$A21) | F21: =COUNTIFS('5月_売上顧客'!$E$5:$E$504,$A21) | G21: =COUNTIFS('6月_売上顧客'!$E$5:$E$504,$A21) | H21: =COUNTIFS('7月_売上顧客'!$E$5:$E$504,$A21) | I21: =COUNTIFS('8月_売上顧客'!$E$5:$E$504,$A21) | J21: =COUNTIFS('9月_売上顧客'!$E$5:$E$504,$A21) | K21: =COUNTIFS('10月_売上顧客'!$E$5:$E$504,$A21) | L21: =COUNTIFS('11月_売上顧客'!$E$5:$E$504,$A21) | M21: =COUNTIFS('12月_売上顧客'!$E$5:$E$504,$A21) | N21: =SUM(B21:M21)
A22: スケジュールマッチング | B22: =COUNTIFS('1月_売上顧客'!$E$5:$E$504,$A22) | C22: =COUNTIFS('2月_売上顧客'!$E$5:$E$504,$A22) | D22: =COUNTIFS('3月_売上顧客'!$E$5:$E$504,$A22) | E22: =COUNTIFS('4月_売上顧客'!$E$5:$E$504,$A22) | F22: =COUNTIFS('5月_売上顧客'!$E$5:$E$504,$A22) | G22: =COUNTIFS('6月_売上顧客'!$E$5:$E$504,$A22) | H22: =COUNTIFS('7月_売上顧客'!$E$5:$E$504,$A22) | I22: =COUNTIFS('8月_売上顧客'!$E$5:$E$504,$A22) | J22: =COUNTIFS('9月_売上顧客'!$E$5:$E$504,$A22) | K22: =COUNTIFS('10月_売上顧客'!$E$5:$E$504,$A22) | L22: =COUNTIFS('11月_売上顧客'!$E$5:$E$504,$A22) | M22: =COUNTIFS('12月_売上顧客'!$E$5:$E$504,$A22) | N22: =SUM(B22:M22)
A23: おそうじ定期便 | B23: =COUNTIFS('1月_売上顧客'!$E$5:$E$504,$A23) | C23: =COUNTIFS('2月_売上顧客'!$E$5:$E$504,$A23) | D23: =COUNTIFS('3月_売上顧客'!$E$5:$E$504,$A23) | E23: =COUNTIFS('4月_売上顧客'!$E$5:$E$504,$A23) | F23: =COUNTIFS('5月_売上顧客'!$E$5:$E$504,$A23) | G23: =COUNTIFS('6月_売上顧客'!$E$5:$E$504,$A23) | H23: =COUNTIFS('7月_売上顧客'!$E$5:$E$504,$A23) | I23: =COUNTIFS('8月_売上顧客'!$E$5:$E$504,$A23) | J23: =COUNTIFS('9月_売上顧客'!$E$5:$E$504,$A23) | K23: =COUNTIFS('10月_売上顧客'!$E$5:$E$504,$A23) | L23: =COUNTIFS('11月_売上顧客'!$E$5:$E$504,$A23) | M23: =COUNTIFS('12月_売上顧客'!$E$5:$E$504,$A23) | N23: =SUM(B23:M23)
A24: 紹介 | B24: =COUNTIFS('1月_売上顧客'!$E$5:$E$504,$A24) | C24: =COUNTIFS('2月_売上顧客'!$E$5:$E$504,$A24) | D24: =COUNTIFS('3月_売上顧客'!$E$5:$E$504,$A24) | E24: =COUNTIFS('4月_売上顧客'!$E$5:$E$504,$A24) | F24: =COUNTIFS('5月_売上顧客'!$E$5:$E$504,$A24) | G24: =COUNTIFS('6月_売上顧客'!$E$5:$E$504,$A24) | H24: =COUNTIFS('7月_売上顧客'!$E$5:$E$504,$A24) | I24: =COUNTIFS('8月_売上顧客'!$E$5:$E$504,$A24) | J24: =COUNTIFS('9月_売上顧客'!$E$5:$E$504,$A24) | K24: =COUNTIFS('10月_売上顧客'!$E$5:$E$504,$A24) | L24: =COUNTIFS('11月_売上顧客'!$E$5:$E$504,$A24) | M24: =COUNTIFS('12月_売上顧客'!$E$5:$E$504,$A24) | N24: =SUM(B24:M24)
A25: 営業 | B25: =COUNTIFS('1月_売上顧客'!$E$5:$E$504,$A25) | C25: =COUNTIFS('2月_売上顧客'!$E$5:$E$504,$A25) | D25: =COUNTIFS('3月_売上顧客'!$E$5:$E$504,$A25) | E25: =COUNTIFS('4月_売上顧客'!$E$5:$E$504,$A25) | F25: =COUNTIFS('5月_売上顧客'!$E$5:$E$504,$A25) | G25: =COUNTIFS('6月_売上顧客'!$E$5:$E$504,$A25) | H25: =COUNTIFS('7月_売上顧客'!$E$5:$E$504,$A25) | I25: =COUNTIFS('8月_売上顧客'!$E$5:$E$504,$A25) | J25: =COUNTIFS('9月_売上顧客'!$E$5:$E$504,$A25) | K25: =COUNTIFS('10月_売上顧客'!$E$5:$E$504,$A25) | L25: =COUNTIFS('11月_売上顧客'!$E$5:$E$504,$A25) | M25: =COUNTIFS('12月_売上顧客'!$E$5:$E$504,$A25) | N25: =SUM(B25:M25)
A26: チラシ(OH) | B26: =COUNTIFS('1月_売上顧客'!$E$5:$E$504,$A26) | C26: =COUNTIFS('2月_売上顧客'!$E$5:$E$504,$A26) | D26: =COUNTIFS('3月_売上顧客'!$E$5:$E$504,$A26) | E26: =COUNTIFS('4月_売上顧客'!$E$5:$E$504,$A26) | F26: =COUNTIFS('5月_売上顧客'!$E$5:$E$504,$A26) | G26: =COUNTIFS('6月_売上顧客'!$E$5:$E$504,$A26) | H26: =COUNTIFS('7月_売上顧客'!$E$5:$E$504,$A26) | I26: =COUNTIFS('8月_売上顧客'!$E$5:$E$504,$A26) | J26: =COUNTIFS('9月_売上顧客'!$E$5:$E$504,$A26) | K26: =COUNTIFS('10月_売上顧客'!$E$5:$E$504,$A26) | L26: =COUNTIFS('11月_売上顧客'!$E$5:$E$504,$A26) | M26: =COUNTIFS('12月_売上顧客'!$E$5:$E$504,$A26) | N26: =SUM(B26:M26)
A27: HP | B27: =COUNTIFS('1月_売上顧客'!$E$5:$E$504,$A27) | C27: =COUNTIFS('2月_売上顧客'!$E$5:$E$504,$A27) | D27: =COUNTIFS('3月_売上顧客'!$E$5:$E$504,$A27) | E27: =COUNTIFS('4月_売上顧客'!$E$5:$E$504,$A27) | F27: =COUNTIFS('5月_売上顧客'!$E$5:$E$504,$A27) | G27: =COUNTIFS('6月_売上顧客'!$E$5:$E$504,$A27) | H27: =COUNTIFS('7月_売上顧客'!$E$5:$E$504,$A27) | I27: =COUNTIFS('8月_売上顧客'!$E$5:$E$504,$A27) | J27: =COUNTIFS('9月_売上顧客'!$E$5:$E$504,$A27) | K27: =COUNTIFS('10月_売上顧客'!$E$5:$E$504,$A27) | L27: =COUNTIFS('11月_売上顧客'!$E$5:$E$504,$A27) | M27: =COUNTIFS('12月_売上顧客'!$E$5:$E$504,$A27) | N27: =SUM(B27:M27)
A28: 入札案件 | B28: =COUNTIFS('1月_売上顧客'!$E$5:$E$504,$A28) | C28: =COUNTIFS('2月_売上顧客'!$E$5:$E$504,$A28) | D28: =COUNTIFS('3月_売上顧客'!$E$5:$E$504,$A28) | E28: =COUNTIFS('4月_売上顧客'!$E$5:$E$504,$A28) | F28: =COUNTIFS('5月_売上顧客'!$E$5:$E$504,$A28) | G28: =COUNTIFS('6月_売上顧客'!$E$5:$E$504,$A28) | H28: =COUNTIFS('7月_売上顧客'!$E$5:$E$504,$A28) | I28: =COUNTIFS('8月_売上顧客'!$E$5:$E$504,$A28) | J28: =COUNTIFS('9月_売上顧客'!$E$5:$E$504,$A28) | K28: =COUNTIFS('10月_売上顧客'!$E$5:$E$504,$A28) | L28: =COUNTIFS('11月_売上顧客'!$E$5:$E$504,$A28) | M28: =COUNTIFS('12月_売上顧客'!$E$5:$E$504,$A28) | N28: =SUM(B28:M28)
A29: チラシ(本舗) | B29: =COUNTIFS('1月_売上顧客'!$E$5:$E$504,$A29) | C29: =COUNTIFS('2月_売上顧客'!$E$5:$E$504,$A29) | D29: =COUNTIFS('3月_売上顧客'!$E$5:$E$504,$A29) | E29: =COUNTIFS('4月_売上顧客'!$E$5:$E$504,$A29) | F29: =COUNTIFS('5月_売上顧客'!$E$5:$E$504,$A29) | G29: =COUNTIFS('6月_売上顧客'!$E$5:$E$504,$A29) | H29: =COUNTIFS('7月_売上顧客'!$E$5:$E$504,$A29) | I29: =COUNTIFS('8月_売上顧客'!$E$5:$E$504,$A29) | J29: =COUNTIFS('9月_売上顧客'!$E$5:$E$504,$A29) | K29: =COUNTIFS('10月_売上顧客'!$E$5:$E$504,$A29) | L29: =COUNTIFS('11月_売上顧客'!$E$5:$E$504,$A29) | M29: =COUNTIFS('12月_売上顧客'!$E$5:$E$504,$A29) | N29: =SUM(B29:M29)
... A39: その他 | B39: =COUNTIFS('1月_売上顧客'!$E$5:$E$504,$A39) | C39: =COUNTIFS('2月_売上顧客'!$E$5:$E$504,$A39) | D39: =COUNTIFS('3月_売上顧客'!$E$5:$E$504,$A39) | E39: =COUNTIFS('4月_売上顧客'!$E$5:$E$504,$A39) | F39: =COUNTIFS('5月_売上顧客'!$E$5:$E$504,$A39) | G39: =COUNTIFS('6月_売上顧客'!$E$5:$E$504,$A39) | H39: =COUNTIFS('7月_売上顧客'!$E$5:$E$504,$A39) | I39: =COUNTIFS('8月_売上顧客'!$E$5:$E$504,$A39) | J39: =COUNTIFS('9月_売上顧客'!$E$5:$E$504,$A39) | K39: =COUNTIFS('10月_売上顧客'!$E$5:$E$504,$A39) | L39: =COUNTIFS('11月_売上顧客'!$E$5:$E$504,$A39) | M39: =COUNTIFS('12月_売上顧客'!$E$5:$E$504,$A39) | N39: =SUM(B39:M39)
A40: 合計 | B40: =SUM(B18:B39) | C40: =SUM(C18:C39) | D40: =SUM(D18:D39) | E40: =SUM(E18:E39) | F40: =SUM(F18:F39) | G40: =SUM(G18:G39) | H40: =SUM(H18:H39) | I40: =SUM(I18:I39) | ... N40: =SUM(N18:N39)
A42: ▼ 流入経路別 売上
A43: 流入経路 | B43: 1月 | C43: 2月 | D43: 3月 | E43: 4月 | F43: 5月 | G43: 6月 | H43: 7月 | I43: 8月 | J43: 9月 | K43: 10月 | L43: 11月 | M43: 12月 | N43: 年計
A44: リピート | B44: =SUMIFS('1月_売上顧客'!$L$5:$L$504,'1月_売上顧客'!$E$5:$E$504,$A44) | C44: =SUMIFS('2月_売上顧客'!$L$5:$L$504,'2月_売上顧客'!$E$5:$E$504,$A44) | D44: =SUMIFS('3月_売上顧客'!$L$5:$L$504,'3月_売上顧客'!$E$5:$E$504,$A44) | E44: =SUMIFS('4月_売上顧客'!$L$5:$L$504,'4月_売上顧客'!$E$5:$E$504,$A44) | F44: =SUMIFS('5月_売上顧客'!$L$5:$L$504,'5月_売上顧客'!$E$5:$E$504,$A44) | G44: =SUMIFS('6月_売上顧客'!$L$5:$L$504,'6月_売上顧客'!$E$5:$E$504,$A44) | H44: =SUMIFS('7月_売上顧客'!$L$5:$L$504,'7月_売上顧客'!$E$5:$E$504,$A44) | I44: =SUMIFS('8月_売上顧客'!$L$5:$L$504,'8月_売上顧客'!$E$5:$E$504,$A44) | J44: =SUMIFS('9月_売上顧客'!$L$5:$L$504,'9月_売上顧客'!$E$5:$E$504,$A44) | K44: =SUMIFS('10月_売上顧客'!$L$5:$L$504,'10月_売上顧客'!$E$5:$E$504,$A44) | L44: =SUMIFS('11月_売上顧客'!$L$5:$L$504,'11月_売上顧客'!$E$5:$E$504,$A44) | M44: =SUMIFS('12月_売上顧客'!$L$5:$L$504,'12月_売上顧客'!$E$5:$E$504,$A44) | N44: =SUM(B44:M44)
A45: 早期予約 | B45: =SUMIFS('1月_売上顧客'!$L$5:$L$504,'1月_売上顧客'!$E$5:$E$504,$A45) | C45: =SUMIFS('2月_売上顧客'!$L$5:$L$504,'2月_売上顧客'!$E$5:$E$504,$A45) | D45: =SUMIFS('3月_売上顧客'!$L$5:$L$504,'3月_売上顧客'!$E$5:$E$504,$A45) | E45: =SUMIFS('4月_売上顧客'!$L$5:$L$504,'4月_売上顧客'!$E$5:$E$504,$A45) | F45: =SUMIFS('5月_売上顧客'!$L$5:$L$504,'5月_売上顧客'!$E$5:$E$504,$A45) | G45: =SUMIFS('6月_売上顧客'!$L$5:$L$504,'6月_売上顧客'!$E$5:$E$504,$A45) | H45: =SUMIFS('7月_売上顧客'!$L$5:$L$504,'7月_売上顧客'!$E$5:$E$504,$A45) | I45: =SUMIFS('8月_売上顧客'!$L$5:$L$504,'8月_売上顧客'!$E$5:$E$504,$A45) | J45: =SUMIFS('9月_売上顧客'!$L$5:$L$504,'9月_売上顧客'!$E$5:$E$504,$A45) | K45: =SUMIFS('10月_売上顧客'!$L$5:$L$504,'10月_売上顧客'!$E$5:$E$504,$A45) | L45: =SUMIFS('11月_売上顧客'!$L$5:$L$504,'11月_売上顧客'!$E$5:$E$504,$A45) | M45: =SUMIFS('12月_売上顧客'!$L$5:$L$504,'12月_売上顧客'!$E$5:$E$504,$A45) | N45: =SUM(B45:M45)
A46: 楽ラクーン | B46: =SUMIFS('1月_売上顧客'!$L$5:$L$504,'1月_売上顧客'!$E$5:$E$504,$A46) | C46: =SUMIFS('2月_売上顧客'!$L$5:$L$504,'2月_売上顧客'!$E$5:$E$504,$A46) | D46: =SUMIFS('3月_売上顧客'!$L$5:$L$504,'3月_売上顧客'!$E$5:$E$504,$A46) | E46: =SUMIFS('4月_売上顧客'!$L$5:$L$504,'4月_売上顧客'!$E$5:$E$504,$A46) | F46: =SUMIFS('5月_売上顧客'!$L$5:$L$504,'5月_売上顧客'!$E$5:$E$504,$A46) | G46: =SUMIFS('6月_売上顧客'!$L$5:$L$504,'6月_売上顧客'!$E$5:$E$504,$A46) | H46: =SUMIFS('7月_売上顧客'!$L$5:$L$504,'7月_売上顧客'!$E$5:$E$504,$A46) | I46: =SUMIFS('8月_売上顧客'!$L$5:$L$504,'8月_売上顧客'!$E$5:$E$504,$A46) | J46: =SUMIFS('9月_売上顧客'!$L$5:$L$504,'9月_売上顧客'!$E$5:$E$504,$A46) | K46: =SUMIFS('10月_売上顧客'!$L$5:$L$504,'10月_売上顧客'!$E$5:$E$504,$A46) | L46: =SUMIFS('11月_売上顧客'!$L$5:$L$504,'11月_売上顧客'!$E$5:$E$504,$A46) | M46: =SUMIFS('12月_売上顧客'!$L$5:$L$504,'12月_売上顧客'!$E$5:$E$504,$A46) | N46: =SUM(B46:M46)
A47: 業務提携 | B47: =SUMIFS('1月_売上顧客'!$L$5:$L$504,'1月_売上顧客'!$E$5:$E$504,$A47) | C47: =SUMIFS('2月_売上顧客'!$L$5:$L$504,'2月_売上顧客'!$E$5:$E$504,$A47) | D47: =SUMIFS('3月_売上顧客'!$L$5:$L$504,'3月_売上顧客'!$E$5:$E$504,$A47) | E47: =SUMIFS('4月_売上顧客'!$L$5:$L$504,'4月_売上顧客'!$E$5:$E$504,$A47) | F47: =SUMIFS('5月_売上顧客'!$L$5:$L$504,'5月_売上顧客'!$E$5:$E$504,$A47) | G47: =SUMIFS('6月_売上顧客'!$L$5:$L$504,'6月_売上顧客'!$E$5:$E$504,$A47) | H47: =SUMIFS('7月_売上顧客'!$L$5:$L$504,'7月_売上顧客'!$E$5:$E$504,$A47) | I47: =SUMIFS('8月_売上顧客'!$L$5:$L$504,'8月_売上顧客'!$E$5:$E$504,$A47) | J47: =SUMIFS('9月_売上顧客'!$L$5:$L$504,'9月_売上顧客'!$E$5:$E$504,$A47) | K47: =SUMIFS('10月_売上顧客'!$L$5:$L$504,'10月_売上顧客'!$E$5:$E$504,$A47) | L47: =SUMIFS('11月_売上顧客'!$L$5:$L$504,'11月_売上顧客'!$E$5:$E$504,$A47) | M47: =SUMIFS('12月_売上顧客'!$L$5:$L$504,'12月_売上顧客'!$E$5:$E$504,$A47) | N47: =SUM(B47:M47)
A48: スケジュールマッチング | B48: =SUMIFS('1月_売上顧客'!$L$5:$L$504,'1月_売上顧客'!$E$5:$E$504,$A48) | C48: =SUMIFS('2月_売上顧客'!$L$5:$L$504,'2月_売上顧客'!$E$5:$E$504,$A48) | D48: =SUMIFS('3月_売上顧客'!$L$5:$L$504,'3月_売上顧客'!$E$5:$E$504,$A48) | E48: =SUMIFS('4月_売上顧客'!$L$5:$L$504,'4月_売上顧客'!$E$5:$E$504,$A48) | F48: =SUMIFS('5月_売上顧客'!$L$5:$L$504,'5月_売上顧客'!$E$5:$E$504,$A48) | G48: =SUMIFS('6月_売上顧客'!$L$5:$L$504,'6月_売上顧客'!$E$5:$E$504,$A48) | H48: =SUMIFS('7月_売上顧客'!$L$5:$L$504,'7月_売上顧客'!$E$5:$E$504,$A48) | I48: =SUMIFS('8月_売上顧客'!$L$5:$L$504,'8月_売上顧客'!$E$5:$E$504,$A48) | J48: =SUMIFS('9月_売上顧客'!$L$5:$L$504,'9月_売上顧客'!$E$5:$E$504,$A48) | K48: =SUMIFS('10月_売上顧客'!$L$5:$L$504,'10月_売上顧客'!$E$5:$E$504,$A48) | L48: =SUMIFS('11月_売上顧客'!$L$5:$L$504,'11月_売上顧客'!$E$5:$E$504,$A48) | M48: =SUMIFS('12月_売上顧客'!$L$5:$L$504,'12月_売上顧客'!$E$5:$E$504,$A48) | N48: =SUM(B48:M48)
A49: おそうじ定期便 | B49: =SUMIFS('1月_売上顧客'!$L$5:$L$504,'1月_売上顧客'!$E$5:$E$504,$A49) | C49: =SUMIFS('2月_売上顧客'!$L$5:$L$504,'2月_売上顧客'!$E$5:$E$504,$A49) | D49: =SUMIFS('3月_売上顧客'!$L$5:$L$504,'3月_売上顧客'!$E$5:$E$504,$A49) | E49: =SUMIFS('4月_売上顧客'!$L$5:$L$504,'4月_売上顧客'!$E$5:$E$504,$A49) | F49: =SUMIFS('5月_売上顧客'!$L$5:$L$504,'5月_売上顧客'!$E$5:$E$504,$A49) | G49: =SUMIFS('6月_売上顧客'!$L$5:$L$504,'6月_売上顧客'!$E$5:$E$504,$A49) | H49: =SUMIFS('7月_売上顧客'!$L$5:$L$504,'7月_売上顧客'!$E$5:$E$504,$A49) | I49: =SUMIFS('8月_売上顧客'!$L$5:$L$504,'8月_売上顧客'!$E$5:$E$504,$A49) | J49: =SUMIFS('9月_売上顧客'!$L$5:$L$504,'9月_売上顧客'!$E$5:$E$504,$A49) | K49: =SUMIFS('10月_売上顧客'!$L$5:$L$504,'10月_売上顧客'!$E$5:$E$504,$A49) | L49: =SUMIFS('11月_売上顧客'!$L$5:$L$504,'11月_売上顧客'!$E$5:$E$504,$A49) | M49: =SUMIFS('12月_売上顧客'!$L$5:$L$504,'12月_売上顧客'!$E$5:$E$504,$A49) | N49: =SUM(B49:M49)
A50: 紹介 | B50: =SUMIFS('1月_売上顧客'!$L$5:$L$504,'1月_売上顧客'!$E$5:$E$504,$A50) | C50: =SUMIFS('2月_売上顧客'!$L$5:$L$504,'2月_売上顧客'!$E$5:$E$504,$A50) | D50: =SUMIFS('3月_売上顧客'!$L$5:$L$504,'3月_売上顧客'!$E$5:$E$504,$A50) | E50: =SUMIFS('4月_売上顧客'!$L$5:$L$504,'4月_売上顧客'!$E$5:$E$504,$A50) | F50: =SUMIFS('5月_売上顧客'!$L$5:$L$504,'5月_売上顧客'!$E$5:$E$504,$A50) | G50: =SUMIFS('6月_売上顧客'!$L$5:$L$504,'6月_売上顧客'!$E$5:$E$504,$A50) | H50: =SUMIFS('7月_売上顧客'!$L$5:$L$504,'7月_売上顧客'!$E$5:$E$504,$A50) | I50: =SUMIFS('8月_売上顧客'!$L$5:$L$504,'8月_売上顧客'!$E$5:$E$504,$A50) | J50: =SUMIFS('9月_売上顧客'!$L$5:$L$504,'9月_売上顧客'!$E$5:$E$504,$A50) | K50: =SUMIFS('10月_売上顧客'!$L$5:$L$504,'10月_売上顧客'!$E$5:$E$504,$A50) | L50: =SUMIFS('11月_売上顧客'!$L$5:$L$504,'11月_売上顧客'!$E$5:$E$504,$A50) | M50: =SUMIFS('12月_売上顧客'!$L$5:$L$504,'12月_売上顧客'!$E$5:$E$504,$A50) | N50: =SUM(B50:M50)
A51: 営業 | B51: =SUMIFS('1月_売上顧客'!$L$5:$L$504,'1月_売上顧客'!$E$5:$E$504,$A51) | C51: =SUMIFS('2月_売上顧客'!$L$5:$L$504,'2月_売上顧客'!$E$5:$E$504,$A51) | D51: =SUMIFS('3月_売上顧客'!$L$5:$L$504,'3月_売上顧客'!$E$5:$E$504,$A51) | E51: =SUMIFS('4月_売上顧客'!$L$5:$L$504,'4月_売上顧客'!$E$5:$E$504,$A51) | F51: =SUMIFS('5月_売上顧客'!$L$5:$L$504,'5月_売上顧客'!$E$5:$E$504,$A51) | G51: =SUMIFS('6月_売上顧客'!$L$5:$L$504,'6月_売上顧客'!$E$5:$E$504,$A51) | H51: =SUMIFS('7月_売上顧客'!$L$5:$L$504,'7月_売上顧客'!$E$5:$E$504,$A51) | I51: =SUMIFS('8月_売上顧客'!$L$5:$L$504,'8月_売上顧客'!$E$5:$E$504,$A51) | J51: =SUMIFS('9月_売上顧客'!$L$5:$L$504,'9月_売上顧客'!$E$5:$E$504,$A51) | K51: =SUMIFS('10月_売上顧客'!$L$5:$L$504,'10月_売上顧客'!$E$5:$E$504,$A51) | L51: =SUMIFS('11月_売上顧客'!$L$5:$L$504,'11月_売上顧客'!$E$5:$E$504,$A51) | M51: =SUMIFS('12月_売上顧客'!$L$5:$L$504,'12月_売上顧客'!$E$5:$E$504,$A51) | N51: =SUM(B51:M51)
A52: チラシ(OH) | B52: =SUMIFS('1月_売上顧客'!$L$5:$L$504,'1月_売上顧客'!$E$5:$E$504,$A52) | C52: =SUMIFS('2月_売上顧客'!$L$5:$L$504,'2月_売上顧客'!$E$5:$E$504,$A52) | D52: =SUMIFS('3月_売上顧客'!$L$5:$L$504,'3月_売上顧客'!$E$5:$E$504,$A52) | E52: =SUMIFS('4月_売上顧客'!$L$5:$L$504,'4月_売上顧客'!$E$5:$E$504,$A52) | F52: =SUMIFS('5月_売上顧客'!$L$5:$L$504,'5月_売上顧客'!$E$5:$E$504,$A52) | G52: =SUMIFS('6月_売上顧客'!$L$5:$L$504,'6月_売上顧客'!$E$5:$E$504,$A52) | H52: =SUMIFS('7月_売上顧客'!$L$5:$L$504,'7月_売上顧客'!$E$5:$E$504,$A52) | I52: =SUMIFS('8月_売上顧客'!$L$5:$L$504,'8月_売上顧客'!$E$5:$E$504,$A52) | J52: =SUMIFS('9月_売上顧客'!$L$5:$L$504,'9月_売上顧客'!$E$5:$E$504,$A52) | K52: =SUMIFS('10月_売上顧客'!$L$5:$L$504,'10月_売上顧客'!$E$5:$E$504,$A52) | L52: =SUMIFS('11月_売上顧客'!$L$5:$L$504,'11月_売上顧客'!$E$5:$E$504,$A52) | M52: =SUMIFS('12月_売上顧客'!$L$5:$L$504,'12月_売上顧客'!$E$5:$E$504,$A52) | N52: =SUM(B52:M52)
A53: HP | B53: =SUMIFS('1月_売上顧客'!$L$5:$L$504,'1月_売上顧客'!$E$5:$E$504,$A53) | C53: =SUMIFS('2月_売上顧客'!$L$5:$L$504,'2月_売上顧客'!$E$5:$E$504,$A53) | D53: =SUMIFS('3月_売上顧客'!$L$5:$L$504,'3月_売上顧客'!$E$5:$E$504,$A53) | E53: =SUMIFS('4月_売上顧客'!$L$5:$L$504,'4月_売上顧客'!$E$5:$E$504,$A53) | F53: =SUMIFS('5月_売上顧客'!$L$5:$L$504,'5月_売上顧客'!$E$5:$E$504,$A53) | G53: =SUMIFS('6月_売上顧客'!$L$5:$L$504,'6月_売上顧客'!$E$5:$E$504,$A53) | H53: =SUMIFS('7月_売上顧客'!$L$5:$L$504,'7月_売上顧客'!$E$5:$E$504,$A53) | I53: =SUMIFS('8月_売上顧客'!$L$5:$L$504,'8月_売上顧客'!$E$5:$E$504,$A53) | J53: =SUMIFS('9月_売上顧客'!$L$5:$L$504,'9月_売上顧客'!$E$5:$E$504,$A53) | K53: =SUMIFS('10月_売上顧客'!$L$5:$L$504,'10月_売上顧客'!$E$5:$E$504,$A53) | L53: =SUMIFS('11月_売上顧客'!$L$5:$L$504,'11月_売上顧客'!$E$5:$E$504,$A53) | M53: =SUMIFS('12月_売上顧客'!$L$5:$L$504,'12月_売上顧客'!$E$5:$E$504,$A53) | N53: =SUM(B53:M53)
A54: 入札案件 | B54: =SUMIFS('1月_売上顧客'!$L$5:$L$504,'1月_売上顧客'!$E$5:$E$504,$A54) | C54: =SUMIFS('2月_売上顧客'!$L$5:$L$504,'2月_売上顧客'!$E$5:$E$504,$A54) | D54: =SUMIFS('3月_売上顧客'!$L$5:$L$504,'3月_売上顧客'!$E$5:$E$504,$A54) | E54: =SUMIFS('4月_売上顧客'!$L$5:$L$504,'4月_売上顧客'!$E$5:$E$504,$A54) | F54: =SUMIFS('5月_売上顧客'!$L$5:$L$504,'5月_売上顧客'!$E$5:$E$504,$A54) | G54: =SUMIFS('6月_売上顧客'!$L$5:$L$504,'6月_売上顧客'!$E$5:$E$504,$A54) | H54: =SUMIFS('7月_売上顧客'!$L$5:$L$504,'7月_売上顧客'!$E$5:$E$504,$A54) | I54: =SUMIFS('8月_売上顧客'!$L$5:$L$504,'8月_売上顧客'!$E$5:$E$504,$A54) | J54: =SUMIFS('9月_売上顧客'!$L$5:$L$504,'9月_売上顧客'!$E$5:$E$504,$A54) | K54: =SUMIFS('10月_売上顧客'!$L$5:$L$504,'10月_売上顧客'!$E$5:$E$504,$A54) | L54: =SUMIFS('11月_売上顧客'!$L$5:$L$504,'11月_売上顧客'!$E$5:$E$504,$A54) | M54: =SUMIFS('12月_売上顧客'!$L$5:$L$504,'12月_売上顧客'!$E$5:$E$504,$A54) | N54: =SUM(B54:M54)
A55: チラシ(本舗) | B55: =SUMIFS('1月_売上顧客'!$L$5:$L$504,'1月_売上顧客'!$E$5:$E$504,$A55) | C55: =SUMIFS('2月_売上顧客'!$L$5:$L$504,'2月_売上顧客'!$E$5:$E$504,$A55) | D55: =SUMIFS('3月_売上顧客'!$L$5:$L$504,'3月_売上顧客'!$E$5:$E$504,$A55) | E55: =SUMIFS('4月_売上顧客'!$L$5:$L$504,'4月_売上顧客'!$E$5:$E$504,$A55) | F55: =SUMIFS('5月_売上顧客'!$L$5:$L$504,'5月_売上顧客'!$E$5:$E$504,$A55) | G55: =SUMIFS('6月_売上顧客'!$L$5:$L$504,'6月_売上顧客'!$E$5:$E$504,$A55) | H55: =SUMIFS('7月_売上顧客'!$L$5:$L$504,'7月_売上顧客'!$E$5:$E$504,$A55) | I55: =SUMIFS('8月_売上顧客'!$L$5:$L$504,'8月_売上顧客'!$E$5:$E$504,$A55) | J55: =SUMIFS('9月_売上顧客'!$L$5:$L$504,'9月_売上顧客'!$E$5:$E$504,$A55) | K55: =SUMIFS('10月_売上顧客'!$L$5:$L$504,'10月_売上顧客'!$E$5:$E$504,$A55) | L55: =SUMIFS('11月_売上顧客'!$L$5:$L$504,'11月_売上顧客'!$E$5:$E$504,$A55) | M55: =SUMIFS('12月_売上顧客'!$L$5:$L$504,'12月_売上顧客'!$E$5:$E$504,$A55) | N55: =SUM(B55:M55)
... A65: その他 | B65: =SUMIFS('1月_売上顧客'!$L$5:$L$504,'1月_売上顧客'!$E$5:$E$504,$A65) | C65: =SUMIFS('2月_売上顧客'!$L$5:$L$504,'2月_売上顧客'!$E$5:$E$504,$A65) | D65: =SUMIFS('3月_売上顧客'!$L$5:$L$504,'3月_売上顧客'!$E$5:$E$504,$A65) | E65: =SUMIFS('4月_売上顧客'!$L$5:$L$504,'4月_売上顧客'!$E$5:$E$504,$A65) | F65: =SUMIFS('5月_売上顧客'!$L$5:$L$504,'5月_売上顧客'!$E$5:$E$504,$A65) | G65: =SUMIFS('6月_売上顧客'!$L$5:$L$504,'6月_売上顧客'!$E$5:$E$504,$A65) | H65: =SUMIFS('7月_売上顧客'!$L$5:$L$504,'7月_売上顧客'!$E$5:$E$504,$A65) | I65: =SUMIFS('8月_売上顧客'!$L$5:$L$504,'8月_売上顧客'!$E$5:$E$504,$A65) | J65: =SUMIFS('9月_売上顧客'!$L$5:$L$504,'9月_売上顧客'!$E$5:$E$504,$A65) | K65: =SUMIFS('10月_売上顧客'!$L$5:$L$504,'10月_売上顧客'!$E$5:$E$504,$A65) | L65: =SUMIFS('11月_売上顧客'!$L$5:$L$504,'11月_売上顧客'!$E$5:$E$504,$A65) | M65: =SUMIFS('12月_売上顧客'!$L$5:$L$504,'12月_売上顧客'!$E$5:$E$504,$A65) | N65: =SUM(B65:M65)
A66: 合計 | B66: =SUM(B44:B65) | C66: =SUM(C44:C65) | D66: =SUM(D44:D65) | E66: =SUM(E44:E65) | F66: =SUM(F44:F65) | G66: =SUM(G44:G65) | H66: =SUM(H44:H65) | I66: =SUM(I44:I65) | ... N66: =SUM(N44:N65)

Sheet 分析_流入経路とLTV
A1: 入口ごとのLTVとリピート率 — 広告CPA上限9,500円の根拠
A2: 2026年実績（docs/流入経路の分析.md、319件＋顧客管理台帳）。2027年の列は年末に埋めます。
A4: ★広告CPAの上限は9,500円。マッチングPFに払っている実質手数料（35%・1件あたり約9,500円）と同額。ここを下回る限り、出すほど有利です。しかも自社経由のお客様はリピート率36%なので2回目以降が上乗せされます。
A6: 初回の入口 | B6: 2026 施工数 | C6: 2026 平均施工回数 | D6: 2026 平均LTV | E6: 2026 リピート率 | F6: 2027 施工数 | G6: 2027 平均LTV | H6: 2027 リピート率 | I6: メモ
A7: マッチングPF（楽ラクーン・スケジュールマッチング等） | B7: 100 | C7: 1.02 | D7: 28172 | E7: 0.02 | I7: 35%の手数料を払って、二度と戻ってこないお客様を借りている状態
A8: 業務提携 | B8: 40 | C8: 2.52 | D8: 186272 | E8: 0.45 | I8: 他の入口とは桁が違う。2社→4社が2027年の②ブロック
A9: 自社直販（HP・紹介・営業・チラシ・SMS） | B9: 28 | C9: 1.26 | D9: 42823 | E9: 0.26 | I9: LTVは1.5倍・リピートは18倍。ここを増やすのが④ブロック
A12: ▼ 2026年 流入経路別の売上（全319件・12,636,141円）
A13: 流入経路 | B13: 件数 | C13: 売上 | D13: 単価 | E13: メモ
A14: リピート | B14: 69 | C14: 3130845 | D14: 45374
A15: 楽ラクーン | B15: 67 | C15: 1845833 | D15: 27549 | E15: フォロー連絡 不可
A16: 早期予約 | B16: 65 | C16: 1510138 | D16: 23232
A17: 業務提携 | B17: 40 | C17: 4005135 | D17: 100128 | E17: 2026年8月の大型案件1,841,740円を含む。再現前提にしない
A18: スケジュールマッチング | B18: 31 | C18: 831050 | D18: 26808 | E18: 本舗の番号から連絡
A19: おそうじ定期便 | B19: 12 | C19: 117600 | D19: 9800
A20: 紹介 | B20: 11 | C20: 379460 | D20: 34496
A21: 営業 | B21: 8 | C21: 391820 | D21: 48977
A22: チラシ(OH) | B22: 4 | C22: 77800 | D22: 19450
A23: HP | B23: 4 | C23: 63100 | D23: 15775 | E23: ★売上全体の0.5%。HP関連費は年580,800円。2027年に必ず黒字化させる
A24: その他（入札・チラシ本舗・SMS等） | B24: 8 | C24: 283360
A27: 【正直に書いておく限界】
A28: ・マッチングPFの規約で、そこ経由のお客様との直接取引が禁じられている可能性があります。再販の前に契約書の確認が要ります
A29: ・台帳の「回数」は通算値。2026年に初めて来たお客様の観察期間は最長8か月です（1〜6月に絞った再計算でもマッチングPFは2%のまま）
A30: ・業務提携のLTVには法人・寮・店舗の大型案件が含まれます。個人のお客様と単純比較はできません
A31: ・おそうじ本舗（フランチャイズ）経由の分は、送信主体が異なるため自社直販に含めていません

Sheet 見積ルール
A1: 見積ルール・料金表（全て税込）
A2: 正データは data/prices.json。ここは焼き込みです。数字を変えるときは prices.json と公開物（公式サイトTOP・LP）も必ず揃えること。
A3: ★5・6・7・12月は全メニューに繁忙期加算 ¥3,300（税込）が加算されます。オプションの防カビコート¥3,630・浴室換気扇洗浄¥3,630と数字が近いので取り違えないこと。
A5: 本メニュー | B5: 単体（税込） | C5: 同時施工（税込） | D5: 所要 | F5: オプション | G5: 価格（税込）
A6: エアコンクリーニング（ノーマル） | B6: 10780 | D6: 60分 | F6: エアコン 室外機セット | G6: 6050
A7: エアコンクリーニング（お掃除機能付き） | B7: 17380 | D7: 120分 | F7: エアコン 防カビコート | G7: 3630
A8: 洗濯機クリーニング | B8: 17380 | C8: 17380 | D8: 120分 | F8: エアコン 防虫キャップ | G8: 1210
A9: レンジフードクリーニング | B9: 18480 | C9: 15180 | D9: 90分 | F9: 洗濯機 設置枠（防水パン） | G9: 3630
A10: レンジフード（プロペラ式） | B10: 10780 | D10: 60分 | F10: 洗濯機 排水溝クリーニング | G10: 3630
A11: キッチンクリーニング | B11: 18480 | C11: 15180 | D11: 150分 | F11: キッチンセット | G11: 15180
A12: 浴室クリーニング | B12: 18480 | C12: 15180 | D12: 180分 | F12: コンロセット | G12: 6050
A13: 追い焚き配管クリーニング | B13: 19910 | C13: 16610 | D13: 60分 | F13: 水回り お掃除時短コーティング | G13: 21780
A14: コンロクリーニング | B14: 10780 | C14: 6050 | D14: 30分 | F14: 浴室乾燥機洗浄 | G14: 8580
A15: トイレクリーニング | B15: 10780 | C15: 10780 | D15: 60分 | F15: 追い焚き配管クリーニング（同時施工） | G15: 16610
A16: 洗面台クリーニング | B16: 10780 | C16: 7480 | D16: 60分 | F16: エプロン内部高圧洗浄 | G16: 8470
A17: お掃除時短コーティング | B17: 21780 | D17: 60分 | F17: 浴室換気扇洗浄 | G17: 3630
F18: 鏡の水垢除去 | G18: 3630
F19: 浴室セット | G19: 15180
A20: ▼ 法人メニュー | F20: 換気扇セット | G20: 15180
A21: メニュー | B21: 価格（税込） | C21: 備考 | F21: 洗面台丸洗い | G21: 7480
A22: 定期清掃 | B22: 32780 | C22: 〜
A23: 空室清掃 | B23: 58080 | C23: 〜
A24: 業務用エアコン | B24: 27280 | C24: 〜
A27: ▼ 割引・紹介のルール
A28: 早期予約割引 1-2月 | B28: 0.15
A29: 早期予約割引 3-4月 | B29: 0.1
A30: 早期予約割引 8-10月 | B30: 0.1
A31: 早期予約割引 5-7月 | B31: 0.0
A32: 早期予約割引 11-12月 | B32: 0.0
A33: 同時施工割引 標準 | B33: 3300
A34: 同時施工割引 コンロ | B34: 4730
A35: 同時施工割引 洗濯機 | B35: 0
A36: 同時施工割引 トイレ | B36: 0
A37: 紹介料 消費者から消費者 | B37: {'種別': '定額', '金額': 1000}
A38: 紹介料 事業者から顧客 | B38: {'種別': '料率', '下限': 0.05, '上限': 0.15, '原則': 0.12}
A39: 繁忙期加算 | B39: 3300円（対象月 [5, 6, 7, 12]）
A41: 【必ず守ること】
A42: ・料金はパンフレットPDFが正。公式サイトの料金表には誤りがあります（docs/site-audit.md）
A43: ・2021年4月から総額表示が義務。必ず「（税込）」を併記すること
A44: ・満足度は 98.6%（209名中206名／2023年1月〜2025年12月）。「98.8%」は根拠と一致しないので使わないこと
A45: ・対応エリアは東京都・千葉県・神奈川県（埼玉は実績ありだが積極開拓しない）
A46: ・この表の出典：data/prices.json（パンフレットPDFの金額は税抜。オーナー確認（2026-09-04）。全メニュー×1.1で税込に換算した。）

Sheet TODO
A1: TODO
A2: 状態を「完了」にしたら行を消さないこと。あとで何をやったか分からなくなります。
A3: 未着手 | B3: =COUNTIF($E$5:$E$304,"未着手") | C3: 進行中 | D3: =COUNTIF($E$5:$E$304,"進行中") | E3: 完了 | F3: =COUNTIF($E$5:$E$304,"完了") | G3: 対象外 | H3: =COUNTIF($E$5:$E$304,"対象外")
A4: No. | B4: 件名 | C4: 内容 | D4: 担当 | E4: 状態 | F4: 期限 | G4: 優先度 | H4: 更新日 | I4: メモ

Sheet 勤怠管理
A1: 勤怠管理
A2: 労働時間は自動計算（終了−開始−休憩）。現場人件費（原価）の根拠になります。
L3: ▼ 月別 集計（自動）
A4: 日付 | B4: 月(自動) | C4: 氏名 | D4: 開始 | E4: 終了 | F4: 休憩(h) | G4: 労働時間(h・自動) | H4: 現場数 | I4: 区分 | J4: メモ | L4: 月 | M4: 労働時間(h) | N4: 現場数
B5: =IFERROR(MONTH($A5),"") | G5: =IFERROR(($E5-$D5)*24-$F5,"") | L5: 1 | M5: =SUMIFS($G$5:$G$1004,$B$5:$B$1004,1) | N5: =SUMIFS($H$5:$H$1004,$B$5:$B$1004,1)
B6: =IFERROR(MONTH($A6),"") | G6: =IFERROR(($E6-$D6)*24-$F6,"") | L6: 2 | M6: =SUMIFS($G$5:$G$1004,$B$5:$B$1004,2) | N6: =SUMIFS($H$5:$H$1004,$B$5:$B$1004,2)
B7: =IFERROR(MONTH($A7),"") | G7: =IFERROR(($E7-$D7)*24-$F7,"") | L7: 3 | M7: =SUMIFS($G$5:$G$1004,$B$5:$B$1004,3) | N7: =SUMIFS($H$5:$H$1004,$B$5:$B$1004,3)
B8: =IFERROR(MONTH($A8),"") | G8: =IFERROR(($E8-$D8)*24-$F8,"") | L8: 4 | M8: =SUMIFS($G$5:$G$1004,$B$5:$B$1004,4) | N8: =SUMIFS($H$5:$H$1004,$B$5:$B$1004,4)
B9: =IFERROR(MONTH($A9),"") | G9: =IFERROR(($E9-$D9)*24-$F9,"") | L9: 5 | M9: =SUMIFS($G$5:$G$1004,$B$5:$B$1004,5) | N9: =SUMIFS($H$5:$H$1004,$B$5:$B$1004,5)
B10: =IFERROR(MONTH($A10),"") | G10: =IFERROR(($E10-$D10)*24-$F10,"") | L10: 6 | M10: =SUMIFS($G$5:$G$1004,$B$5:$B$1004,6) | N10: =SUMIFS($H$5:$H$1004,$B$5:$B$1004,6)
B11: =IFERROR(MONTH($A11),"") | G11: =IFERROR(($E11-$D11)*24-$F11,"") | L11: 7 | M11: =SUMIFS($G$5:$G$1004,$B$5:$B$1004,7) | N11: =SUMIFS($H$5:$H$1004,$B$5:$B$1004,7)
B12: =IFERROR(MONTH($A12),"") | G12: =IFERROR(($E12-$D12)*24-$F12,"") | L12: 8 | M12: =SUMIFS($G$5:$G$1004,$B$5:$B$1004,8) | N12: =SUMIFS($H$5:$H$1004,$B$5:$B$1004,8)
B13: =IFERROR(MONTH($A13),"") | G13: =IFERROR(($E13-$D13)*24-$F13,"") | L13: 9 | M13: =SUMIFS($G$5:$G$1004,$B$5:$B$1004,9) | N13: =SUMIFS($H$5:$H$1004,$B$5:$B$1004,9)
B14: =IFERROR(MONTH($A14),"") | G14: =IFERROR(($E14-$D14)*24-$F14,"") | L14: 10 | M14: =SUMIFS($G$5:$G$1004,$B$5:$B$1004,10) | N14: =SUMIFS($H$5:$H$1004,$B$5:$B$1004,10)
B15: =IFERROR(MONTH($A15),"") | G15: =IFERROR(($E15-$D15)*24-$F15,"") | L15: 11 | M15: =SUMIFS($G$5:$G$1004,$B$5:$B$1004,11) | N15: =SUMIFS($H$5:$H$1004,$B$5:$B$1004,11)
B16: =IFERROR(MONTH($A16),"") | G16: =IFERROR(($E16-$D16)*24-$F16,"") | L16: 12 | M16: =SUMIFS($G$5:$G$1004,$B$5:$B$1004,12) | N16: =SUMIFS($H$5:$H$1004,$B$5:$B$1004,12)
B17: =IFERROR(MONTH($A17),"") | G17: =IFERROR(($E17-$D17)*24-$F17,"") | L17: 年計 | M17: =SUM(M5:M16) | N17: =SUM(N5:N16)
B18: =IFERROR(MONTH($A18),"") | G18: =IFERROR(($E18-$D18)*24-$F18,"")
B19: =IFERROR(MONTH($A19),"") | G19: =IFERROR(($E19-$D19)*24-$F19,"")
B20: =IFERROR(MONTH($A20),"") | G20: =IFERROR(($E20-$D20)*24-$F20,"")
B21: =IFERROR(MONTH($A21),"") | G21: =IFERROR(($E21-$D21)*24-$F21,"")
B22: =IFERROR(MONTH($A22),"") | G22: =IFERROR(($E22-$D22)*24-$F22,"")
B23: =IFERROR(MONTH($A23),"") | G23: =IFERROR(($E23-$D23)*24-$F23,"")
B24: =IFERROR(MONTH($A24),"") | G24: =IFERROR(($E24-$D24)*24-$F24,"")
B25: =IFERROR(MONTH($A25),"") | G25: =IFERROR(($E25-$D25)*24-$F25,"")
B26: =IFERROR(MONTH($A26),"") | G26: =IFERROR(($E26-$D26)*24-$F26,"")
B27: =IFERROR(MONTH($A27),"") | G27: =IFERROR(($E27-$D27)*24-$F27,"")
B28: =IFERROR(MONTH($A28),"") | G28: =IFERROR(($E28-$D28)*24-$F28,"")
B29: =IFERROR(MONTH($A29),"") | G29: =IFERROR(($E29-$D29)*24-$F29,"")
... B1004: =IFERROR(MONTH($A1004),"") | G1004: =IFERROR(($E1004-$D1004)*24-$F1004,"")

Sheet メモ・変更履歴
A1: メモ・変更履歴
A2: このスプレッドシートに手を入れたら1行足すこと。元に戻せるようにしておくのが目的です。
A4: 日付 | B4: 変更したタブ | C4: 変更内容 | D4: 変更した人 | E4: 元に戻す方法 | F4: バックアップの場所
A5: 46278 | B5: 全タブ | C5: 2027年度版を新規作成（tools/build-sheet-2027.py で生成） | D5: CMO配下スレッド | E5: 同スクリプトを再実行すれば同じものが出ます | F5: リポジトリ one-marketing / spreadsheet/2027/
A6: 46278 | B6: ◯月_支出成績 | C6: 月次P/Lを経費入力表の右（M列）へ移動。2026年版は経費行を足すとP/Lがずれていた（6月+19行・7月+33行） | D6: CMO配下スレッド | E6: — | F6: —
A7: 46278 | B7: ◯月_支出成績 | C7: 科目に 保険料・通信費・外注費 を追加。人件費を「現場人件費(原価)」と「固定給(販管費)」に分割 | D7: CMO配下スレッド | E7: — | F7: —
A8: 46278 | B8: ◯月_支出成績 | C8: ロイヤリティの二重計上を解消。P/Lの1か所だけで数える（15行目で引いて19行目で足す） | D8: CMO配下スレッド | E8: — | F8: —
A9: 46278 | B9: ◯月_売上顧客 | C9: 列を追加：流入元の識別子(?src=)／施工担当。④自社ネット新規を機械で数えられるようにした | D9: CMO配下スレッド | E9: — | F9: —
A10: 46278 | B10: 年間成績 | C10: 和真配分の行を削除し、「対計画の差額」「累計の対計画の差額」を追加 | D10: CMO配下スレッド | E10: — | F10: —
A11: 46293 | B11: ◯月_売上顧客 | C11: 列を追加：紹介者（顧客ID）。紹介カードで『紹介した方に次回1,000円割引』を運用するのに、誰の紹介かを記録する列がどこにも無かったため（cmo 20260927-01）。入れるのは紹介した方の顧客ID（顧客管理台帳のA列）。台帳で見つからなければ氏名のあとに（未照合）と書く。予約ページの受け口は `紹介者`（?src=shokai）。4行目に『紹介 ◯件』の自動集計。法人が個人客を紹介する案件は従来どおり顧客管理台帳の『紹介者（法人名など）』で、紹介料の対象。こちらとは別 | D11: 経営企画室 | E11: — | F11: —
A12: 46291 | B12: 選択肢マスター（流入経路） | C12: 「広告」を追加し、④自社ネット新規の数え方（L_NET_NEW）にも入れた。検索広告が2026-09-20に配信を始めたのに、2027年版の選択肢に無く、④に数えられない状態だった（作り落とし）。予約ページ・GBP予約ボタンなど『入口の仕組み』は流入経路ではなく『流入元の識別子(?src=)』列で見る | D12: 経営企画室 | E12: — | F12: —
A13: 46286 | B13: 年間成績・ダッシュボード・◯月_売上顧客 | C13: 「自社／本舗」で見る行を追加（年間成績 56〜58行・ダッシュボード29行）。ブロック①〜⑤は流入経路で切っていて自社と本舗が混ざるため。2026年は1〜9月で自社+26%（¥8,627,308）・本舗−27%（¥3,729,583）と中身が別物だった。月次タブの4行目に『自社 ◯円』『本舗 ◯円』の自動集計を足してある（列の追加ではなく空きセルの利用） | D13: 経営企画室 | E13: — | F13: —
A14: 46282 | B14: 提携先_パイプライン | C14: ①列を追加：最終接触日・接触回数(累計)。提携先1社に何回接触して1件受注できるかが、どこにも記録されていなかったため（2026年の台帳には接触の記録が無い）。②目標を「2社→4社」から「アクティブ10社→12/15/18社」に修正。2社は2026-09-14にオーナーが訂正した古い数字。③空室清掃の記載を削除（オーナー決定 2026-09-14「完全なる悪手」）。④ダッシュボードの参照列もE→Gへ追従（ステージ列が移動したため） | D14: 経営企画室 | E14: — | F14: —
A15: 46282 | B15: ◯月_売上顧客（12タブ） | C15: 列を追加：受注日（施工日付の隣）。4行目に「受注→施工 平均◯日」が自動で出る。2026年の台帳は施工日付しか無く、受注が止まったのかリードタイムが短いだけなのかを区別できなかった。生成スクリプトから作り直し、追加の前後で集計値が変わらないことを機械で確認済み | D15: 経営企画室 | E15: — | F15: —
A210: 【このスプレッドシートを直すときの3原則】
A211: 1. 過去の実績データを書き換えない（施工日付・売上・氏名・住所・メニュー等の記録）
A212: 2. 変更前にバックアップを取る（Driveでコピー）
A213: 3. 変更履歴を残す（この表 または docs/sheet-changelog.md）
A215: この3つを守るなら、集計タブ・入力規則・書式の変更や新規タブの追加は、確認を取らずに進めてよい（オーナー方針）。

Sheet 選択肢マスター
A1: 売上種類 | B1: 流入経路 | C1: 実施メニュー | D1: 施工担当 | E1: 早期予約提案 | F1: フォローコール | G1: 入金経路 | H1: ＯＨ打診 | I1: 本舗ロイ区分 | J1: TRUE/FALSE | K1: 科目 | L1: TODO状態 | M1: TODO優先度 | N1: 提携ステージ | O1: 協力業者 契約形態 | P1: 協力業者 品質 | Q1: Web予約 状態 | R1: 再販 案内状況 | S1: 再販 手段 | T1: 名義 | U1: 送信系統 | V1: 勤怠 区分 | W1: 広告 段 | X1: 広告 判定 | Y1: ④自社ネット新規に数える流入経路 | AA1: 【このタブは全タブのプルダウンの元データです。並べ替え・行削除をしないこと。
A2: One Hitter | B2: リピート | C2: エアコン(ノーマル) | D2: 和真 | E2: 未記録 | F2: 未記録 | G2: 現金 | H2: 未記録 | I2: 38% | J2: TRUE | K2: 交通費 | L2: 未着手 | M2: 高 | N2: リスト化 | O2: 歩合(売価%) | P2: 良 | Q2: 未対応 | R2: 未案内 | S2: SMS | T2: 自社 | U2: 自社 | V2: 現場 | W2: 段0（テスト） | X2: 次の段へ上がる | Y2: HP | AA2: 選択肢を足すときは、列のいちばん下に追記してから、使う側のタブの入力規則の範囲を伸ばしてください】
A3: 本舗 | B3: 早期予約 | C3: エアコン(ロボ) | D3: 新人 | E3: 提案済み | F3: 実施 | G3: (OH)クレカ | H3: 打診済み | I3: 10% | J3: FALSE | K3: 保険料 | L3: 進行中 | M3: 中 | N3: 接触済み | O3: 固定単価(メニュー別) | P3: 可 | Q3: 連絡済み | R3: 送信済 | S3: 公式LINE | T3: 本舗 | U3: 本舗 | V3: 移動 | W3: 段1 | X3: 据え置き | Y3: LP
B4: 楽ラクーン | C4: 浴室 | D4: 協力業者A | E4: 成約 | F4: 不通 | G4: (OH)QR決済 | H4: 成約 | I4: 個別ロイ | K4: 通信費 | L4: 完了 | M4: 低 | N4: 商談中 | O4: 日当 | P4: 要改善 | Q4: 日程確定 | R4: 反応あり | S4: 電話 | U4: 連絡不可 | V4: 事務 | W4: 段2（繁忙期） | X4: 段を下げる | Y4: SNS
B5: 業務提携 | C5: 換気扇 | D5: 協力業者B | E5: 見送り | F5: 対象外 | G5: (本舗)クレカ | H5: 見送り | I5: ロイ相殺 | K5: 広告費 | L5: 対象外 | N5: 条件提示 | O5: 未契約 | Q5: 受注 | R5: 受注 | S5: DM | V5: 研修 | W5: 段3（年末） | X5: 止める | Y5: GBP(地図検索)
B6: スケジュールマッチング | C6: 天カセ | D6: 協力業者C | G6: (本舗)QR決済 | K6: 耐久品 | N6: 成約 | Q6: 不成立 | R6: 対象外 | S6: メール | V6: 休み | W6: 出さない | X6: 未判定 | Y6: 公式LINE
B7: おそうじ定期便 | C7: おそうじ定期便 | D7: その他 | G7: 請求書(翌月) | K7: 備品 | N7: 見送り | Y7: アフィリエイト
B8: 紹介 | C8: 空室 | G8: 請求書(2か月後) | K8: 個別ロイ | Y8: LINE/SMS再販
B9: 営業 | C9: まるごと(備考に内容) | K9: 現場人件費(原価) | Y9: SMS
B10: チラシ(OH) | C10: 洗濯機(ノーマル) | K10: 固定給(販管費) | Y10: 広告
B11: HP | C11: 洗濯機(ドラム) | K11: 外注費
B12: 入札案件 | C12: 定期清掃 | K12: その他(備考へ)
B13: チラシ(本舗) | C13: 業務用エアコン1方向
B14: SMS | C14: 追焚配管
B15: LP | C15: 排水溝高圧洗浄
B16: SNS | C16: トイレ
B17: GBP(地図検索)
B18: 公式LINE
B19: アフィリエイト
B20: LINE/SMS再販
B21: ギフト
B22: 広告
B23: その他
